Workbook

Sheet Lista Movimenti
A1: Nome | B1: Categoria | C1: Importo | D1: Data | E1: Tipo
B2: ✈️ Viaggi/Vacanze | C2: 500 | D2: 46023 | E2: Risparmio
B3: 🌟 Altro extra | C3: 50 | D3: 46023 | E3: Risparmio
B4: 🍔 Cibo fuori | C4: 64 | D4: 46023 | E4: Spesa
B5: 🍲 Cibo/Spesa | C5: 125 | D5: 46023 | E5: Spesa
B6: 🎁 Regali | C6: 200 | D6: 46023 | E6: Spesa
B7: 🎫 Abbonamenti | C7: 9 | D7: 46023 | E7: Spesa
B8: 🎬 Intrattenimento | C8: 36 | D8: 46023 | E8: Spesa
B9: 🏋️ Palestra e affini | C9: 29 | D9: 46023 | E9: Spesa
B10: 🏠 Casa | C10: 230 | D10: 46023 | E10: Spesa
B11: 👕 Vestiti | C11: 112 | D11: 46023 | E11: Spesa
B12: 💅 Cura personale | C12: 100 | D12: 46023 | E12: Spesa
B13: 📚 Cultura | C13: 32 | D13: 46023 | E13: Spesa
B14: 📱 Telefono | C14: 12 | D14: 46023 | E14: Spesa
B15: 🤑 Stipendio | C15: 1500 | D15: 46023
B16: 🪙 Altre entrate | C16: 50 | D16: 46023
B17: 🚌 Trasporti | C17: 60 | D17: 46023 | E17: Spesa
B18: 🚑 Sanità | C18: 100 | D18: 46023 | E18: Spesa
B19: ✈️ Viaggi/Vacanze | C19: 200 | D19: 46054 | E19: Risparmio
B20: 🌟 Altro extra | C20: 112 | D20: 46054 | E20: Spesa
B21: 🍔 Cibo fuori | C21: 79 | D21: 46054 | E21: Spesa
B22: 🍲 Cibo/Spesa | D22: 46054
B23: 🎁 Regali | D23: 46054
B24: 🎫 Abbonamenti | D24: 46054
B25: 🎬 Intrattenimento | D25: 46054
B26: 🏋️ Palestra e affini | D26: 46054
B27: 🏠 Casa | C27: 780 | D27: 46054 | E27: Spesa
B28: 👕 Vestiti | D28: 46054
B29: 💅 Cura personale | D29: 46054
B30: 📚 Cultura | D30: 46054
B31: 📱 Telefono | D31: 46054
B32: 🤑 Stipendio | C32: 1400 | D32: 46054
B33: 🪙 Altre entrate | D33: 46054
B34: 🚌 Trasporti | D34: 46054
B35: 🚑 Sanità | D35: 46054
B36: ✈️ Viaggi/Vacanze | C36: 350 | D36: 46082 | E36: Spesa
B37: 🌟 Altro extra | D37: 46082
B38: 🍔 Cibo fuori | D38: 46082
B39: 🍲 Cibo/Spesa | D39: 46082
B40: 🎁 Regali | D40: 46082
B41: 🎫 Abbonamenti | D41: 46082
B42: 🎬 Intrattenimento | D42: 46082
B43: 🏋️ Palestra e affini | D43: 46082
B44: 🏠 Casa | D44: 46082
B45: 👕 Vestiti | D45: 46082
B46: 💅 Cura personale | C46: 30 | D46: 46082 | E46: Spesa
B47: 📚 Cultura | D47: 46082
B48: 📱 Telefono | D48: 46082
B49: 🤑 Stipendio | C49: 1500 | D49: 46082
B50: 🪙 Altre entrate | C50: 10 | D50: 46082
B51: 🚌 Trasporti | D51: 46082
B52: 🚑 Sanità | D52: 46082
B53: ✈️ Viaggi/Vacanze | D53: 46113 | E53: Spesa
B54: 🌟 Altro extra | C54: 54 | D54: 46113
B55: 🍔 Cibo fuori | D55: 46113
B56: 🍲 Cibo/Spesa | D56: 46113
B57: 🎁 Regali | D57: 46113
B58: 🎫 Abbonamenti | C58: 32 | D58: 46113 | E58: Spesa
B59: 🎬 Intrattenimento | D59: 46113
B60: 🏋️ Palestra e affini | D60: 46113
B61: 🏠 Casa | C61: 300 | D61: 46113 | E61: Risparmio
B62: 👕 Vestiti | D62: 46113
B63: 💅 Cura personale | D63: 46113
B64: 📚 Cultura | D64: 46113
B65: 📱 Telefono | D65: 46113
B66: 🤑 Stipendio | C66: 1300 | D66: 46113
B67: 🪙 Altre entrate | D67: 46113
B68: 🚌 Trasporti | D68: 46113
B69: 🚑 Sanità | D69: 46113
B70: 🍲 Cibo/Spesa | C70: 300 | D70: 46140 | E70: Spesa
B71: ✈️ Viaggi/Vacanze | C71: 300 | D71: 46143 | E71: Spesa
B72: 🌟 Altro extra | D72: 46143
B73: 🍔 Cibo fuori | D73: 46143
B74: 🍲 Cibo/Spesa | D74: 46143
B75: 🎁 Regali | C75: 50 | D75: 46143 | E75: Spesa
B76: 🎫 Abbonamenti | D76: 46143
B77: 🎬 Intrattenimento | C77: 24 | D77: 46143 | E77: Spesa
B78: 🏋️ Palestra e affini | D78: 46143
B79: 🏠 Casa | C79: 500 | D79: 46143 | E79: Risparmio
B80: 👕 Vestiti | D80: 46143
B81: 💅 Cura personale | D81: 46143
B82: 📚 Cultura | D82: 46143
B83: 📱 Telefono | D83: 46143
B84: 🤑 Stipendio | C84: 1230 | D84: 46143
B85: 🪙 Altre entrate | C85: 30 | D85: 46143
B86: 🚌 Trasporti | D86: 46143
B87: 🚑 Sanità | D87: 46143
A88: Dentista | B88: 🚑 Sanità | C88: 350 | D88: 46143
B89: ✈️ Viaggi/Vacanze | D89: 46174 | E89: Spesa
B90: 🌟 Altro extra | D90: 46174
B91: 🍔 Cibo fuori | D91: 46174
B92: 🍲 Cibo/Spesa | D92: 46174
B93: 🎁 Regali | D93: 46174
B94: 🎫 Abbonamenti | D94: 46174
B95: 🎬 Intrattenimento | C95: 22 | D95: 46174 | E95: Spesa
B96: 🏋️ Palestra e affini | D96: 46174
B97: 🏠 Casa | D97: 46174
B98: 👕 Vestiti | D98: 46174
B99: 💅 Cura personale | D99: 46174
B100: 📚 Cultura | D100: 46174
...

Sheet ANNO
A3: Categoria | B3: Gennaio | C3: Febbraio | D3: Marzo | E3: Aprile | F3: Maggio | G3: Giugno | H3: Luglio | I3: Agosto | J3: Settembre | K3: Ottobre | L3: Novembre | M3: Dicembre | N3: Media | O3: Obiettivo | P3: Totale Annuo
A4: 🤑 Stipendio | B4: =SUMIFS('Lista Movimenti'!C:C, 'Lista Movimenti'!B:B, A4,'Lista Movimenti'!D:D, ">=01/01/2026", 'Lista Movimenti'!D:D, "<=31/01/2026") -> 1500 | C4: =SUMIFS('Lista Movimenti'!$C:$C, 'Lista Movimenti'!$B:$B, $A4, 'Lista Movimenti'!$D:$D, ">="&DATE(2026,2,1), 'Lista Movimenti'!$D:$D, "<="&DATE(2026,2,28)) -> 1400 | D4: =SUMIFS('Lista Movimenti'!$C:$C, 'Lista Movimenti'!$B:$B, $A4, 'Lista Movimenti'!$D:$D, ">="&DATE(2026,3,1), 'Lista Movimenti'!$D:$D, "<="&DATE(2026,3,31)) -> 1500 | E4: =SUMIFS('Lista Movimenti'!$C:$C, 'Lista Movimenti'!$B:$B, $A4, 'Lista Movimenti'!$D:$D, ">="&DATE(2026,4,1), 'Lista Movimenti'!$D:$D, "<="&DATE(2026,4,30)) -> 1300 | F4: =SUMIFS('Lista Movimenti'!$C:$C, 'Lista Movimenti'!$B:$B, $A4, 'Lista Movimenti'!$D:$D, ">="&DATE(2026,5,1), 'Lista Movimenti'!$D:$D, "<="&DATE(2026,5,31)) -> 1230 | G4: =SUMIFS('Lista Movimenti'!$C:$C, 'Lista Movimenti'!$B:$B, $A4, 'Lista Movimenti'!$D:$D, ">="&DATE(2026,6,1), 'Lista Movimenti'!$D:$D, "<="&DATE(2026,6,30)) -> 1450 | H4: =SUMIFS('Lista Movimenti'!$C:$C, 'Lista Movimenti'!$B:$B, $A4, 'Lista Movimenti'!$D:$D, ">="&DATE(2026,7,1), 'Lista Movimenti'!$D:$D, "<="&DATE(2026,7,31)) -> 1000 | I4: =SUMIFS('Lista Movimenti'!$C:$C, 'Lista Movimenti'!$B:$B, $A4, 'Lista Movimenti'!$D:$D, ">="&DATE(2026,8,1), 'Lista Movimenti'!$D:$D, "<="&DATE(2026,8,31)) -> 1250 | J4: =SUMIFS('Lista Movimenti'!$C:$C, 'Lista Movimenti'!$B:$B, $A4, 'Lista Movimenti'!$D:$D, ">="&DATE(2026,9,1), 'Lista Movimenti'!$D:$D, "<="&DATE(2026,9,30)) -> 1500 | K4: =SUMIFS('Lista Movimenti'!$C:$C, 'Lista Movimenti'!$B:$B, $A4, 'Lista Movimenti'!$D:$D, ">="&DATE(2026,10,1), 'Lista Movimenti'!$D:$D, "<="&DATE(2026,10,31)) -> 1600 | L4: =SUMIFS('Lista Movimenti'!$C:$C, 'Lista Movimenti'!$B:$B, $A4, 'Lista Movimenti'!$D:$D, ">="&DATE(2026,11,1), 'Lista Movimenti'!$D:$D, "<="&DATE(2026,11,30)) -> 1150 | M4: =SUMIFS('Lista Movimenti'!$C:$C, 'Lista Movimenti'!$B:$B, $A4, 'Lista Movimenti'!$D:$D, ">="&DATE(2026,12,1), 'Lista Movimenti'!$D:$D, "<="&DATE(2026,12,31)) -> 1450 | N4: =AVERAGE(B4:M4) -> 1360.8333 | P4: =SUM(B4:M4) -> 16330
A5: 🪙 Altre entrate | B5: =SUMIFS('Lista Movimenti'!C:C, 'Lista Movimenti'!B:B, A5,'Lista Movimenti'!D:D, ">=01/01/2026", 'Lista Movimenti'!D:D, "<=31/01/2026") -> 50 | C5: =SUMIFS('Lista Movimenti'!$C:$C, 'Lista Movimenti'!$B:$B, $A5, 'Lista Movimenti'!$D:$D, ">="&DATE(2026,2,1), 'Lista Movimenti'!$D:$D, "<="&DATE(2026,2,28)) -> 0 | D5: =SUMIFS('Lista Movimenti'!$C:$C, 'Lista Movimenti'!$B:$B, $A5, 'Lista Movimenti'!$D:$D, ">="&DATE(2026,3,1), 'Lista Movimenti'!$D:$D, "<="&DATE(2026,3,31)) -> 10 | E5: =SUMIFS('Lista Movimenti'!$C:$C, 'Lista Movimenti'!$B:$B, $A5, 'Lista Movimenti'!$D:$D, ">="&DATE(2026,4,1), 'Lista Movimenti'!$D:$D, "<="&DATE(2026,4,30)) -> 0 | F5: =SUMIFS('Lista Movimenti'!$C:$C, 'Lista Movimenti'!$B:$B, $A5, 'Lista Movimenti'!$D:$D, ">="&DATE(2026,5,1), 'Lista Movimenti'!$D:$D, "<="&DATE(2026,5,31)) -> 30 | G5: =SUMIFS('Lista Movimenti'!$C:$C, 'Lista Movimenti'!$B:$B, $A5, 'Lista Movimenti'!$D:$D, ">="&DATE(2026,6,1), 'Lista Movimenti'!$D:$D, "<="&DATE(2026,6,30)) -> 0 | H5: =SUMIFS('Lista Movimenti'!$C:$C, 'Lista Movimenti'!$B:$B, $A5, 'Lista Movimenti'!$D:$D, ">="&DATE(2026,7,1), 'Lista Movimenti'!$D:$D, "<="&DATE(2026,7,31)) -> 0 | I5: =SUMIFS('Lista Movimenti'!$C:$C, 'Lista Movimenti'!$B:$B, $A5, 'Lista Movimenti'!$D:$D, ">="&DATE(2026,8,1), 'Lista Movimenti'!$D:$D, "<="&DATE(2026,8,31)) -> 60 | J5: =SUMIFS('Lista Movimenti'!$C:$C, 'Lista Movimenti'!$B:$B, $A5, 'Lista Movimenti'!$D:$D, ">="&DATE(2026,9,1), 'Lista Movimenti'!$D:$D, "<="&DATE(2026,9,30)) -> 0 | K5: =SUMIFS('Lista Movimenti'!$C:$C, 'Lista Movimenti'!$B:$B, $A5, 'Lista Movimenti'!$D:$D, ">="&DATE(2026,10,1), 'Lista Movimenti'!$D:$D, "<="&DATE(2026,10,31)) -> 20 | L5: =SUMIFS('Lista Movimenti'!$C:$C, 'Lista Movimenti'!$B:$B, $A5, 'Lista Movimenti'!$D:$D, ">="&DATE(2026,11,1), 'Lista Movimenti'!$D:$D, "<="&DATE(2026,11,30)) -> 0 | M5: =SUMIFS('Lista Movimenti'!$C:$C, 'Lista Movimenti'!$B:$B, $A5, 'Lista Movimenti'!$D:$D, ">="&DATE(2026,12,1), 'Lista Movimenti'!$D:$D, "<="&DATE(2026,12,31)) -> 0 | N5: =AVERAGE(B5:M5) -> 14.166667 | P5: =SUM(B5:M5) -> 170
B6: =SUMIFS('Lista Movimenti'!C:C, 'Lista Movimenti'!B:B, A6,'Lista Movimenti'!D:D, ">=01/01/2026", 'Lista Movimenti'!D:D, "<=31/01/2026") -> 0 | C6: =SUMIFS('Lista Movimenti'!$C:$C, 'Lista Movimenti'!$B:$B, $A6, 'Lista Movimenti'!$D:$D, ">="&DATE(2026,2,1), 'Lista Movimenti'!$D:$D, "<="&DATE(2026,2,28)) -> 0 | D6: =SUMIFS('Lista Movimenti'!$C:$C, 'Lista Movimenti'!$B:$B, $A6, 'Lista Movimenti'!$D:$D, ">="&DATE(2026,3,1), 'Lista Movimenti'!$D:$D, "<="&DATE(2026,3,31)) -> 0 | E6: =SUMIFS('Lista Movimenti'!$C:$C, 'Lista Movimenti'!$B:$B, $A6, 'Lista Movimenti'!$D:$D, ">="&DATE(2026,4,1), 'Lista Movimenti'!$D:$D, "<="&DATE(2026,4,30)) -> 0 | F6: =SUMIFS('Lista Movimenti'!$C:$C, 'Lista Movimenti'!$B:$B, $A6, 'Lista Movimenti'!$D:$D, ">="&DATE(2026,5,1), 'Lista Movimenti'!$D:$D, "<="&DATE(2026,5,31)) -> 0 | G6: =SUMIFS('Lista Movimenti'!$C:$C, 'Lista Movimenti'!$B:$B, $A6, 'Lista Movimenti'!$D:$D, ">="&DATE(2026,6,1), 'Lista Movimenti'!$D:$D, "<="&DATE(2026,6,30)) -> 0 | H6: =SUMIFS('Lista Movimenti'!$C:$C, 'Lista Movimenti'!$B:$B, $A6, 'Lista Movimenti'!$D:$D, ">="&DATE(2026,7,1), 'Lista Movimenti'!$D:$D, "<="&DATE(2026,7,31)) -> 0 | I6: =SUMIFS('Lista Movimenti'!$C:$C, 'Lista Movimenti'!$B:$B, $A6, 'Lista Movimenti'!$D:$D, ">="&DATE(2026,8,1), 'Lista Movimenti'!$D:$D, "<="&DATE(2026,8,31)) -> 0 | J6: =SUMIFS('Lista Movimenti'!$C:$C, 'Lista Movimenti'!$B:$B, $A6, 'Lista Movimenti'!$D:$D, ">="&DATE(2026,9,1), 'Lista Movimenti'!$D:$D, "<="&DATE(2026,9,30)) -> 0 | K6: =SUMIFS('Lista Movimenti'!$C:$C, 'Lista Movimenti'!$B:$B, $A6, 'Lista Movimenti'!$D:$D, ">="&DATE(2026,10,1), 'Lista Movimenti'!$D:$D, "<="&DATE(2026,10,31)) -> 0 | L6: =SUMIFS('Lista Movimenti'!$C:$C, 'Lista Movimenti'!$B:$B, $A6, 'Lista Movimenti'!$D:$D, ">="&DATE(2026,11,1), 'Lista Movimenti'!$D:$D, "<="&DATE(2026,11,30)) -> 0 | M6: =SUMIFS('Lista Movimenti'!$C:$C, 'Lista Movimenti'!$B:$B, $A6, 'Lista Movimenti'!$D:$D, ">="&DATE(2026,12,1), 'Lista Movimenti'!$D:$D, "<="&DATE(2026,12,31)) -> 0 | N6: =AVERAGE(B6:M6) -> 0 | P6: =SUM(B6:M6) -> 0
B7: =SUMIFS('Lista Movimenti'!C:C, 'Lista Movimenti'!B:B, A7,'Lista Movimenti'!D:D, ">=01/01/2026", 'Lista Movimenti'!D:D, "<=31/01/2026") -> 0 | C7: =SUMIFS('Lista Movimenti'!$C:$C, 'Lista Movimenti'!$B:$B, $A7, 'Lista Movimenti'!$D:$D, ">="&DATE(2026,2,1), 'Lista Movimenti'!$D:$D, "<="&DATE(2026,2,28)) -> 0 | D7: =SUMIFS('Lista Movimenti'!$C:$C, 'Lista Movimenti'!$B:$B, $A7, 'Lista Movimenti'!$D:$D, ">="&DATE(2026,3,1), 'Lista Movimenti'!$D:$D, "<="&DATE(2026,3,31)) -> 0 | E7: =SUMIFS('Lista Movimenti'!$C:$C, 'Lista Movimenti'!$B:$B, $A7, 'Lista Movimenti'!$D:$D, ">="&DATE(2026,4,1), 'Lista Movimenti'!$D:$D, "<="&DATE(2026,4,30)) -> 0 | F7: =SUMIFS('Lista Movimenti'!$C:$C, 'Lista Movimenti'!$B:$B, $A7, 'Lista Movimenti'!$D:$D, ">="&DATE(2026,5,1), 'Lista Movimenti'!$D:$D, "<="&DATE(2026,5,31)) -> 0 | G7: =SUMIFS('Lista Movimenti'!$C:$C, 'Lista Movimenti'!$B:$B, $A7, 'Lista Movimenti'!$D:$D, ">="&DATE(2026,6,1), 'Lista Movimenti'!$D:$D, "<="&DATE(2026,6,30)) -> 0 | H7: =SUMIFS('Lista Movimenti'!$C:$C, 'Lista Movimenti'!$B:$B, $A7, 'Lista Movimenti'!$D:$D, ">="&DATE(2026,7,1), 'Lista Movimenti'!$D:$D, "<="&DATE(2026,7,31)) -> 0 | I7: =SUMIFS('Lista Movimenti'!$C:$C, 'Lista Movimenti'!$B:$B, $A7, 'Lista Movimenti'!$D:$D, ">="&DATE(2026,8,1), 'Lista Movimenti'!$D:$D, "<="&DATE(2026,8,31)) -> 0 | J7: =SUMIFS('Lista Movimenti'!$C:$C, 'Lista Movimenti'!$B:$B, $A7, 'Lista Movimenti'!$D:$D, ">="&DATE(2026,9,1), 'Lista Movimenti'!$D:$D, "<="&DATE(2026,9,30)) -> 0 | K7: =SUMIFS('Lista Movimenti'!$C:$C, 'Lista Movimenti'!$B:$B, $A7, 'Lista Movimenti'!$D:$D, ">="&DATE(2026,10,1), 'Lista Movimenti'!$D:$D, "<="&DATE(2026,10,31)) -> 0 | L7: =SUMIFS('Lista Movimenti'!$C:$C, 'Lista Movimenti'!$B:$B, $A7, 'Lista Movimenti'!$D:$D, ">="&DATE(2026,11,1), 'Lista Movimenti'!$D:$D, "<="&DATE(2026,11,30)) -> 0 | M7: =SUMIFS('Lista Movimenti'!$C:$C, 'Lista Movimenti'!$B:$B, $A7, 'Lista Movimenti'!$D:$D, ">="&DATE(2026,12,1), 'Lista Movimenti'!$D:$D, "<="&DATE(2026,12,31)) -> 0 | N7: =AVERAGE(B7:M7) -> 0 | P7: =SUM(B7:M7) -> 0
A8: Totale Entrate | B8: =SUM(Entrate_Anno[Gennaio]) -> 1550 | C8: =SUM(C4:C7) -> 1400 | D8: =SUM(D4:D7) -> 1510 | E8: =SUM(E4:E7) -> 1300 | F8: =SUM(F4:F7) -> 1260 | G8: =SUM(G4:G7) -> 1450 | H8: =SUM(H4:H7) -> 1000 | I8: =SUM(I4:I7) -> 1310 | J8: =SUM(J4:J7) -> 1500 | ... M8: =SUM(M4:M7) -> 1450 | N8: =AVERAGE(B8:M8) -> 1375 | P8: =SUM(Entrate_Anno[Totale Annuo]) -> 16500
A12: Necessita | B12: Categoria | C12: Gennaio | D12: Febbraio | E12: Marzo | F12: Aprile | G12: Maggio | H12: Giugno | I12: Luglio | J12: Agosto | K12: Settembre | L12: Ottobre | M12: Novembre | N12: Dicembre | O12: Media | P12: Obiettivo | Q12: Totale Annuo
B13: 🏠 Casa | C13: =SUMIFS('Lista Movimenti'!$C:$C, 'Lista Movimenti'!$B:$B, $B13, 'Lista Movimenti'!$E:$E, "Spesa", 'Lista Movimenti'!$D:$D, ">=01/01/2026", 'Lista Movimenti'!$D:$D, "<=31/01/2026") -> 230 | D13: =SUMIFS('Lista Movimenti'!$C:$C, 'Lista Movimenti'!$B:$B, $B13, 'Lista Movimenti'!$E:$E, "Spesa", 'Lista Movimenti'!$D:$D, ">=01/02/2026", 'Lista Movimenti'!$D:$D, "<=28/02/2026") -> 780 | E13: =SUMIFS('Lista Movimenti'!$C:$C, 'Lista Movimenti'!$B:$B, $B13, 'Lista Movimenti'!$E:$E, "Spesa", 'Lista Movimenti'!$D:$D, ">=01/03/2026", 'Lista Movimenti'!$D:$D, "<=31/03/2026") -> 0 | F13: =SUMIFS('Lista Movimenti'!$C:$C, 'Lista Movimenti'!$B:$B, $B13, 'Lista Movimenti'!$E:$E, "Spesa", 'Lista Movimenti'!$D:$D, ">=01/04/2026", 'Lista Movimenti'!$D:$D, "<=30/04/2026") -> 0 | G13: =SUMIFS('Lista Movimenti'!$C:$C, 'Lista Movimenti'!$B:$B, $B13, 'Lista Movimenti'!$E:$E, "Spesa", 'Lista Movimenti'!$D:$D, ">=01/05/2026", 'Lista Movimenti'!$D:$D, "<=31/05/2026") -> 0 | H13: =SUMIFS('Lista Movimenti'!$C:$C, 'Lista Movimenti'!$B:$B, $B13, 'Lista Movimenti'!$E:$E, "Spesa", 'Lista Movimenti'!$D:$D, ">=01/06/2026", 'Lista Movimenti'!$D:$D, "<=30/06/2026") -> 0 | I13: =SUMIFS('Lista Movimenti'!$C:$C, 'Lista Movimenti'!$B:$B, $B13, 'Lista Movimenti'!$E:$E, "Spesa", 'Lista Movimenti'!$D:$D, ">=01/07/2026", 'Lista Movimenti'!$D:$D, "<=31/07/2026") -> 399 | J13: =SUMIFS('Lista Movimenti'!$C:$C, 'Lista Movimenti'!$B:$B, $B13, 'Lista Movimenti'!$E:$E, "Spesa", 'Lista Movimenti'!$D:$D, ">=01/08/2026", 'Lista Movimenti'!$D:$D, "<=31/08/2026") -> 0 | K13: =SUMIFS('Lista Movimenti'!$C:$C, 'Lista Movimenti'!$B:$B, $B13, 'Lista Movimenti'!$E:$E, "Spesa", 'Lista Movimenti'!$D:$D, ">=01/09/2026", 'Lista Movimenti'!$D:$D, "<=30/09/2026") -> 0 | L13: =SUMIFS('Lista Movimenti'!$C:$C, 'Lista Movimenti'!$B:$B, $B13, 'Lista Movimenti'!$E:$E, "Spesa", 'Lista Movimenti'!$D:$D, ">=01/10/2026", 'Lista Movimenti'!$D:$D, "<=31/10/2026") -> 0 | M13: =SUMIFS('Lista Movimenti'!$C:$C, 'Lista Movimenti'!$B:$B, $B13, 'Lista Movimenti'!$E:$E, "Spesa", 'Lista Movimenti'!$D:$D, ">=01/11/2026", 'Lista Movimenti'!$D:$D, "<=30/11/2026") -> 200 | N13: =SUMIFS('Lista Movimenti'!$C:$C, 'Lista Movimenti'!$B:$B, $B13, 'Lista Movimenti'!$E:$E, "Spesa", 'Lista Movimenti'!$D:$D, ">=01/12/2026", 'Lista Movimenti'!$D:$D, "<=31/12/2026") -> 0 | O13: =AVERAGE(C13:N13) -> 134.08333 | P13: 200 | Q13: =SUM(C13:N13) -> 1609
B14: 🍲 Cibo/Spesa | C14: =SUMIFS('Lista Movimenti'!C:C, 'Lista Movimenti'!B:B, B14, 'Lista Movimenti'!E:E, "Spesa", 'Lista Movimenti'!D:D, ">=01/01/2026", 'Lista Movimenti'!D:D, "<=31/01/2026") -> 125 | D14: =SUMIFS('Lista Movimenti'!$C:$C, 'Lista Movimenti'!$B:$B, $B14, 'Lista Movimenti'!$E:$E, "Spesa", 'Lista Movimenti'!$D:$D, ">=01/02/2026", 'Lista Movimenti'!$D:$D, "<=28/02/2026") -> 0 | E14: =SUMIFS('Lista Movimenti'!$C:$C, 'Lista Movimenti'!$B:$B, $B14, 'Lista Movimenti'!$E:$E, "Spesa", 'Lista Movimenti'!$D:$D, ">=01/03/2026", 'Lista Movimenti'!$D:$D, "<=31/03/2026") -> 0 | F14: =SUMIFS('Lista Movimenti'!$C:$C, 'Lista Movimenti'!$B:$B, $B14, 'Lista Movimenti'!$E:$E, "Spesa", 'Lista Movimenti'!$D:$D, ">=01/04/2026", 'Lista Movimenti'!$D:$D, "<=30/04/2026") -> 300 | G14: =SUMIFS('Lista Movimenti'!$C:$C, 'Lista Movimenti'!$B:$B, $B14, 'Lista Movimenti'!$E:$E, "Spesa", 'Lista Movimenti'!$D:$D, ">=01/05/2026", 'Lista Movimenti'!$D:$D, "<=31/05/2026") -> 0 | H14: =SUMIFS('Lista Movimenti'!$C:$C, 'Lista Movimenti'!$B:$B, $B14, 'Lista Movimenti'!$E:$E, "Spesa", 'Lista Movimenti'!$D:$D, ">=01/06/2026", 'Lista Movimenti'!$D:$D, "<=30/06/2026") -> 0 | I14: =SUMIFS('Lista Movimenti'!$C:$C, 'Lista Movimenti'!$B:$B, $B14, 'Lista Movimenti'!$E:$E, "Spesa", 'Lista Movimenti'!$D:$D, ">=01/07/2026", 'Lista Movimenti'!$D:$D, "<=31/07/2026") -> 200 | J14: =SUMIFS('Lista Movimenti'!$C:$C, 'Lista Movimenti'!$B:$B, $B14, 'Lista Movimenti'!$E:$E, "Spesa", 'Lista Movimenti'!$D:$D, ">=01/08/2026", 'Lista Movimenti'!$D:$D, "<=31/08/2026") -> 0 | K14: =SUMIFS('Lista Movimenti'!$C:$C, 'Lista Movimenti'!$B:$B, $B14, 'Lista Movimenti'!$E:$E, "Spesa", 'Lista Movimenti'!$D:$D, ">=01/09/2026", 'Lista Movimenti'!$D:$D, "<=30/09/2026") -> 0 | L14: =SUMIFS('Lista Movimenti'!$C:$C, 'Lista Movimenti'!$B:$B, $B14, 'Lista Movimenti'!$E:$E, "Spesa", 'Lista Movimenti'!$D:$D, ">=01/10/2026", 'Lista Movimenti'!$D:$D, "<=31/10/2026") -> 100 | M14: =SUMIFS('Lista Movimenti'!$C:$C, 'Lista Movimenti'!$B:$B, $B14, 'Lista Movimenti'!$E:$E, "Spesa", 'Lista Movimenti'!$D:$D, ">=01/11/2026", 'Lista Movimenti'!$D:$D, "<=30/11/2026") -> 0 | N14: =SUMIFS('Lista Movimenti'!$C:$C, 'Lista Movimenti'!$B:$B, $B14, 'Lista Movimenti'!$E:$E, "Spesa", 'Lista Movimenti'!$D:$D, ">=01/12/2026", 'Lista Movimenti'!$D:$D, "<=31/12/2026") -> 0 | O14: =AVERAGE(C14:N14) -> 60.416667 | P14: 280 | Q14: =SUM(C14:N14) -> 725
B15: 🚑 Sanità | C15: =SUMIFS('Lista Movimenti'!C:C, 'Lista Movimenti'!B:B, B15, 'Lista Movimenti'!E:E, "Spesa", 'Lista Movimenti'!D:D, ">=01/01/2026", 'Lista Movimenti'!D:D, "<=31/01/2026") -> 100 | D15: =SUMIFS('Lista Movimenti'!$C:$C, 'Lista Movimenti'!$B:$B, $B15, 'Lista Movimenti'!$E:$E, "Spesa", 'Lista Movimenti'!$D:$D, ">=01/02/2026", 'Lista Movimenti'!$D:$D, "<=28/02/2026") -> 0 | E15: =SUMIFS('Lista Movimenti'!$C:$C, 'Lista Movimenti'!$B:$B, $B15, 'Lista Movimenti'!$E:$E, "Spesa", 'Lista Movimenti'!$D:$D, ">=01/03/2026", 'Lista Movimenti'!$D:$D, "<=31/03/2026") -> 0 | F15: =SUMIFS('Lista Movimenti'!$C:$C, 'Lista Movimenti'!$B:$B, $B15, 'Lista Movimenti'!$E:$E, "Spesa", 'Lista Movimenti'!$D:$D, ">=01/04/2026", 'Lista Movimenti'!$D:$D, "<=30/04/2026") -> 0 | G15: =SUMIFS('Lista Movimenti'!$C:$C, 'Lista Movimenti'!$B:$B, $B15, 'Lista Movimenti'!$E:$E, "Spesa", 'Lista Movimenti'!$D:$D, ">=01/05/2026", 'Lista Movimenti'!$D:$D, "<=31/05/2026") -> 0 | H15: =SUMIFS('Lista Movimenti'!$C:$C, 'Lista Movimenti'!$B:$B, $B15, 'Lista Movimenti'!$E:$E, "Spesa", 'Lista Movimenti'!$D:$D, ">=01/06/2026", 'Lista Movimenti'!$D:$D, "<=30/06/2026") -> 0 | I15: =SUMIFS('Lista Movimenti'!$C:$C, 'Lista Movimenti'!$B:$B, $B15, 'Lista Movimenti'!$E:$E, "Spesa", 'Lista Movimenti'!$D:$D, ">=01/07/2026", 'Lista Movimenti'!$D:$D, "<=31/07/2026") -> 0 | J15: =SUMIFS('Lista Movimenti'!$C:$C, 'Lista Movimenti'!$B:$B, $B15, 'Lista Movimenti'!$E:$E, "Spesa", 'Lista Movimenti'!$D:$D, ">=01/08/2026", 'Lista Movimenti'!$D:$D, "<=31/08/2026") -> 0 | K15: =SUMIFS('Lista Movimenti'!$C:$C, 'Lista Movimenti'!$B:$B, $B15, 'Lista Movimenti'!$E:$E, "Spesa", 'Lista Movimenti'!$D:$D, ">=01/09/2026", 'Lista Movimenti'!$D:$D, "<=30/09/2026") -> 0 | L15: =SUMIFS('Lista Movimenti'!$C:$C, 'Lista Movimenti'!$B:$B, $B15, 'Lista Movimenti'!$E:$E, "Spesa", 'Lista Movimenti'!$D:$D, ">=01/10/2026", 'Lista Movimenti'!$D:$D, "<=31/10/2026") -> 0 | M15: =SUMIFS('Lista Movimenti'!$C:$C, 'Lista Movimenti'!$B:$B, $B15, 'Lista Movimenti'!$E:$E, "Spesa", 'Lista Movimenti'!$D:$D, ">=01/11/2026", 'Lista Movimenti'!$D:$D, "<=30/11/2026") -> 0 | N15: =SUMIFS('Lista Movimenti'!$C:$C, 'Lista Movimenti'!$B:$B, $B15, 'Lista Movimenti'!$E:$E, "Spesa", 'Lista Movimenti'!$D:$D, ">=01/12/2026", 'Lista Movimenti'!$D:$D, "<=31/12/2026") -> 0 | O15: =AVERAGE(C15:N15) -> 8.3333333 | P15: 50 | Q15: =SUM(C15:N15) -> 100
B16: 🏋️ Palestra e affini | C16: =SUMIFS('Lista Movimenti'!C:C, 'Lista Movimenti'!B:B, B16, 'Lista Movimenti'!E:E, "Spesa", 'Lista Movimenti'!D:D, ">=01/01/2026", 'Lista Movimenti'!D:D, "<=31/01/2026") -> 29 | D16: =SUMIFS('Lista Movimenti'!$C:$C, 'Lista Movimenti'!$B:$B, $B16, 'Lista Movimenti'!$E:$E, "Spesa", 'Lista Movimenti'!$D:$D, ">=01/02/2026", 'Lista Movimenti'!$D:$D, "<=28/02/2026") -> 0 | E16: =SUMIFS('Lista Movimenti'!$C:$C, 'Lista Movimenti'!$B:$B, $B16, 'Lista Movimenti'!$E:$E, "Spesa", 'Lista Movimenti'!$D:$D, ">=01/03/2026", 'Lista Movimenti'!$D:$D, "<=31/03/2026") -> 0 | F16: =SUMIFS('Lista Movimenti'!$C:$C, 'Lista Movimenti'!$B:$B, $B16, 'Lista Movimenti'!$E:$E, "Spesa", 'Lista Movimenti'!$D:$D, ">=01/04/2026", 'Lista Movimenti'!$D:$D, "<=30/04/2026") -> 0 | G16: =SUMIFS('Lista Movimenti'!$C:$C, 'Lista Movimenti'!$B:$B, $B16, 'Lista Movimenti'!$E:$E, "Spesa", 'Lista Movimenti'!$D:$D, ">=01/05/2026", 'Lista Movimenti'!$D:$D, "<=31/05/2026") -> 0 | H16: =SUMIFS('Lista Movimenti'!$C:$C, 'Lista Movimenti'!$B:$B, $B16, 'Lista Movimenti'!$E:$E, "Spesa", 'Lista Movimenti'!$D:$D, ">=01/06/2026", 'Lista Movimenti'!$D:$D, "<=30/06/2026") -> 0 | I16: =SUMIFS('Lista Movimenti'!$C:$C, 'Lista Movimenti'!$B:$B, $B16, 'Lista Movimenti'!$E:$E, "Spesa", 'Lista Movimenti'!$D:$D, ">=01/07/2026", 'Lista Movimenti'!$D:$D, "<=31/07/2026") -> 0 | J16: =SUMIFS('Lista Movimenti'!$C:$C, 'Lista Movimenti'!$B:$B, $B16, 'Lista Movimenti'!$E:$E, "Spesa", 'Lista Movimenti'!$D:$D, ">=01/08/2026", 'Lista Movimenti'!$D:$D, "<=31/08/2026") -> 55 | K16: =SUMIFS('Lista Movimenti'!$C:$C, 'Lista Movimenti'!$B:$B, $B16, 'Lista Movimenti'!$E:$E, "Spesa", 'Lista Movimenti'!$D:$D, ">=01/09/2026", 'Lista Movimenti'!$D:$D, "<=30/09/2026") -> 0 | L16: =SUMIFS('Lista Movimenti'!$C:$C, 'Lista Movimenti'!$B:$B, $B16, 'Lista Movimenti'!$E:$E, "Spesa", 'Lista Movimenti'!$D:$D, ">=01/10/2026", 'Lista Movimenti'!$D:$D, "<=31/10/2026") -> 0 | M16: =SUMIFS('Lista Movimenti'!$C:$C, 'Lista Movimenti'!$B:$B, $B16, 'Lista Movimenti'!$E:$E, "Spesa", 'Lista Movimenti'!$D:$D, ">=01/11/2026", 'Lista Movimenti'!$D:$D, "<=30/11/2026") -> 0 | N16: =SUMIFS('Lista Movimenti'!$C:$C, 'Lista Movimenti'!$B:$B, $B16, 'Lista Movimenti'!$E:$E, "Spesa", 'Lista Movimenti'!$D:$D, ">=01/12/2026", 'Lista Movimenti'!$D:$D, "<=31/12/2026") -> 45 | O16: =AVERAGE(C16:N16) -> 10.75 | P16: 40 | Q16: =SUM(C16:N16) -> 129
B17: 📱 Telefono | C17: =SUMIFS('Lista Movimenti'!C:C, 'Lista Movimenti'!B:B, B17, 'Lista Movimenti'!E:E, "Spesa", 'Lista Movimenti'!D:D, ">=01/01/2026", 'Lista Movimenti'!D:D, "<=31/01/2026") -> 12 | D17: =SUMIFS('Lista Movimenti'!$C:$C, 'Lista Movimenti'!$B:$B, $B17, 'Lista Movimenti'!$E:$E, "Spesa", 'Lista Movimenti'!$D:$D, ">=01/02/2026", 'Lista Movimenti'!$D:$D, "<=28/02/2026") -> 0 | E17: =SUMIFS('Lista Movimenti'!$C:$C, 'Lista Movimenti'!$B:$B, $B17, 'Lista Movimenti'!$E:$E, "Spesa", 'Lista Movimenti'!$D:$D, ">=01/03/2026", 'Lista Movimenti'!$D:$D, "<=31/03/2026") -> 0 | F17: =SUMIFS('Lista Movimenti'!$C:$C, 'Lista Movimenti'!$B:$B, $B17, 'Lista Movimenti'!$E:$E, "Spesa", 'Lista Movimenti'!$D:$D, ">=01/04/2026", 'Lista Movimenti'!$D:$D, "<=30/04/2026") -> 0 | G17: =SUMIFS('Lista Movimenti'!$C:$C, 'Lista Movimenti'!$B:$B, $B17, 'Lista Movimenti'!$E:$E, "Spesa", 'Lista Movimenti'!$D:$D, ">=01/05/2026", 'Lista Movimenti'!$D:$D, "<=31/05/2026") -> 0 | H17: =SUMIFS('Lista Movimenti'!$C:$C, 'Lista Movimenti'!$B:$B, $B17, 'Lista Movimenti'!$E:$E, "Spesa", 'Lista Movimenti'!$D:$D, ">=01/06/2026", 'Lista Movimenti'!$D:$D, "<=30/06/2026") -> 35 | I17: =SUMIFS('Lista Movimenti'!$C:$C, 'Lista Movimenti'!$B:$B, $B17, 'Lista Movimenti'!$E:$E, "Spesa", 'Lista Movimenti'!$D:$D, ">=01/07/2026", 'Lista Movimenti'!$D:$D, "<=31/07/2026") -> 0 | J17: =SUMIFS('Lista Movimenti'!$C:$C, 'Lista Movimenti'!$B:$B, $B17, 'Lista Movimenti'!$E:$E, "Spesa", 'Lista Movimenti'!$D:$D, ">=01/08/2026", 'Lista Movimenti'!$D:$D, "<=31/08/2026") -> 0 | K17: =SUMIFS('Lista Movimenti'!$C:$C, 'Lista Movimenti'!$B:$B, $B17, 'Lista Movimenti'!$E:$E, "Spesa", 'Lista Movimenti'!$D:$D, ">=01/09/2026", 'Lista Movimenti'!$D:$D, "<=30/09/2026") -> 0 | L17: =SUMIFS('Lista Movimenti'!$C:$C, 'Lista Movimenti'!$B:$B, $B17, 'Lista Movimenti'!$E:$E, "Spesa", 'Lista Movimenti'!$D:$D, ">=01/10/2026", 'Lista Movimenti'!$D:$D, "<=31/10/2026") -> 0 | M17: =SUMIFS('Lista Movimenti'!$C:$C, 'Lista Movimenti'!$B:$B, $B17, 'Lista Movimenti'!$E:$E, "Spesa", 'Lista Movimenti'!$D:$D, ">=01/11/2026", 'Lista Movimenti'!$D:$D, "<=30/11/2026") -> 0 | N17: =SUMIFS('Lista Movimenti'!$C:$C, 'Lista Movimenti'!$B:$B, $B17, 'Lista Movimenti'!$E:$E, "Spesa", 'Lista Movimenti'!$D:$D, ">=01/12/2026", 'Lista Movimenti'!$D:$D, "<=31/12/2026") -> 25 | O17: =AVERAGE(C17:N17) -> 6 | P17: 15 | Q17: =SUM(C17:N17) -> 72
B18: 🚌 Trasporti | C18: =SUMIFS('Lista Movimenti'!C:C, 'Lista Movimenti'!B:B, B18, 'Lista Movimenti'!E:E, "Spesa", 'Lista Movimenti'!D:D, ">=01/01/2026", 'Lista Movimenti'!D:D, "<=31/01/2026") -> 60 | D18: =SUMIFS('Lista Movimenti'!$C:$C, 'Lista Movimenti'!$B:$B, $B18, 'Lista Movimenti'!$E:$E, "Spesa", 'Lista Movimenti'!$D:$D, ">=01/02/2026", 'Lista Movimenti'!$D:$D, "<=28/02/2026") -> 0 | E18: =SUMIFS('Lista Movimenti'!$C:$C, 'Lista Movimenti'!$B:$B, $B18, 'Lista Movimenti'!$E:$E, "Spesa", 'Lista Movimenti'!$D:$D, ">=01/03/2026", 'Lista Movimenti'!$D:$D, "<=31/03/2026") -> 0 | F18: =SUMIFS('Lista Movimenti'!$C:$C, 'Lista Movimenti'!$B:$B, $B18, 'Lista Movimenti'!$E:$E, "Spesa", 'Lista Movimenti'!$D:$D, ">=01/04/2026", 'Lista Movimenti'!$D:$D, "<=30/04/2026") -> 0 | G18: =SUMIFS('Lista Movimenti'!$C:$C, 'Lista Movimenti'!$B:$B, $B18, 'Lista Movimenti'!$E:$E, "Spesa", 'Lista Movimenti'!$D:$D, ">=01/05/2026", 'Lista Movimenti'!$D:$D, "<=31/05/2026") -> 0 | H18: =SUMIFS('Lista Movimenti'!$C:$C, 'Lista Movimenti'!$B:$B, $B18, 'Lista Movimenti'!$E:$E, "Spesa", 'Lista Movimenti'!$D:$D, ">=01/06/2026", 'Lista Movimenti'!$D:$D, "<=30/06/2026") -> 0 | I18: =SUMIFS('Lista Movimenti'!$C:$C, 'Lista Movimenti'!$B:$B, $B18, 'Lista Movimenti'!$E:$E, "Spesa", 'Lista Movimenti'!$D:$D, ">=01/07/2026", 'Lista Movimenti'!$D:$D, "<=31/07/2026") -> 0 | J18: =SUMIFS('Lista Movimenti'!$C:$C, 'Lista Movimenti'!$B:$B, $B18, 'Lista Movimenti'!$E:$E, "Spesa", 'Lista Movimenti'!$D:$D, ">=01/08/2026", 'Lista Movimenti'!$D:$D, "<=31/08/2026") -> 0 | K18: =SUMIFS('Lista Movimenti'!$C:$C, 'Lista Movimenti'!$B:$B, $B18, 'Lista Movimenti'!$E:$E, "Spesa", 'Lista Movimenti'!$D:$D, ">=01/09/2026", 'Lista Movimenti'!$D:$D, "<=30/09/2026") -> 0 | L18: =SUMIFS('Lista Movimenti'!$C:$C, 'Lista Movimenti'!$B:$B, $B18, 'Lista Movimenti'!$E:$E, "Spesa", 'Lista Movimenti'!$D:$D, ">=01/10/2026", 'Lista Movimenti'!$D:$D, "<=31/10/2026") -> 0 | M18: =SUMIFS('Lista Movimenti'!$C:$C, 'Lista Movimenti'!$B:$B, $B18, 'Lista Movimenti'!$E:$E, "Spesa", 'Lista Movimenti'!$D:$D, ">=01/11/2026", 'Lista Movimenti'!$D:$D, "<=30/11/2026") -> 0 | N18: =SUMIFS('Lista Movimenti'!$C:$C, 'Lista Movimenti'!$B:$B, $B18, 'Lista Movimenti'!$E:$E, "Spesa", 'Lista Movimenti'!$D:$D, ">=01/12/2026", 'Lista Movimenti'!$D:$D, "<=31/12/2026") -> 0 | O18: =AVERAGE(C18:N18) -> 5 | P18: 45 | Q18: =SUM(C18:N18) -> 60
B19: 👕 Vestiti | C19: =SUMIFS('Lista Movimenti'!C:C, 'Lista Movimenti'!B:B, B19, 'Lista Movimenti'!E:E, "Spesa", 'Lista Movimenti'!D:D, ">=01/01/2026", 'Lista Movimenti'!D:D, "<=31/01/2026") -> 112 | D19: =SUMIFS('Lista Movimenti'!$C:$C, 'Lista Movimenti'!$B:$B, $B19, 'Lista Movimenti'!$E:$E, "Spesa", 'Lista Movimenti'!$D:$D, ">=01/02/2026", 'Lista Movimenti'!$D:$D, "<=28/02/2026") -> 0 | E19: =SUMIFS('Lista Movimenti'!$C:$C, 'Lista Movimenti'!$B:$B, $B19, 'Lista Movimenti'!$E:$E, "Spesa", 'Lista Movimenti'!$D:$D, ">=01/03/2026", 'Lista Movimenti'!$D:$D, "<=31/03/2026") -> 0 | F19: =SUMIFS('Lista Movimenti'!$C:$C, 'Lista Movimenti'!$B:$B, $B19, 'Lista Movimenti'!$E:$E, "Spesa", 'Lista Movimenti'!$D:$D, ">=01/04/2026", 'Lista Movimenti'!$D:$D, "<=30/04/2026") -> 0 | G19: =SUMIFS('Lista Movimenti'!$C:$C, 'Lista Movimenti'!$B:$B, $B19, 'Lista Movimenti'!$E:$E, "Spesa", 'Lista Movimenti'!$D:$D, ">=01/05/2026", 'Lista Movimenti'!$D:$D, "<=31/05/2026") -> 0 | H19: =SUMIFS('Lista Movimenti'!$C:$C, 'Lista Movimenti'!$B:$B, $B19, 'Lista Movimenti'!$E:$E, "Spesa", 'Lista Movimenti'!$D:$D, ">=01/06/2026", 'Lista Movimenti'!$D:$D, "<=30/06/2026") -> 0 | I19: =SUMIFS('Lista Movimenti'!$C:$C, 'Lista Movimenti'!$B:$B, $B19, 'Lista Movimenti'!$E:$E, "Spesa", 'Lista Movimenti'!$D:$D, ">=01/07/2026", 'Lista Movimenti'!$D:$D, "<=31/07/2026") -> 0 | J19: =SUMIFS('Lista Movimenti'!$C:$C, 'Lista Movimenti'!$B:$B, $B19, 'Lista Movimenti'!$E:$E, "Spesa", 'Lista Movimenti'!$D:$D, ">=01/08/2026", 'Lista Movimenti'!$D:$D, "<=31/08/2026") -> 0 | K19: =SUMIFS('Lista Movimenti'!$C:$C, 'Lista Movimenti'!$B:$B, $B19, 'Lista Movimenti'!$E:$E, "Spesa", 'Lista Movimenti'!$D:$D, ">=01/09/2026", 'Lista Movimenti'!$D:$D, "<=30/09/2026") -> 0 | L19: =SUMIFS('Lista Movimenti'!$C:$C, 'Lista Movimenti'!$B:$B, $B19, 'Lista Movimenti'!$E:$E, "Spesa", 'Lista Movimenti'!$D:$D, ">=01/10/2026", 'Lista Movimenti'!$D:$D, "<=31/10/2026") -> 0 | M19: =SUMIFS('Lista Movimenti'!$C:$C, 'Lista Movimenti'!$B:$B, $B19, 'Lista Movimenti'!$E:$E, "Spesa", 'Lista Movimenti'!$D:$D, ">=01/11/2026", 'Lista Movimenti'!$D:$D, "<=30/11/2026") -> 0 | N19: =SUMIFS('Lista Movimenti'!$C:$C, 'Lista Movimenti'!$B:$B, $B19, 'Lista Movimenti'!$E:$E, "Spesa", 'Lista Movimenti'!$D:$D, ">=01/12/2026", 'Lista Movimenti'!$D:$D, "<=31/12/2026") -> 110 | O19: =AVERAGE(C19:N19) -> 18.5 | P19: 35 | Q19: =SUM(C19:N19) -> 222
A20: Totale Necessità | B20: -- Necessità -- | C20: =SUM(C13:C19) -> 668 | D20: =SUM(D13:D19) -> 780 | E20: =SUM(E13:E19) -> 0 | F20: =SUM(F13:F19) -> 300 | G20: =SUM(G13:G19) -> 0 | H20: =SUM(H13:H19) -> 35 | I20: =SUM(I13:I19) -> 599 | J20: =SUM(J13:J19) -> 55 | ... P20: =SUM(P13:P19) -> 665 | Q20: =SUM(C20:N20) -> 2917
A22: EXTRA | B22: -- Extra -- | C22: Gennaio | D22: Febbraio | E22: Marzo | F22: Aprile | G22: Maggio | H22: Giugno | I22: Luglio | J22: Agosto | K22: Settembre | L22: Ottobre | M22: Novembre | N22: Dicembre | O22: Media | P22: Obiettivo | Q22: Totale Annuo
B23: 🎫 Abbonamenti | C23: =SUMIFS('Lista Movimenti'!$C:$C, 'Lista Movimenti'!$B:$B, $B23, 'Lista Movimenti'!$E:$E, "Spesa", 'Lista Movimenti'!$D:$D, ">=01/01/2026", 'Lista Movimenti'!$D:$D, "<=31/01/2026") -> 9 | D23: =SUMIFS('Lista Movimenti'!$C:$C, 'Lista Movimenti'!$B:$B, $B23, 'Lista Movimenti'!$E:$E, "Spesa", 'Lista Movimenti'!$D:$D, ">=01/02/2026", 'Lista Movimenti'!$D:$D, "<=28/02/2026") -> 0 | E23: =SUMIFS('Lista Movimenti'!$C:$C, 'Lista Movimenti'!$B:$B, $B23, 'Lista Movimenti'!$E:$E, "Spesa", 'Lista Movimenti'!$D:$D, ">=01/03/2026", 'Lista Movimenti'!$D:$D, "<=31/03/2026") -> 0 | F23: =SUMIFS('Lista Movimenti'!$C:$C, 'Lista Movimenti'!$B:$B, $B23, 'Lista Movimenti'!$E:$E, "Spesa", 'Lista Movimenti'!$D:$D, ">=01/04/2026", 'Lista Movimenti'!$D:$D, "<=30/04/2026") -> 32 | G23: =SUMIFS('Lista Movimenti'!$C:$C, 'Lista Movimenti'!$B:$B, $B23, 'Lista Movimenti'!$E:$E, "Spesa", 'Lista Movimenti'!$D:$D, ">=01/05/2026", 'Lista Movimenti'!$D:$D, "<=31/05/2026") -> 0 | H23: =SUMIFS('Lista Movimenti'!$C:$C, 'Lista Movimenti'!$B:$B, $B23, 'Lista Movimenti'!$E:$E, "Spesa", 'Lista Movimenti'!$D:$D, ">=01/06/2026", 'Lista Movimenti'!$D:$D, "<=30/06/2026") -> 0 | I23: =SUMIFS('Lista Movimenti'!$C:$C, 'Lista Movimenti'!$B:$B, $B23, 'Lista Movimenti'!$E:$E, "Spesa", 'Lista Movimenti'!$D:$D, ">=01/07/2026", 'Lista Movimenti'!$D:$D, "<=31/07/2026") -> 12 | J23: =SUMIFS('Lista Movimenti'!$C:$C, 'Lista Movimenti'!$B:$B, $B23, 'Lista Movimenti'!$E:$E, "Spesa", 'Lista Movimenti'!$D:$D, ">=01/08/2026", 'Lista Movimenti'!$D:$D, "<=31/08/2026") -> 0 | K23: =SUMIFS('Lista Movimenti'!$C:$C, 'Lista Movimenti'!$B:$B, $B23, 'Lista Movimenti'!$E:$E, "Spesa", 'Lista Movimenti'!$D:$D, ">=01/09/2026", 'Lista Movimenti'!$D:$D, "<=30/09/2026") -> 0 | L23: =SUMIFS('Lista Movimenti'!$C:$C, 'Lista Movimenti'!$B:$B, $B23, 'Lista Movimenti'!$E:$E, "Spesa", 'Lista Movimenti'!$D:$D, ">=01/10/2026", 'Lista Movimenti'!$D:$D, "<=31/10/2026") -> 0 | M23: =SUMIFS('Lista Movimenti'!$C:$C, 'Lista Movimenti'!$B:$B, $B23, 'Lista Movimenti'!$E:$E, "Spesa", 'Lista Movimenti'!$D:$D, ">=01/11/2026", 'Lista Movimenti'!$D:$D, "<=30/11/2026") -> 12 | N23: =SUMIFS('Lista Movimenti'!$C:$C, 'Lista Movimenti'!$B:$B, $B23, 'Lista Movimenti'!$E:$E, "Spesa", 'Lista Movimenti'!$D:$D, ">=01/12/2026", 'Lista Movimenti'!$D:$D, "<=31/12/2026") -> 0 | O23: =AVERAGE(C23:N23) -> 5.4166667 | P23: 22 | Q23: =SUM(C23:N23) -> 65
B24: 🍔 Cibo fuori | C24: =SUMIFS('Lista Movimenti'!C:C, 'Lista Movimenti'!B:B, B24, 'Lista Movimenti'!E:E, "Spesa", 'Lista Movimenti'!D:D, ">=01/01/2026", 'Lista Movimenti'!D:D, "<=31/01/2026") -> 64 | D24: =SUMIFS('Lista Movimenti'!$C:$C, 'Lista Movimenti'!$B:$B, $B24, 'Lista Movimenti'!$E:$E, "Spesa", 'Lista Movimenti'!$D:$D, ">=01/02/2026", 'Lista Movimenti'!$D:$D, "<=28/02/2026") -> 79 | E24: =SUMIFS('Lista Movimenti'!$C:$C, 'Lista Movimenti'!$B:$B, $B24, 'Lista Movimenti'!$E:$E, "Spesa", 'Lista Movimenti'!$D:$D, ">=01/03/2026", 'Lista Movimenti'!$D:$D, "<=31/03/2026") -> 0 | F24: =SUMIFS('Lista Movimenti'!$C:$C, 'Lista Movimenti'!$B:$B, $B24, 'Lista Movimenti'!$E:$E, "Spesa", 'Lista Movimenti'!$D:$D, ">=01/04/2026", 'Lista Movimenti'!$D:$D, "<=30/04/2026") -> 0 | G24: =SUMIFS('Lista Movimenti'!$C:$C, 'Lista Movimenti'!$B:$B, $B24, 'Lista Movimenti'!$E:$E, "Spesa", 'Lista Movimenti'!$D:$D, ">=01/05/2026", 'Lista Movimenti'!$D:$D, "<=31/05/2026") -> 0 | H24: =SUMIFS('Lista Movimenti'!$C:$C, 'Lista Movimenti'!$B:$B, $B24, 'Lista Movimenti'!$E:$E, "Spesa", 'Lista Movimenti'!$D:$D, ">=01/06/2026", 'Lista Movimenti'!$D:$D, "<=30/06/2026") -> 0 | I24: =SUMIFS('Lista Movimenti'!$C:$C, 'Lista Movimenti'!$B:$B, $B24, 'Lista Movimenti'!$E:$E, "Spesa", 'Lista Movimenti'!$D:$D, ">=01/07/2026", 'Lista Movimenti'!$D:$D, "<=31/07/2026") -> 0 | J24: =SUMIFS('Lista Movimenti'!$C:$C, 'Lista Movimenti'!$B:$B, $B24, 'Lista Movimenti'!$E:$E, "Spesa", 'Lista Movimenti'!$D:$D, ">=01/08/2026", 'Lista Movimenti'!$D:$D, "<=31/08/2026") -> 0 | K24: =SUMIFS('Lista Movimenti'!$C:$C, 'Lista Movimenti'!$B:$B, $B24, 'Lista Movimenti'!$E:$E, "Spesa", 'Lista Movimenti'!$D:$D, ">=01/09/2026", 'Lista Movimenti'!$D:$D, "<=30/09/2026") -> 0 | L24: =SUMIFS('Lista Movimenti'!$C:$C, 'Lista Movimenti'!$B:$B, $B24, 'Lista Movimenti'!$E:$E, "Spesa", 'Lista Movimenti'!$D:$D, ">=01/10/2026", 'Lista Movimenti'!$D:$D, "<=31/10/2026") -> 0 | M24: =SUMIFS('Lista Movimenti'!$C:$C, 'Lista Movimenti'!$B:$B, $B24, 'Lista Movimenti'!$E:$E, "Spesa", 'Lista Movimenti'!$D:$D, ">=01/11/2026", 'Lista Movimenti'!$D:$D, "<=30/11/2026") -> 0 | N24: =SUMIFS('Lista Movimenti'!$C:$C, 'Lista Movimenti'!$B:$B, $B24, 'Lista Movimenti'!$E:$E, "Spesa", 'Lista Movimenti'!$D:$D, ">=01/12/2026", 'Lista Movimenti'!$D:$D, "<=31/12/2026") -> 120 | O24: =AVERAGE(C24:N24) -> 21.916667 | P24: 85 | Q24: =SUM(C24:N24) -> 263
B25: 🎬 Intrattenimento | C25: =SUMIFS('Lista Movimenti'!C:C, 'Lista Movimenti'!B:B, B25, 'Lista Movimenti'!E:E, "Spesa", 'Lista Movimenti'!D:D, ">=01/01/2026", 'Lista Movimenti'!D:D, "<=31/01/2026") -> 36 | D25: =SUMIFS('Lista Movimenti'!$C:$C, 'Lista Movimenti'!$B:$B, $B25, 'Lista Movimenti'!$E:$E, "Spesa", 'Lista Movimenti'!$D:$D, ">=01/02/2026", 'Lista Movimenti'!$D:$D, "<=28/02/2026") -> 0 | E25: =SUMIFS('Lista Movimenti'!$C:$C, 'Lista Movimenti'!$B:$B, $B25, 'Lista Movimenti'!$E:$E, "Spesa", 'Lista Movimenti'!$D:$D, ">=01/03/2026", 'Lista Movimenti'!$D:$D, "<=31/03/2026") -> 0 | F25: =SUMIFS('Lista Movimenti'!$C:$C, 'Lista Movimenti'!$B:$B, $B25, 'Lista Movimenti'!$E:$E, "Spesa", 'Lista Movimenti'!$D:$D, ">=01/04/2026", 'Lista Movimenti'!$D:$D, "<=30/04/2026") -> 0 | G25: =SUMIFS('Lista Movimenti'!$C:$C, 'Lista Movimenti'!$B:$B, $B25, 'Lista Movimenti'!$E:$E, "Spesa", 'Lista Movimenti'!$D:$D, ">=01/05/2026", 'Lista Movimenti'!$D:$D, "<=31/05/2026") -> 24 | H25: =SUMIFS('Lista Movimenti'!$C:$C, 'Lista Movimenti'!$B:$B, $B25, 'Lista Movimenti'!$E:$E, "Spesa", 'Lista Movimenti'!$D:$D, ">=01/06/2026", 'Lista Movimenti'!$D:$D, "<=30/06/2026") -> 22 | I25: =SUMIFS('Lista Movimenti'!$C:$C, 'Lista Movimenti'!$B:$B, $B25, 'Lista Movimenti'!$E:$E, "Spesa", 'Lista Movimenti'!$D:$D, ">=01/07/2026", 'Lista Movimenti'!$D:$D, "<=31/07/2026") -> 120 | J25: =SUMIFS('Lista Movimenti'!$C:$C, 'Lista Movimenti'!$B:$B, $B25, 'Lista Movimenti'!$E:$E, "Spesa", 'Lista Movimenti'!$D:$D, ">=01/08/2026", 'Lista Movimenti'!$D:$D, "<=31/08/2026") -> 0 | K25: =SUMIFS('Lista Movimenti'!$C:$C, 'Lista Movimenti'!$B:$B, $B25, 'Lista Movimenti'!$E:$E, "Spesa", 'Lista Movimenti'!$D:$D, ">=01/09/2026", 'Lista Movimenti'!$D:$D, "<=30/09/2026") -> 0 | L25: =SUMIFS('Lista Movimenti'!$C:$C, 'Lista Movimenti'!$B:$B, $B25, 'Lista Movimenti'!$E:$E, "Spesa", 'Lista Movimenti'!$D:$D, ">=01/10/2026", 'Lista Movimenti'!$D:$D, "<=31/10/2026") -> 0 | M25: =SUMIFS('Lista Movimenti'!$C:$C, 'Lista Movimenti'!$B:$B, $B25, 'Lista Movimenti'!$E:$E, "Spesa", 'Lista Movimenti'!$D:$D, ">=01/11/2026", 'Lista Movimenti'!$D:$D, "<=30/11/2026") -> 0 | N25: =SUMIFS('Lista Movimenti'!$C:$C, 'Lista Movimenti'!$B:$B, $B25, 'Lista Movimenti'!$E:$E, "Spesa", 'Lista Movimenti'!$D:$D, ">=01/12/2026", 'Lista Movimenti'!$D:$D, "<=31/12/2026") -> 0 | O25: =AVERAGE(C25:N25) -> 16.833333 | P25: 24 | Q25: =SUM(C25:N25) -> 202
B26: 🎁 Regali | C26: =SUMIFS('Lista Movimenti'!C:C, 'Lista Movimenti'!B:B, B26, 'Lista Movimenti'!E:E, "Spesa", 'Lista Movimenti'!D:D, ">=01/01/2026", 'Lista Movimenti'!D:D, "<=31/01/2026") -> 200 | D26: =SUMIFS('Lista Movimenti'!$C:$C, 'Lista Movimenti'!$B:$B, $B26, 'Lista Movimenti'!$E:$E, "Spesa", 'Lista Movimenti'!$D:$D, ">=01/02/2026", 'Lista Movimenti'!$D:$D, "<=28/02/2026") -> 0 | E26: =SUMIFS('Lista Movimenti'!$C:$C, 'Lista Movimenti'!$B:$B, $B26, 'Lista Movimenti'!$E:$E, "Spesa", 'Lista Movimenti'!$D:$D, ">=01/03/2026", 'Lista Movimenti'!$D:$D, "<=31/03/2026") -> 0 | F26: =SUMIFS('Lista Movimenti'!$C:$C, 'Lista Movimenti'!$B:$B, $B26, 'Lista Movimenti'!$E:$E, "Spesa", 'Lista Movimenti'!$D:$D, ">=01/04/2026", 'Lista Movimenti'!$D:$D, "<=30/04/2026") -> 0 | G26: =SUMIFS('Lista Movimenti'!$C:$C, 'Lista Movimenti'!$B:$B, $B26, 'Lista Movimenti'!$E:$E, "Spesa", 'Lista Movimenti'!$D:$D, ">=01/05/2026", 'Lista Movimenti'!$D:$D, "<=31/05/2026") -> 50 | H26: =SUMIFS('Lista Movimenti'!$C:$C, 'Lista Movimenti'!$B:$B, $B26, 'Lista Movimenti'!$E:$E, "Spesa", 'Lista Movimenti'!$D:$D, ">=01/06/2026", 'Lista Movimenti'!$D:$D, "<=30/06/2026") -> 0 | I26: =SUMIFS('Lista Movimenti'!$C:$C, 'Lista Movimenti'!$B:$B, $B26, 'Lista Movimenti'!$E:$E, "Spesa", 'Lista Movimenti'!$D:$D, ">=01/07/2026", 'Lista Movimenti'!$D:$D, "<=31/07/2026") -> 0 | J26: =SUMIFS('Lista Movimenti'!$C:$C, 'Lista Movimenti'!$B:$B, $B26, 'Lista Movimenti'!$E:$E, "Spesa", 'Lista Movimenti'!$D:$D, ">=01/08/2026", 'Lista Movimenti'!$D:$D, "<=31/08/2026") -> 0 | K26: =SUMIFS('Lista Movimenti'!$C:$C, 'Lista Movimenti'!$B:$B, $B26, 'Lista Movimenti'!$E:$E, "Spesa", 'Lista Movimenti'!$D:$D, ">=01/09/2026", 'Lista Movimenti'!$D:$D, "<=30/09/2026") -> 0 | L26: =SUMIFS('Lista Movimenti'!$C:$C, 'Lista Movimenti'!$B:$B, $B26, 'Lista Movimenti'!$E:$E, "Spesa", 'Lista Movimenti'!$D:$D, ">=01/10/2026", 'Lista Movimenti'!$D:$D, "<=31/10/2026") -> 0 | M26: =SUMIFS('Lista Movimenti'!$C:$C, 'Lista Movimenti'!$B:$B, $B26, 'Lista Movimenti'!$E:$E, "Spesa", 'Lista Movimenti'!$D:$D, ">=01/11/2026", 'Lista Movimenti'!$D:$D, "<=30/11/2026") -> 0 | N26: =SUMIFS('Lista Movimenti'!$C:$C, 'Lista Movimenti'!$B:$B, $B26, 'Lista Movimenti'!$E:$E, "Spesa", 'Lista Movimenti'!$D:$D, ">=01/12/2026", 'Lista Movimenti'!$D:$D, "<=31/12/2026") -> 0 | O26: =AVERAGE(C26:N26) -> 20.833333 | P26: 20 | Q26: =SUM(C26:N26) -> 250
B27: ✈️ Viaggi/Vacanze | C27: =SUMIFS('Lista Movimenti'!C:C, 'Lista Movimenti'!B:B, B27, 'Lista Movimenti'!E:E, "Spesa", 'Lista Movimenti'!D:D, ">=01/01/2026", 'Lista Movimenti'!D:D, "<=31/01/2026") -> 0 | D27: =SUMIFS('Lista Movimenti'!$C:$C, 'Lista Movimenti'!$B:$B, $B27, 'Lista Movimenti'!$E:$E, "Spesa", 'Lista Movimenti'!$D:$D, ">=01/02/2026", 'Lista Movimenti'!$D:$D, "<=28/02/2026") -> 0 | E27: =SUMIFS('Lista Movimenti'!$C:$C, 'Lista Movimenti'!$B:$B, $B27, 'Lista Movimenti'!$E:$E, "Spesa", 'Lista Movimenti'!$D:$D, ">=01/03/2026", 'Lista Movimenti'!$D:$D, "<=31/03/2026") -> 350 | F27: =SUMIFS('Lista Movimenti'!$C:$C, 'Lista Movimenti'!$B:$B, $B27, 'Lista Movimenti'!$E:$E, "Spesa", 'Lista Movimenti'!$D:$D, ">=01/04/2026", 'Lista Movimenti'!$D:$D, "<=30/04/2026") -> 0 | G27: =SUMIFS('Lista Movimenti'!$C:$C, 'Lista Movimenti'!$B:$B, $B27, 'Lista Movimenti'!$E:$E, "Spesa", 'Lista Movimenti'!$D:$D, ">=01/05/2026", 'Lista Movimenti'!$D:$D, "<=31/05/2026") -> 300 | H27: =SUMIFS('Lista Movimenti'!$C:$C, 'Lista Movimenti'!$B:$B, $B27, 'Lista Movimenti'!$E:$E, "Spesa", 'Lista Movimenti'!$D:$D, ">=01/06/2026", 'Lista Movimenti'!$D:$D, "<=30/06/2026") -> 0 | I27: =SUMIFS('Lista Movimenti'!$C:$C, 'Lista Movimenti'!$B:$B, $B27, 'Lista Movimenti'!$E:$E, "Spesa", 'Lista Movimenti'!$D:$D, ">=01/07/2026", 'Lista Movimenti'!$D:$D, "<=31/07/2026") -> 120 | J27: =SUMIFS('Lista Movimenti'!$C:$C, 'Lista Movimenti'!$B:$B, $B27, 'Lista Movimenti'!$E:$E, "Spesa", 'Lista Movimenti'!$D:$D, ">=01/08/2026", 'Lista Movimenti'!$D:$D, "<=31/08/2026") -> 0 | K27: =SUMIFS('Lista Movimenti'!$C:$C, 'Lista Movimenti'!$B:$B, $B27, 'Lista Movimenti'!$E:$E, "Spesa", 'Lista Movimenti'!$D:$D, ">=01/09/2026", 'Lista Movimenti'!$D:$D, "<=30/09/2026") -> 150 | L27: =SUMIFS('Lista Movimenti'!$C:$C, 'Lista Movimenti'!$B:$B, $B27, 'Lista Movimenti'!$E:$E, "Spesa", 'Lista Movimenti'!$D:$D, ">=01/10/2026", 'Lista Movimenti'!$D:$D, "<=31/10/2026") -> 0 | M27: =SUMIFS('Lista Movimenti'!$C:$C, 'Lista Movimenti'!$B:$B, $B27, 'Lista Movimenti'!$E:$E, "Spesa", 'Lista Movimenti'!$D:$D, ">=01/11/2026", 'Lista Movimenti'!$D:$D, "<=30/11/2026") -> 0 | N27: =SUMIFS('Lista Movimenti'!$C:$C, 'Lista Movimenti'!$B:$B, $B27, 'Lista Movimenti'!$E:$E, "Spesa", 'Lista Movimenti'!$D:$D, ">=01/12/2026", 'Lista Movimenti'!$D:$D, "<=31/12/2026") -> 0 | O27: =AVERAGE(C27:N27) -> 76.666667 | P27: 60 | Q27: =SUM(C27:N27) -> 920
B28: 📚 Cultura | C28: =SUMIFS('Lista Movimenti'!C:C, 'Lista Movimenti'!B:B, B28, 'Lista Movimenti'!E:E, "Spesa", 'Lista Movimenti'!D:D, ">=01/01/2026", 'Lista Movimenti'!D:D, "<=31/01/2026") -> 32 | D28: =SUMIFS('Lista Movimenti'!$C:$C, 'Lista Movimenti'!$B:$B, $B28, 'Lista Movimenti'!$E:$E, "Spesa", 'Lista Movimenti'!$D:$D, ">=01/02/2026", 'Lista Movimenti'!$D:$D, "<=28/02/2026") -> 0 | E28: =SUMIFS('Lista Movimenti'!$C:$C, 'Lista Movimenti'!$B:$B, $B28, 'Lista Movimenti'!$E:$E, "Spesa", 'Lista Movimenti'!$D:$D, ">=01/03/2026", 'Lista Movimenti'!$D:$D, "<=31/03/2026") -> 0 | F28: =SUMIFS('Lista Movimenti'!$C:$C, 'Lista Movimenti'!$B:$B, $B28, 'Lista Movimenti'!$E:$E, "Spesa", 'Lista Movimenti'!$D:$D, ">=01/04/2026", 'Lista Movimenti'!$D:$D, "<=30/04/2026") -> 0 | G28: =SUMIFS('Lista Movimenti'!$C:$C, 'Lista Movimenti'!$B:$B, $B28, 'Lista Movimenti'!$E:$E, "Spesa", 'Lista Movimenti'!$D:$D, ">=01/05/2026", 'Lista Movimenti'!$D:$D, "<=31/05/2026") -> 0 | H28: =SUMIFS('Lista Movimenti'!$C:$C, 'Lista Movimenti'!$B:$B, $B28, 'Lista Movimenti'!$E:$E, "Spesa", 'Lista Movimenti'!$D:$D, ">=01/06/2026", 'Lista Movimenti'!$D:$D, "<=30/06/2026") -> 0 | I28: =SUMIFS('Lista Movimenti'!$C:$C, 'Lista Movimenti'!$B:$B, $B28, 'Lista Movimenti'!$E:$E, "Spesa", 'Lista Movimenti'!$D:$D, ">=01/07/2026", 'Lista Movimenti'!$D:$D, "<=31/07/2026") -> 0 | J28: =SUMIFS('Lista Movimenti'!$C:$C, 'Lista Movimenti'!$B:$B, $B28, 'Lista Movimenti'!$E:$E, "Spesa", 'Lista Movimenti'!$D:$D, ">=01/08/2026", 'Lista Movimenti'!$D:$D, "<=31/08/2026") -> 10 | K28: =SUMIFS('Lista Movimenti'!$C:$C, 'Lista Movimenti'!$B:$B, $B28, 'Lista Movimenti'!$E:$E, "Spesa", 'Lista Movimenti'!$D:$D, ">=01/09/2026", 'Lista Movimenti'!$D:$D, "<=30/09/2026") -> 0 | L28: =SUMIFS('Lista Movimenti'!$C:$C, 'Lista Movimenti'!$B:$B, $B28, 'Lista Movimenti'!$E:$E, "Spesa", 'Lista Movimenti'!$D:$D, ">=01/10/2026", 'Lista Movimenti'!$D:$D, "<=31/10/2026") -> 10 | M28: =SUMIFS('Lista Movimenti'!$C:$C, 'Lista Movimenti'!$B:$B, $B28, 'Lista Movimenti'!$E:$E, "Spesa", 'Lista Movimenti'!$D:$D, ">=01/11/2026", 'Lista Movimenti'!$D:$D, "<=30/11/2026") -> 0 | N28: =SUMIFS('Lista Movimenti'!$C:$C, 'Lista Movimenti'!$B:$B, $B28, 'Lista Movimenti'!$E:$E, "Spesa", 'Lista Movimenti'!$D:$D, ">=01/12/2026", 'Lista Movimenti'!$D:$D, "<=31/12/2026") -> 0 | O28: =AVERAGE(C28:N28) -> 4.3333333 | P28: 40 | Q28: =SUM(C28:N28) -> 52
B29: 💅 Cura personale | C29: =SUMIFS('Lista Movimenti'!C:C, 'Lista Movimenti'!B:B, B29, 'Lista Movimenti'!E:E, "Spesa", 'Lista Movimenti'!D:D, ">=01/01/2026", 'Lista Movimenti'!D:D, "<=31/01/2026") -> 100 | D29: =SUMIFS('Lista Movimenti'!$C:$C, 'Lista Movimenti'!$B:$B, $B29, 'Lista Movimenti'!$E:$E, "Spesa", 'Lista Movimenti'!$D:$D, ">=01/02/2026", 'Lista Movimenti'!$D:$D, "<=28/02/2026") -> 0 | E29: =SUMIFS('Lista Movimenti'!$C:$C, 'Lista Movimenti'!$B:$B, $B29, 'Lista Movimenti'!$E:$E, "Spesa", 'Lista Movimenti'!$D:$D, ">=01/03/2026", 'Lista Movimenti'!$D:$D, "<=31/03/2026") -> 30 | F29: =SUMIFS('Lista Movimenti'!$C:$C, 'Lista Movimenti'!$B:$B, $B29, 'Lista Movimenti'!$E:$E, "Spesa", 'Lista Movimenti'!$D:$D, ">=01/04/2026", 'Lista Movimenti'!$D:$D, "<=30/04/2026") -> 0 | G29: =SUMIFS('Lista Movimenti'!$C:$C, 'Lista Movimenti'!$B:$B, $B29, 'Lista Movimenti'!$E:$E, "Spesa", 'Lista Movimenti'!$D:$D, ">=01/05/2026", 'Lista Movimenti'!$D:$D, "<=31/05/2026") -> 0 | H29: =SUMIFS('Lista Movimenti'!$C:$C, 'Lista Movimenti'!$B:$B, $B29, 'Lista Movimenti'!$E:$E, "Spesa", 'Lista Movimenti'!$D:$D, ">=01/06/2026", 'Lista Movimenti'!$D:$D, "<=30/06/2026") -> 0 | I29: =SUMIFS('Lista Movimenti'!$C:$C, 'Lista Movimenti'!$B:$B, $B29, 'Lista Movimenti'!$E:$E, "Spesa", 'Lista Movimenti'!$D:$D, ">=01/07/2026", 'Lista Movimenti'!$D:$D, "<=31/07/2026") -> 20 | J29: =SUMIFS('Lista Movimenti'!$C:$C, 'Lista Movimenti'!$B:$B, $B29, 'Lista Movimenti'!$E:$E, "Spesa", 'Lista Movimenti'!$D:$D, ">=01/08/2026", 'Lista Movimenti'!$D:$D, "<=31/08/2026") -> 0 | K29: =SUMIFS('Lista Movimenti'!$C:$C, 'Lista Movimenti'!$B:$B, $B29, 'Lista Movimenti'!$E:$E, "Spesa", 'Lista Movimenti'!$D:$D, ">=01/09/2026", 'Lista Movimenti'!$D:$D, "<=30/09/2026") -> 0 | L29: =SUMIFS('Lista Movimenti'!$C:$C, 'Lista Movimenti'!$B:$B, $B29, 'Lista Movimenti'!$E:$E, "Spesa", 'Lista Movimenti'!$D:$D, ">=01/10/2026", 'Lista Movimenti'!$D:$D, "<=31/10/2026") -> 0 | M29: =SUMIFS('Lista Movimenti'!$C:$C, 'Lista Movimenti'!$B:$B, $B29, 'Lista Movimenti'!$E:$E, "Spesa", 'Lista Movimenti'!$D:$D, ">=01/11/2026", 'Lista Movimenti'!$D:$D, "<=30/11/2026") -> 0 | N29: =SUMIFS('Lista Movimenti'!$C:$C, 'Lista Movimenti'!$B:$B, $B29, 'Lista Movimenti'!$E:$E, "Spesa", 'Lista Movimenti'!$D:$D, ">=01/12/2026", 'Lista Movimenti'!$D:$D, "<=31/12/2026") -> 0 | O29: =AVERAGE(C29:N29) -> 12.5 | P29: 95 | Q29: =SUM(C29:N29) -> 150
B30: 🌟 Altro extra | C30: =SUMIFS('Lista Movimenti'!C:C, 'Lista Movimenti'!B:B, B30, 'Lista Movimenti'!E:E, "Spesa", 'Lista Movimenti'!D:D, ">=01/01/2026", 'Lista Movimenti'!D:D, "<=31/01/2026") -> 0 | D30: =SUMIFS('Lista Movimenti'!$C:$C, 'Lista Movimenti'!$B:$B, $B30, 'Lista Movimenti'!$E:$E, "Spesa", 'Lista Movimenti'!$D:$D, ">=01/02/2026", 'Lista Movimenti'!$D:$D, "<=28/02/2026") -> 112 | E30: =SUMIFS('Lista Movimenti'!$C:$C, 'Lista Movimenti'!$B:$B, $B30, 'Lista Movimenti'!$E:$E, "Spesa", 'Lista Movimenti'!$D:$D, ">=01/03/2026", 'Lista Movimenti'!$D:$D, "<=31/03/2026") -> 0 | F30: =SUMIFS('Lista Movimenti'!$C:$C, 'Lista Movimenti'!$B:$B, $B30, 'Lista Movimenti'!$E:$E, "Spesa", 'Lista Movimenti'!$D:$D, ">=01/04/2026", 'Lista Movimenti'!$D:$D, "<=30/04/2026") -> 0 | G30: =SUMIFS('Lista Movimenti'!$C:$C, 'Lista Movimenti'!$B:$B, $B30, 'Lista Movimenti'!$E:$E, "Spesa", 'Lista Movimenti'!$D:$D, ">=01/05/2026", 'Lista Movimenti'!$D:$D, "<=31/05/2026") -> 0 | H30: =SUMIFS('Lista Movimenti'!$C:$C, 'Lista Movimenti'!$B:$B, $B30, 'Lista Movimenti'!$E:$E, "Spesa", 'Lista Movimenti'!$D:$D, ">=01/06/2026", 'Lista Movimenti'!$D:$D, "<=30/06/2026") -> 0 | I30: =SUMIFS('Lista Movimenti'!$C:$C, 'Lista Movimenti'!$B:$B, $B30, 'Lista Movimenti'!$E:$E, "Spesa", 'Lista Movimenti'!$D:$D, ">=01/07/2026", 'Lista Movimenti'!$D:$D, "<=31/07/2026") -> 30 | J30: =SUMIFS('Lista Movimenti'!$C:$C, 'Lista Movimenti'!$B:$B, $B30, 'Lista Movimenti'!$E:$E, "Spesa", 'Lista Movimenti'!$D:$D, ">=01/08/2026", 'Lista Movimenti'!$D:$D, "<=31/08/2026") -> 0 | K30: =SUMIFS('Lista Movimenti'!$C:$C, 'Lista Movimenti'!$B:$B, $B30, 'Lista Movimenti'!$E:$E, "Spesa", 'Lista Movimenti'!$D:$D, ">=01/09/2026", 'Lista Movimenti'!$D:$D, "<=30/09/2026") -> 0 | L30: =SUMIFS('Lista Movimenti'!$C:$C, 'Lista Movimenti'!$B:$B, $B30, 'Lista Movimenti'!$E:$E, "Spesa", 'Lista Movimenti'!$D:$D, ">=01/10/2026", 'Lista Movimenti'!$D:$D, "<=31/10/2026") -> 0 | M30: =SUMIFS('Lista Movimenti'!$C:$C, 'Lista Movimenti'!$B:$B, $B30, 'Lista Movimenti'!$E:$E, "Spesa", 'Lista Movimenti'!$D:$D, ">=01/11/2026", 'Lista Movimenti'!$D:$D, "<=30/11/2026") -> 0 | N30: =SUMIFS('Lista Movimenti'!$C:$C, 'Lista Movimenti'!$B:$B, $B30, 'Lista Movimenti'!$E:$E, "Spesa", 'Lista Movimenti'!$D:$D, ">=01/12/2026", 'Lista Movimenti'!$D:$D, "<=31/12/2026") -> 0 | O30: =AVERAGE(C30:N30) -> 11.833333 | P30: 13 | Q30: =SUM(C30:N30) -> 142
A31: Totale Extra | B31: -- Extra -- | C31: =SUM(C23:C30) -> 441 | D31: =SUM(D23:D30) -> 191 | E31: =SUM(E23:E30) -> 380 | F31: =SUM(F23:F30) -> 32 | G31: =SUM(G23:G30) -> 374 | H31: =SUM(H23:H30) -> 22 | I31: =SUM(I23:I30) -> 302 | J31: =SUM(J23:J30) -> 10 | ... P31: =SUM(P23:P30) -> 359 | Q31: =SUM(C31:N31) -> 2044
A33: Totale Uscite | C33: =(C31 + C20) -> 1109 | D33: =(D31 + D20) -> 971 | E33: =(E31 + E20) -> 380 | F33: =(F31 + F20) -> 332 | G33: =(G31 + G20) -> 374 | H33: =(H31 + H20) -> 57 | I33: =(I31 + I20) -> 901 | J33: =(J31 + J20) -> 65 | ... Q33: =(Q31 + Q20) -> 4961
A34: Differenza Entrate Uscite | C34: =(B8-C33) -> 441 | D34: =(C8-D33) -> 429 | E34: =(D8-E33) -> 1130 | F34: =(E8-F33) -> 968 | G34: =(F8-G33) -> 886 | H34: =(G8-H33) -> 1393 | I34: =(H8-I33) -> 99 | J34: =(I8-J33) -> 1245 | ... O34: =(N8-O33) -> 961.58333 | Q34: =(P8-Q33) -> 11539
A37: Categoria | B37: Gennaio | C37: Febbraio | D37: Marzo | E37: Aprile | F37: Maggio | G37: Giugno | H37: Luglio | I37: Agosto | J37: Settembre | K37: Ottobre | L37: Novembre | M37: Dicembre | N37: Media | O37: Obiettivo
A38: 🏠 Casa | B38: =SUMIFS('Lista Movimenti'!$C:$C, 'Lista Movimenti'!$B:$B, $A38, 'Lista Movimenti'!$E:$E, "Risparmio", 'Lista Movimenti'!$D:$D, ">=01/01/2026", 'Lista Movimenti'!$D:$D, "<=31/01/2026") -> 0 | C38: =SUMIFS('Lista Movimenti'!$C:$C, 'Lista Movimenti'!$B:$B, $A38, 'Lista Movimenti'!$E:$E, "Risparmio", 'Lista Movimenti'!$D:$D, ">=01/02/2026", 'Lista Movimenti'!$D:$D, "<=28/02/2026") -> 0 | D38: =SUMIFS('Lista Movimenti'!$C:$C, 'Lista Movimenti'!$B:$B, $A38, 'Lista Movimenti'!$E:$E, "Risparmio", 'Lista Movimenti'!$D:$D, ">=01/03/2026", 'Lista Movimenti'!$D:$D, "<=31/03/2026") -> 0 | E38: =SUMIFS('Lista Movimenti'!$C:$C, 'Lista Movimenti'!$B:$B, $A38, 'Lista Movimenti'!$E:$E, "Risparmio", 'Lista Movimenti'!$D:$D, ">=01/04/2026", 'Lista Movimenti'!$D:$D, "<=30/04/2026") -> 300 | F38: =SUMIFS('Lista Movimenti'!$C:$C, 'Lista Movimenti'!$B:$B, $A38, 'Lista Movimenti'!$E:$E, "Risparmio", 'Lista Movimenti'!$D:$D, ">=01/05/2026", 'Lista Movimenti'!$D:$D, "<=31/05/2026") -> 500 | G38: =SUMIFS('Lista Movimenti'!$C:$C, 'Lista Movimenti'!$B:$B, $A38, 'Lista Movimenti'!$E:$E, "Risparmio", 'Lista Movimenti'!$D:$D, ">=01/06/2026", 'Lista Movimenti'!$D:$D, "<=30/06/2026") -> 0 | H38: =SUMIFS('Lista Movimenti'!$C:$C, 'Lista Movimenti'!$B:$B, $A38, 'Lista Movimenti'!$E:$E, "Risparmio", 'Lista Movimenti'!$D:$D, ">=01/07/2026", 'Lista Movimenti'!$D:$D, "<=31/07/2026") -> 0 | I38: =SUMIFS('Lista Movimenti'!$C:$C, 'Lista Movimenti'!$B:$B, $A38, 'Lista Movimenti'!$E:$E, "Risparmio", 'Lista Movimenti'!$D:$D, ">=01/08/2026", 'Lista Movimenti'!$D:$D, "<=31/08/2026") -> 0 | J38: =SUMIFS('Lista Movimenti'!$C:$C, 'Lista Movimenti'!$B:$B, $A38, 'Lista Movimenti'!$E:$E, "Risparmio", 'Lista Movimenti'!$D:$D, ">=01/09/2026", 'Lista Movimenti'!$D:$D, "<=30/09/2026") -> 230 | K38: =SUMIFS('Lista Movimenti'!$C:$C, 'Lista Movimenti'!$B:$B, $A38, 'Lista Movimenti'!$E:$E, "Risparmio", 'Lista Movimenti'!$D:$D, ">=01/10/2026", 'Lista Movimenti'!$D:$D, "<=31/10/2026") -> 115 | L38: =SUMIFS('Lista Movimenti'!$C:$C, 'Lista Movimenti'!$B:$B, $A38, 'Lista Movimenti'!$E:$E, "Risparmio", 'Lista Movimenti'!$D:$D, ">=01/11/2026", 'Lista Movimenti'!$D:$D, "<=30/11/2026") -> 0 | M38: =SUMIFS('Lista Movimenti'!$C:$C, 'Lista Movimenti'!$B:$B, $A38, 'Lista Movimenti'!$E:$E, "Risparmio", 'Lista Movimenti'!$D:$D, ">=01/12/2026", 'Lista Movimenti'!$D:$D, "<=31/12/2026") -> 250 | N38: =AVERAGE(B38:M38) -> 116.25
A39: 🍲 Cibo/Spesa | B39: =SUMIFS('Lista Movimenti'!C:C, 'Lista Movimenti'!B:B, A39, 'Lista Movimenti'!E:E, "Risparmio", 'Lista Movimenti'!D:D, ">=01/01/2026", 'Lista Movimenti'!D:D, "<=31/01/2026") -> 0 | C39: =SUMIFS('Lista Movimenti'!$C:$C, 'Lista Movimenti'!$B:$B, $A39, 'Lista Movimenti'!$E:$E, "Risparmio", 'Lista Movimenti'!$D:$D, ">=01/02/2026", 'Lista Movimenti'!$D:$D, "<=28/02/2026") -> 0 | D39: =SUMIFS('Lista Movimenti'!$C:$C, 'Lista Movimenti'!$B:$B, $A39, 'Lista Movimenti'!$E:$E, "Risparmio", 'Lista Movimenti'!$D:$D, ">=01/03/2026", 'Lista Movimenti'!$D:$D, "<=31/03/2026") -> 0 | E39: =SUMIFS('Lista Movimenti'!$C:$C, 'Lista Movimenti'!$B:$B, $A39, 'Lista Movimenti'!$E:$E, "Risparmio", 'Lista Movimenti'!$D:$D, ">=01/04/2026", 'Lista Movimenti'!$D:$D, "<=30/04/2026") -> 0 | F39: =SUMIFS('Lista Movimenti'!$C:$C, 'Lista Movimenti'!$B:$B, $A39, 'Lista Movimenti'!$E:$E, "Risparmio", 'Lista Movimenti'!$D:$D, ">=01/05/2026", 'Lista Movimenti'!$D:$D, "<=31/05/2026") -> 0 | G39: =SUMIFS('Lista Movimenti'!$C:$C, 'Lista Movimenti'!$B:$B, $A39, 'Lista Movimenti'!$E:$E, "Risparmio", 'Lista Movimenti'!$D:$D, ">=01/06/2026", 'Lista Movimenti'!$D:$D, "<=30/06/2026") -> 0 | H39: =SUMIFS('Lista Movimenti'!$C:$C, 'Lista Movimenti'!$B:$B, $A39, 'Lista Movimenti'!$E:$E, "Risparmio", 'Lista Movimenti'!$D:$D, ">=01/07/2026", 'Lista Movimenti'!$D:$D, "<=31/07/2026") -> 0 | I39: =SUMIFS('Lista Movimenti'!$C:$C, 'Lista Movimenti'!$B:$B, $A39, 'Lista Movimenti'!$E:$E, "Risparmio", 'Lista Movimenti'!$D:$D, ">=01/08/2026", 'Lista Movimenti'!$D:$D, "<=31/08/2026") -> 0 | J39: =SUMIFS('Lista Movimenti'!$C:$C, 'Lista Movimenti'!$B:$B, $A39, 'Lista Movimenti'!$E:$E, "Risparmio", 'Lista Movimenti'!$D:$D, ">=01/09/2026", 'Lista Movimenti'!$D:$D, "<=30/09/2026") -> 0 | K39: =SUMIFS('Lista Movimenti'!$C:$C, 'Lista Movimenti'!$B:$B, $A39, 'Lista Movimenti'!$E:$E, "Risparmio", 'Lista Movimenti'!$D:$D, ">=01/10/2026", 'Lista Movimenti'!$D:$D, "<=31/10/2026") -> 0 | L39: =SUMIFS('Lista Movimenti'!$C:$C, 'Lista Movimenti'!$B:$B, $A39, 'Lista Movimenti'!$E:$E, "Risparmio", 'Lista Movimenti'!$D:$D, ">=01/11/2026", 'Lista Movimenti'!$D:$D, "<=30/11/2026") -> 0 | M39: =SUMIFS('Lista Movimenti'!$C:$C, 'Lista Movimenti'!$B:$B, $A39, 'Lista Movimenti'!$E:$E, "Risparmio", 'Lista Movimenti'!$D:$D, ">=01/12/2026", 'Lista Movimenti'!$D:$D, "<=31/12/2026") -> 0 | N39: =AVERAGE(B39:M39) -> 0
A40: 🚑 Sanità | B40: =SUMIFS('Lista Movimenti'!C:C, 'Lista Movimenti'!B:B, A40, 'Lista Movimenti'!E:E, "Risparmio", 'Lista Movimenti'!D:D, ">=01/01/2026", 'Lista Movimenti'!D:D, "<=31/01/2026") -> 0 | C40: =SUMIFS('Lista Movimenti'!$C:$C, 'Lista Movimenti'!$B:$B, $A40, 'Lista Movimenti'!$E:$E, "Risparmio", 'Lista Movimenti'!$D:$D, ">=01/02/2026", 'Lista Movimenti'!$D:$D, "<=28/02/2026") -> 0 | D40: =SUMIFS('Lista Movimenti'!$C:$C, 'Lista Movimenti'!$B:$B, $A40, 'Lista Movimenti'!$E:$E, "Risparmio", 'Lista Movimenti'!$D:$D, ">=01/03/2026", 'Lista Movimenti'!$D:$D, "<=31/03/2026") -> 0 | E40: =SUMIFS('Lista Movimenti'!$C:$C, 'Lista Movimenti'!$B:$B, $A40, 'Lista Movimenti'!$E:$E, "Risparmio", 'Lista Movimenti'!$D:$D, ">=01/04/2026", 'Lista Movimenti'!$D:$D, "<=30/04/2026") -> 0 | F40: =SUMIFS('Lista Movimenti'!$C:$C, 'Lista Movimenti'!$B:$B, $A40, 'Lista Movimenti'!$E:$E, "Risparmio", 'Lista Movimenti'!$D:$D, ">=01/05/2026", 'Lista Movimenti'!$D:$D, "<=31/05/2026") -> 0 | G40: =SUMIFS('Lista Movimenti'!$C:$C, 'Lista Movimenti'!$B:$B, $A40, 'Lista Movimenti'!$E:$E, "Risparmio", 'Lista Movimenti'!$D:$D, ">=01/06/2026", 'Lista Movimenti'!$D:$D, "<=30/06/2026") -> 0 | H40: =SUMIFS('Lista Movimenti'!$C:$C, 'Lista Movimenti'!$B:$B, $A40, 'Lista Movimenti'!$E:$E, "Risparmio", 'Lista Movimenti'!$D:$D, ">=01/07/2026", 'Lista Movimenti'!$D:$D, "<=31/07/2026") -> 0 | I40: =SUMIFS('Lista Movimenti'!$C:$C, 'Lista Movimenti'!$B:$B, $A40, 'Lista Movimenti'!$E:$E, "Risparmio", 'Lista Movimenti'!$D:$D, ">=01/08/2026", 'Lista Movimenti'!$D:$D, "<=31/08/2026") -> 0 | J40: =SUMIFS('Lista Movimenti'!$C:$C, 'Lista Movimenti'!$B:$B, $A40, 'Lista Movimenti'!$E:$E, "Risparmio", 'Lista Movimenti'!$D:$D, ">=01/09/2026", 'Lista Movimenti'!$D:$D, "<=30/09/2026") -> 0 | K40: =SUMIFS('Lista Movimenti'!$C:$C, 'Lista Movimenti'!$B:$B, $A40, 'Lista Movimenti'!$E:$E, "Risparmio", 'Lista Movimenti'!$D:$D, ">=01/10/2026", 'Lista Movimenti'!$D:$D, "<=31/10/2026") -> 0 | L40: =SUMIFS('Lista Movimenti'!$C:$C, 'Lista Movimenti'!$B:$B, $A40, 'Lista Movimenti'!$E:$E, "Risparmio", 'Lista Movimenti'!$D:$D, ">=01/11/2026", 'Lista Movimenti'!$D:$D, "<=30/11/2026") -> 0 | M40: =SUMIFS('Lista Movimenti'!$C:$C, 'Lista Movimenti'!$B:$B, $A40, 'Lista Movimenti'!$E:$E, "Risparmio", 'Lista Movimenti'!$D:$D, ">=01/12/2026", 'Lista Movimenti'!$D:$D, "<=31/12/2026") -> 0 | N40: =AVERAGE(B40:M40) -> 0
A41: 🏋️ Palestra e affini | B41: =SUMIFS('Lista Movimenti'!C:C, 'Lista Movimenti'!B:B, A41, 'Lista Movimenti'!E:E, "Risparmio", 'Lista Movimenti'!D:D, ">=01/01/2026", 'Lista Movimenti'!D:D, "<=31/01/2026") -> 0 | C41: =SUMIFS('Lista Movimenti'!$C:$C, 'Lista Movimenti'!$B:$B, $A41, 'Lista Movimenti'!$E:$E, "Risparmio", 'Lista Movimenti'!$D:$D, ">=01/02/2026", 'Lista Movimenti'!$D:$D, "<=28/02/2026") -> 0 | D41: =SUMIFS('Lista Movimenti'!$C:$C, 'Lista Movimenti'!$B:$B, $A41, 'Lista Movimenti'!$E:$E, "Risparmio", 'Lista Movimenti'!$D:$D, ">=01/03/2026", 'Lista Movimenti'!$D:$D, "<=31/03/2026") -> 0 | E41: =SUMIFS('Lista Movimenti'!$C:$C, 'Lista Movimenti'!$B:$B, $A41, 'Lista Movimenti'!$E:$E, "Risparmio", 'Lista Movimenti'!$D:$D, ">=01/04/2026", 'Lista Movimenti'!$D:$D, "<=30/04/2026") -> 0 | F41: =SUMIFS('Lista Movimenti'!$C:$C, 'Lista Movimenti'!$B:$B, $A41, 'Lista Movimenti'!$E:$E, "Risparmio", 'Lista Movimenti'!$D:$D, ">=01/05/2026", 'Lista Movimenti'!$D:$D, "<=31/05/2026") -> 0 | G41: =SUMIFS('Lista Movimenti'!$C:$C, 'Lista Movimenti'!$B:$B, $A41, 'Lista Movimenti'!$E:$E, "Risparmio", 'Lista Movimenti'!$D:$D, ">=01/06/2026", 'Lista Movimenti'!$D:$D, "<=30/06/2026") -> 0 | H41: =SUMIFS('Lista Movimenti'!$C:$C, 'Lista Movimenti'!$B:$B, $A41, 'Lista Movimenti'!$E:$E, "Risparmio", 'Lista Movimenti'!$D:$D, ">=01/07/2026", 'Lista Movimenti'!$D:$D, "<=31/07/2026") -> 0 | I41: =SUMIFS('Lista Movimenti'!$C:$C, 'Lista Movimenti'!$B:$B, $A41, 'Lista Movimenti'!$E:$E, "Risparmio", 'Lista Movimenti'!$D:$D, ">=01/08/2026", 'Lista Movimenti'!$D:$D, "<=31/08/2026") -> 0 | J41: =SUMIFS('Lista Movimenti'!$C:$C, 'Lista Movimenti'!$B:$B, $A41, 'Lista Movimenti'!$E:$E, "Risparmio", 'Lista Movimenti'!$D:$D, ">=01/09/2026", 'Lista Movimenti'!$D:$D, "<=30/09/2026") -> 0 | K41: =SUMIFS('Lista Movimenti'!$C:$C, 'Lista Movimenti'!$B:$B, $A41, 'Lista Movimenti'!$E:$E, "Risparmio", 'Lista Movimenti'!$D:$D, ">=01/10/2026", 'Lista Movimenti'!$D:$D, "<=31/10/2026") -> 1500 | L41: =SUMIFS('Lista Movimenti'!$C:$C, 'Lista Movimenti'!$B:$B, $A41, 'Lista Movimenti'!$E:$E, "Risparmio", 'Lista Movimenti'!$D:$D, ">=01/11/2026", 'Lista Movimenti'!$D:$D, "<=30/11/2026") -> 0 | M41: =SUMIFS('Lista Movimenti'!$C:$C, 'Lista Movimenti'!$B:$B, $A41, 'Lista Movimenti'!$E:$E, "Risparmio", 'Lista Movimenti'!$D:$D, ">=01/12/2026", 'Lista Movimenti'!$D:$D, "<=31/12/2026") -> 0 | N41: =AVERAGE(B41:M41) -> 125
A42: 📱 Telefono | B42: =SUMIFS('Lista Movimenti'!C:C, 'Lista Movimenti'!B:B, A42, 'Lista Movimenti'!E:E, "Risparmio", 'Lista Movimenti'!D:D, ">=01/01/2026", 'Lista Movimenti'!D:D, "<=31/01/2026") -> 0 | C42: =SUMIFS('Lista Movimenti'!$C:$C, 'Lista Movimenti'!$B:$B, $A42, 'Lista Movimenti'!$E:$E, "Risparmio", 'Lista Movimenti'!$D:$D, ">=01/02/2026", 'Lista Movimenti'!$D:$D, "<=28/02/2026") -> 0 | D42: =SUMIFS('Lista Movimenti'!$C:$C, 'Lista Movimenti'!$B:$B, $A42, 'Lista Movimenti'!$E:$E, "Risparmio", 'Lista Movimenti'!$D:$D, ">=01/03/2026", 'Lista Movimenti'!$D:$D, "<=31/03/2026") -> 0 | E42: =SUMIFS('Lista Movimenti'!$C:$C, 'Lista Movimenti'!$B:$B, $A42, 'Lista Movimenti'!$E:$E, "Risparmio", 'Lista Movimenti'!$D:$D, ">=01/04/2026", 'Lista Movimenti'!$D:$D, "<=30/04/2026") -> 0 | F42: =SUMIFS('Lista Movimenti'!$C:$C, 'Lista Movimenti'!$B:$B, $A42, 'Lista Movimenti'!$E:$E, "Risparmio", 'Lista Movimenti'!$D:$D, ">=01/05/2026", 'Lista Movimenti'!$D:$D, "<=31/05/2026") -> 0 | G42: =SUMIFS('Lista Movimenti'!$C:$C, 'Lista Movimenti'!$B:$B, $A42, 'Lista Movimenti'!$E:$E, "Risparmio", 'Lista Movimenti'!$D:$D, ">=01/06/2026", 'Lista Movimenti'!$D:$D, "<=30/06/2026") -> 0 | H42: =SUMIFS('Lista Movimenti'!$C:$C, 'Lista Movimenti'!$B:$B, $A42, 'Lista Movimenti'!$E:$E, "Risparmio", 'Lista Movimenti'!$D:$D, ">=01/07/2026", 'Lista Movimenti'!$D:$D, "<=31/07/2026") -> 0 | I42: =SUMIFS('Lista Movimenti'!$C:$C, 'Lista Movimenti'!$B:$B, $A42, 'Lista Movimenti'!$E:$E, "Risparmio", 'Lista Movimenti'!$D:$D, ">=01/08/2026", 'Lista Movimenti'!$D:$D, "<=31/08/2026") -> 0 | J42: =SUMIFS('Lista Movimenti'!$C:$C, 'Lista Movimenti'!$B:$B, $A42, 'Lista Movimenti'!$E:$E, "Risparmio", 'Lista Movimenti'!$D:$D, ">=01/09/2026", 'Lista Movimenti'!$D:$D, "<=30/09/2026") -> 0 | K42: =SUMIFS('Lista Movimenti'!$C:$C, 'Lista Movimenti'!$B:$B, $A42, 'Lista Movimenti'!$E:$E, "Risparmio", 'Lista Movimenti'!$D:$D, ">=01/10/2026", 'Lista Movimenti'!$D:$D, "<=31/10/2026") -> 0 | L42: =SUMIFS('Lista Movimenti'!$C:$C, 'Lista Movimenti'!$B:$B, $A42, 'Lista Movimenti'!$E:$E, "Risparmio", 'Lista Movimenti'!$D:$D, ">=01/11/2026", 'Lista Movimenti'!$D:$D, "<=30/11/2026") -> 0 | M42: =SUMIFS('Lista Movimenti'!$C:$C, 'Lista Movimenti'!$B:$B, $A42, 'Lista Movimenti'!$E:$E, "Risparmio", 'Lista Movimenti'!$D:$D, ">=01/12/2026", 'Lista Movimenti'!$D:$D, "<=31/12/2026") -> 0 | N42: =AVERAGE(B42:M42) -> 0
A43: 🚌 Trasporti | B43: =SUMIFS('Lista Movimenti'!C:C, 'Lista Movimenti'!B:B, A43, 'Lista Movimenti'!E:E, "Risparmio", 'Lista Movimenti'!D:D, ">=01/01/2026", 'Lista Movimenti'!D:D, "<=31/01/2026") -> 0 | C43: =SUMIFS('Lista Movimenti'!$C:$C, 'Lista Movimenti'!$B:$B, $A43, 'Lista Movimenti'!$E:$E, "Risparmio", 'Lista Movimenti'!$D:$D, ">=01/02/2026", 'Lista Movimenti'!$D:$D, "<=28/02/2026") -> 0 | D43: =SUMIFS('Lista Movimenti'!$C:$C, 'Lista Movimenti'!$B:$B, $A43, 'Lista Movimenti'!$E:$E, "Risparmio", 'Lista Movimenti'!$D:$D, ">=01/03/2026", 'Lista Movimenti'!$D:$D, "<=31/03/2026") -> 0 | E43: =SUMIFS('Lista Movimenti'!$C:$C, 'Lista Movimenti'!$B:$B, $A43, 'Lista Movimenti'!$E:$E, "Risparmio", 'Lista Movimenti'!$D:$D, ">=01/04/2026", 'Lista Movimenti'!$D:$D, "<=30/04/2026") -> 0 | F43: =SUMIFS('Lista Movimenti'!$C:$C, 'Lista Movimenti'!$B:$B, $A43, 'Lista Movimenti'!$E:$E, "Risparmio", 'Lista Movimenti'!$D:$D, ">=01/05/2026", 'Lista Movimenti'!$D:$D, "<=31/05/2026") -> 0 | G43: =SUMIFS('Lista Movimenti'!$C:$C, 'Lista Movimenti'!$B:$B, $A43, 'Lista Movimenti'!$E:$E, "Risparmio", 'Lista Movimenti'!$D:$D, ">=01/06/2026", 'Lista Movimenti'!$D:$D, "<=30/06/2026") -> 0 | H43: =SUMIFS('Lista Movimenti'!$C:$C, 'Lista Movimenti'!$B:$B, $A43, 'Lista Movimenti'!$E:$E, "Risparmio", 'Lista Movimenti'!$D:$D, ">=01/07/2026", 'Lista Movimenti'!$D:$D, "<=31/07/2026") -> 0 | I43: =SUMIFS('Lista Movimenti'!$C:$C, 'Lista Movimenti'!$B:$B, $A43, 'Lista Movimenti'!$E:$E, "Risparmio", 'Lista Movimenti'!$D:$D, ">=01/08/2026", 'Lista Movimenti'!$D:$D, "<=31/08/2026") -> 0 | J43: =SUMIFS('Lista Movimenti'!$C:$C, 'Lista Movimenti'!$B:$B, $A43, 'Lista Movimenti'!$E:$E, "Risparmio", 'Lista Movimenti'!$D:$D, ">=01/09/2026", 'Lista Movimenti'!$D:$D, "<=30/09/2026") -> 0 | K43: =SUMIFS('Lista Movimenti'!$C:$C, 'Lista Movimenti'!$B:$B, $A43, 'Lista Movimenti'!$E:$E, "Risparmio", 'Lista Movimenti'!$D:$D, ">=01/10/2026", 'Lista Movimenti'!$D:$D, "<=31/10/2026") -> 0 | L43: =SUMIFS('Lista Movimenti'!$C:$C, 'Lista Movimenti'!$B:$B, $A43, 'Lista Movimenti'!$E:$E, "Risparmio", 'Lista Movimenti'!$D:$D, ">=01/11/2026", 'Lista Movimenti'!$D:$D, "<=30/11/2026") -> 0 | M43: =SUMIFS('Lista Movimenti'!$C:$C, 'Lista Movimenti'!$B:$B, $A43, 'Lista Movimenti'!$E:$E, "Risparmio", 'Lista Movimenti'!$D:$D, ">=01/12/2026", 'Lista Movimenti'!$D:$D, "<=31/12/2026") -> 0 | N43: =AVERAGE(B43:M43) -> 0
A44: 👕 Vestiti | B44: =SUMIFS('Lista Movimenti'!C:C, 'Lista Movimenti'!B:B, A44, 'Lista Movimenti'!E:E, "Risparmio", 'Lista Movimenti'!D:D, ">=01/01/2026", 'Lista Movimenti'!D:D, "<=31/01/2026") -> 0 | C44: =SUMIFS('Lista Movimenti'!$C:$C, 'Lista Movimenti'!$B:$B, $A44, 'Lista Movimenti'!$E:$E, "Risparmio", 'Lista Movimenti'!$D:$D, ">=01/02/2026", 'Lista Movimenti'!$D:$D, "<=28/02/2026") -> 0 | D44: =SUMIFS('Lista Movimenti'!$C:$C, 'Lista Movimenti'!$B:$B, $A44, 'Lista Movimenti'!$E:$E, "Risparmio", 'Lista Movimenti'!$D:$D, ">=01/03/2026", 'Lista Movimenti'!$D:$D, "<=31/03/2026") -> 0 | E44: =SUMIFS('Lista Movimenti'!$C:$C, 'Lista Movimenti'!$B:$B, $A44, 'Lista Movimenti'!$E:$E, "Risparmio", 'Lista Movimenti'!$D:$D, ">=01/04/2026", 'Lista Movimenti'!$D:$D, "<=30/04/2026") -> 0 | F44: =SUMIFS('Lista Movimenti'!$C:$C, 'Lista Movimenti'!$B:$B, $A44, 'Lista Movimenti'!$E:$E, "Risparmio", 'Lista Movimenti'!$D:$D, ">=01/05/2026", 'Lista Movimenti'!$D:$D, "<=31/05/2026") -> 0 | G44: =SUMIFS('Lista Movimenti'!$C:$C, 'Lista Movimenti'!$B:$B, $A44, 'Lista Movimenti'!$E:$E, "Risparmio", 'Lista Movimenti'!$D:$D, ">=01/06/2026", 'Lista Movimenti'!$D:$D, "<=30/06/2026") -> 0 | H44: =SUMIFS('Lista Movimenti'!$C:$C, 'Lista Movimenti'!$B:$B, $A44, 'Lista Movimenti'!$E:$E, "Risparmio", 'Lista Movimenti'!$D:$D, ">=01/07/2026", 'Lista Movimenti'!$D:$D, "<=31/07/2026") -> 0 | I44: =SUMIFS('Lista Movimenti'!$C:$C, 'Lista Movimenti'!$B:$B, $A44, 'Lista Movimenti'!$E:$E, "Risparmio", 'Lista Movimenti'!$D:$D, ">=01/08/2026", 'Lista Movimenti'!$D:$D, "<=31/08/2026") -> 0 | J44: =SUMIFS('Lista Movimenti'!$C:$C, 'Lista Movimenti'!$B:$B, $A44, 'Lista Movimenti'!$E:$E, "Risparmio", 'Lista Movimenti'!$D:$D, ">=01/09/2026", 'Lista Movimenti'!$D:$D, "<=30/09/2026") -> 0 | K44: =SUMIFS('Lista Movimenti'!$C:$C, 'Lista Movimenti'!$B:$B, $A44, 'Lista Movimenti'!$E:$E, "Risparmio", 'Lista Movimenti'!$D:$D, ">=01/10/2026", 'Lista Movimenti'!$D:$D, "<=31/10/2026") -> 0 | L44: =SUMIFS('Lista Movimenti'!$C:$C, 'Lista Movimenti'!$B:$B, $A44, 'Lista Movimenti'!$E:$E, "Risparmio", 'Lista Movimenti'!$D:$D, ">=01/11/2026", 'Lista Movimenti'!$D:$D, "<=30/11/2026") -> 0 | M44: =SUMIFS('Lista Movimenti'!$C:$C, 'Lista Movimenti'!$B:$B, $A44, 'Lista Movimenti'!$E:$E, "Risparmio", 'Lista Movimenti'!$D:$D, ">=01/12/2026", 'Lista Movimenti'!$D:$D, "<=31/12/2026") -> 0 | N44: =AVERAGE(B44:M44) -> 0
A45: 🎫 Abbonamenti | B45: =SUMIFS('Lista Movimenti'!C:C, 'Lista Movimenti'!B:B, A45, 'Lista Movimenti'!E:E, "Risparmio", 'Lista Movimenti'!D:D, ">=01/01/2026", 'Lista Movimenti'!D:D, "<=31/01/2026") -> 0 | C45: =SUMIFS('Lista Movimenti'!$C:$C, 'Lista Movimenti'!$B:$B, $A45, 'Lista Movimenti'!$E:$E, "Risparmio", 'Lista Movimenti'!$D:$D, ">=01/02/2026", 'Lista Movimenti'!$D:$D, "<=28/02/2026") -> 0 | D45: =SUMIFS('Lista Movimenti'!$C:$C, 'Lista Movimenti'!$B:$B, $A45, 'Lista Movimenti'!$E:$E, "Risparmio", 'Lista Movimenti'!$D:$D, ">=01/03/2026", 'Lista Movimenti'!$D:$D, "<=31/03/2026") -> 0 | E45: =SUMIFS('Lista Movimenti'!$C:$C, 'Lista Movimenti'!$B:$B, $A45, 'Lista Movimenti'!$E:$E, "Risparmio", 'Lista Movimenti'!$D:$D, ">=01/04/2026", 'Lista Movimenti'!$D:$D, "<=30/04/2026") -> 0 | F45: =SUMIFS('Lista Movimenti'!$C:$C, 'Lista Movimenti'!$B:$B, $A45, 'Lista Movimenti'!$E:$E, "Risparmio", 'Lista Movimenti'!$D:$D, ">=01/05/2026", 'Lista Movimenti'!$D:$D, "<=31/05/2026") -> 0 | G45: =SUMIFS('Lista Movimenti'!$C:$C, 'Lista Movimenti'!$B:$B, $A45, 'Lista Movimenti'!$E:$E, "Risparmio", 'Lista Movimenti'!$D:$D, ">=01/06/2026", 'Lista Movimenti'!$D:$D, "<=30/06/2026") -> 0 | H45: =SUMIFS('Lista Movimenti'!$C:$C, 'Lista Movimenti'!$B:$B, $A45, 'Lista Movimenti'!$E:$E, "Risparmio", 'Lista Movimenti'!$D:$D, ">=01/07/2026", 'Lista Movimenti'!$D:$D, "<=31/07/2026") -> 0 | I45: =SUMIFS('Lista Movimenti'!$C:$C, 'Lista Movimenti'!$B:$B, $A45, 'Lista Movimenti'!$E:$E, "Risparmio", 'Lista Movimenti'!$D:$D, ">=01/08/2026", 'Lista Movimenti'!$D:$D, "<=31/08/2026") -> 0 | J45: =SUMIFS('Lista Movimenti'!$C:$C, 'Lista Movimenti'!$B:$B, $A45, 'Lista Movimenti'!$E:$E, "Risparmio", 'Lista Movimenti'!$D:$D, ">=01/09/2026", 'Lista Movimenti'!$D:$D, "<=30/09/2026") -> 0 | K45: =SUMIFS('Lista Movimenti'!$C:$C, 'Lista Movimenti'!$B:$B, $A45, 'Lista Movimenti'!$E:$E, "Risparmio", 'Lista Movimenti'!$D:$D, ">=01/10/2026", 'Lista Movimenti'!$D:$D, "<=31/10/2026") -> 0 | L45: =SUMIFS('Lista Movimenti'!$C:$C, 'Lista Movimenti'!$B:$B, $A45, 'Lista Movimenti'!$E:$E, "Risparmio", 'Lista Movimenti'!$D:$D, ">=01/11/2026", 'Lista Movimenti'!$D:$D, "<=30/11/2026") -> 0 | M45: =SUMIFS('Lista Movimenti'!$C:$C, 'Lista Movimenti'!$B:$B, $A45, 'Lista Movimenti'!$E:$E, "Risparmio", 'Lista Movimenti'!$D:$D, ">=01/12/2026", 'Lista Movimenti'!$D:$D, "<=31/12/2026") -> 0 | N45: =AVERAGE(B45:M45) -> 0
A46: 🍔 Cibo fuori | B46: =SUMIFS('Lista Movimenti'!C:C, 'Lista Movimenti'!B:B, A46, 'Lista Movimenti'!E:E, "Risparmio", 'Lista Movimenti'!D:D, ">=01/01/2026", 'Lista Movimenti'!D:D, "<=31/01/2026") -> 0 | C46: =SUMIFS('Lista Movimenti'!$C:$C, 'Lista Movimenti'!$B:$B, $A46, 'Lista Movimenti'!$E:$E, "Risparmio", 'Lista Movimenti'!$D:$D, ">=01/02/2026", 'Lista Movimenti'!$D:$D, "<=28/02/2026") -> 0 | D46: =SUMIFS('Lista Movimenti'!$C:$C, 'Lista Movimenti'!$B:$B, $A46, 'Lista Movimenti'!$E:$E, "Risparmio", 'Lista Movimenti'!$D:$D, ">=01/03/2026", 'Lista Movimenti'!$D:$D, "<=31/03/2026") -> 0 | E46: =SUMIFS('Lista Movimenti'!$C:$C, 'Lista Movimenti'!$B:$B, $A46, 'Lista Movimenti'!$E:$E, "Risparmio", 'Lista Movimenti'!$D:$D, ">=01/04/2026", 'Lista Movimenti'!$D:$D, "<=30/04/2026") -> 0 | F46: =SUMIFS('Lista Movimenti'!$C:$C, 'Lista Movimenti'!$B:$B, $A46, 'Lista Movimenti'!$E:$E, "Risparmio", 'Lista Movimenti'!$D:$D, ">=01/05/2026", 'Lista Movimenti'!$D:$D, "<=31/05/2026") -> 0 | G46: =SUMIFS('Lista Movimenti'!$C:$C, 'Lista Movimenti'!$B:$B, $A46, 'Lista Movimenti'!$E:$E, "Risparmio", 'Lista Movimenti'!$D:$D, ">=01/06/2026", 'Lista Movimenti'!$D:$D, "<=30/06/2026") -> 0 | H46: =SUMIFS('Lista Movimenti'!$C:$C, 'Lista Movimenti'!$B:$B, $A46, 'Lista Movimenti'!$E:$E, "Risparmio", 'Lista Movimenti'!$D:$D, ">=01/07/2026", 'Lista Movimenti'!$D:$D, "<=31/07/2026") -> 0 | I46: =SUMIFS('Lista Movimenti'!$C:$C, 'Lista Movimenti'!$B:$B, $A46, 'Lista Movimenti'!$E:$E, "Risparmio", 'Lista Movimenti'!$D:$D, ">=01/08/2026", 'Lista Movimenti'!$D:$D, "<=31/08/2026") -> 0 | J46: =SUMIFS('Lista Movimenti'!$C:$C, 'Lista Movimenti'!$B:$B, $A46, 'Lista Movimenti'!$E:$E, "Risparmio", 'Lista Movimenti'!$D:$D, ">=01/09/2026", 'Lista Movimenti'!$D:$D, "<=30/09/2026") -> 0 | K46: =SUMIFS('Lista Movimenti'!$C:$C, 'Lista Movimenti'!$B:$B, $A46, 'Lista Movimenti'!$E:$E, "Risparmio", 'Lista Movimenti'!$D:$D, ">=01/10/2026", 'Lista Movimenti'!$D:$D, "<=31/10/2026") -> 0 | L46: =SUMIFS('Lista Movimenti'!$C:$C, 'Lista Movimenti'!$B:$B, $A46, 'Lista Movimenti'!$E:$E, "Risparmio", 'Lista Movimenti'!$D:$D, ">=01/11/2026", 'Lista Movimenti'!$D:$D, "<=30/11/2026") -> 0 | M46: =SUMIFS('Lista Movimenti'!$C:$C, 'Lista Movimenti'!$B:$B, $A46, 'Lista Movimenti'!$E:$E, "Risparmio", 'Lista Movimenti'!$D:$D, ">=01/12/2026", 'Lista Movimenti'!$D:$D, "<=31/12/2026") -> 0 | N46: =AVERAGE(B46:M46) -> 0
A47: 🎬 Intrattenimento | B47: =SUMIFS('Lista Movimenti'!C:C, 'Lista Movimenti'!B:B, A47, 'Lista Movimenti'!E:E, "Risparmio", 'Lista Movimenti'!D:D, ">=01/01/2026", 'Lista Movimenti'!D:D, "<=31/01/2026") -> 0 | C47: =SUMIFS('Lista Movimenti'!$C:$C, 'Lista Movimenti'!$B:$B, $A47, 'Lista Movimenti'!$E:$E, "Risparmio", 'Lista Movimenti'!$D:$D, ">=01/02/2026", 'Lista Movimenti'!$D:$D, "<=28/02/2026") -> 0 | D47: =SUMIFS('Lista Movimenti'!$C:$C, 'Lista Movimenti'!$B:$B, $A47, 'Lista Movimenti'!$E:$E, "Risparmio", 'Lista Movimenti'!$D:$D, ">=01/03/2026", 'Lista Movimenti'!$D:$D, "<=31/03/2026") -> 0 | E47: =SUMIFS('Lista Movimenti'!$C:$C, 'Lista Movimenti'!$B:$B, $A47, 'Lista Movimenti'!$E:$E, "Risparmio", 'Lista Movimenti'!$D:$D, ">=01/04/2026", 'Lista Movimenti'!$D:$D, "<=30/04/2026") -> 0 | F47: =SUMIFS('Lista Movimenti'!$C:$C, 'Lista Movimenti'!$B:$B, $A47, 'Lista Movimenti'!$E:$E, "Risparmio", 'Lista Movimenti'!$D:$D, ">=01/05/2026", 'Lista Movimenti'!$D:$D, "<=31/05/2026") -> 0 | G47: =SUMIFS('Lista Movimenti'!$C:$C, 'Lista Movimenti'!$B:$B, $A47, 'Lista Movimenti'!$E:$E, "Risparmio", 'Lista Movimenti'!$D:$D, ">=01/06/2026", 'Lista Movimenti'!$D:$D, "<=30/06/2026") -> 0 | H47: =SUMIFS('Lista Movimenti'!$C:$C, 'Lista Movimenti'!$B:$B, $A47, 'Lista Movimenti'!$E:$E, "Risparmio", 'Lista Movimenti'!$D:$D, ">=01/07/2026", 'Lista Movimenti'!$D:$D, "<=31/07/2026") -> 0 | I47: =SUMIFS('Lista Movimenti'!$C:$C, 'Lista Movimenti'!$B:$B, $A47, 'Lista Movimenti'!$E:$E, "Risparmio", 'Lista Movimenti'!$D:$D, ">=01/08/2026", 'Lista Movimenti'!$D:$D, "<=31/08/2026") -> 0 | J47: =SUMIFS('Lista Movimenti'!$C:$C, 'Lista Movimenti'!$B:$B, $A47, 'Lista Movimenti'!$E:$E, "Risparmio", 'Lista Movimenti'!$D:$D, ">=01/09/2026", 'Lista Movimenti'!$D:$D, "<=30/09/2026") -> 0 | K47: =SUMIFS('Lista Movimenti'!$C:$C, 'Lista Movimenti'!$B:$B, $A47, 'Lista Movimenti'!$E:$E, "Risparmio", 'Lista Movimenti'!$D:$D, ">=01/10/2026", 'Lista Movimenti'!$D:$D, "<=31/10/2026") -> 0 | L47: =SUMIFS('Lista Movimenti'!$C:$C, 'Lista Movimenti'!$B:$B, $A47, 'Lista Movimenti'!$E:$E, "Risparmio", 'Lista Movimenti'!$D:$D, ">=01/11/2026", 'Lista Movimenti'!$D:$D, "<=30/11/2026") -> 0 | M47: =SUMIFS('Lista Movimenti'!$C:$C, 'Lista Movimenti'!$B:$B, $A47, 'Lista Movimenti'!$E:$E, "Risparmio", 'Lista Movimenti'!$D:$D, ">=01/12/2026", 'Lista Movimenti'!$D:$D, "<=31/12/2026") -> 0 | N47: =AVERAGE(B47:M47) -> 0
A48: 🎁 Regali | B48: =SUMIFS('Lista Movimenti'!C:C, 'Lista Movimenti'!B:B, A48, 'Lista Movimenti'!E:E, "Risparmio", 'Lista Movimenti'!D:D, ">=01/01/2026", 'Lista Movimenti'!D:D, "<=31/01/2026") -> 0 | C48: =SUMIFS('Lista Movimenti'!$C:$C, 'Lista Movimenti'!$B:$B, $A48, 'Lista Movimenti'!$E:$E, "Risparmio", 'Lista Movimenti'!$D:$D, ">=01/02/2026", 'Lista Movimenti'!$D:$D, "<=28/02/2026") -> 0 | D48: =SUMIFS('Lista Movimenti'!$C:$C, 'Lista Movimenti'!$B:$B, $A48, 'Lista Movimenti'!$E:$E, "Risparmio", 'Lista Movimenti'!$D:$D, ">=01/03/2026", 'Lista Movimenti'!$D:$D, "<=31/03/2026") -> 0 | E48: =SUMIFS('Lista Movimenti'!$C:$C, 'Lista Movimenti'!$B:$B, $A48, 'Lista Movimenti'!$E:$E, "Risparmio", 'Lista Movimenti'!$D:$D, ">=01/04/2026", 'Lista Movimenti'!$D:$D, "<=30/04/2026") -> 0 | F48: =SUMIFS('Lista Movimenti'!$C:$C, 'Lista Movimenti'!$B:$B, $A48, 'Lista Movimenti'!$E:$E, "Risparmio", 'Lista Movimenti'!$D:$D, ">=01/05/2026", 'Lista Movimenti'!$D:$D, "<=31/05/2026") -> 0 | G48: =SUMIFS('Lista Movimenti'!$C:$C, 'Lista Movimenti'!$B:$B, $A48, 'Lista Movimenti'!$E:$E, "Risparmio", 'Lista Movimenti'!$D:$D, ">=01/06/2026", 'Lista Movimenti'!$D:$D, "<=30/06/2026") -> 0 | H48: =SUMIFS('Lista Movimenti'!$C:$C, 'Lista Movimenti'!$B:$B, $A48, 'Lista Movimenti'!$E:$E, "Risparmio", 'Lista Movimenti'!$D:$D, ">=01/07/2026", 'Lista Movimenti'!$D:$D, "<=31/07/2026") -> 100 | I48: =SUMIFS('Lista Movimenti'!$C:$C, 'Lista Movimenti'!$B:$B, $A48, 'Lista Movimenti'!$E:$E, "Risparmio", 'Lista Movimenti'!$D:$D, ">=01/08/2026", 'Lista Movimenti'!$D:$D, "<=31/08/2026") -> 0 | J48: =SUMIFS('Lista Movimenti'!$C:$C, 'Lista Movimenti'!$B:$B, $A48, 'Lista Movimenti'!$E:$E, "Risparmio", 'Lista Movimenti'!$D:$D, ">=01/09/2026", 'Lista Movimenti'!$D:$D, "<=30/09/2026") -> 0 | K48: =SUMIFS('Lista Movimenti'!$C:$C, 'Lista Movimenti'!$B:$B, $A48, 'Lista Movimenti'!$E:$E, "Risparmio", 'Lista Movimenti'!$D:$D, ">=01/10/2026", 'Lista Movimenti'!$D:$D, "<=31/10/2026") -> 175 | L48: =SUMIFS('Lista Movimenti'!$C:$C, 'Lista Movimenti'!$B:$B, $A48, 'Lista Movimenti'!$E:$E, "Risparmio", 'Lista Movimenti'!$D:$D, ">=01/11/2026", 'Lista Movimenti'!$D:$D, "<=30/11/2026") -> 0 | M48: =SUMIFS('Lista Movimenti'!$C:$C, 'Lista Movimenti'!$B:$B, $A48, 'Lista Movimenti'!$E:$E, "Risparmio", 'Lista Movimenti'!$D:$D, ">=01/12/2026", 'Lista Movimenti'!$D:$D, "<=31/12/2026") -> 0 | N48: =AVERAGE(B48:M48) -> 22.916667
A49: ✈️ Viaggi/Vacanze | B49: =SUMIFS('Lista Movimenti'!C:C, 'Lista Movimenti'!B:B, A49, 'Lista Movimenti'!E:E, "Risparmio", 'Lista Movimenti'!D:D, ">=01/01/2026", 'Lista Movimenti'!D:D, "<=31/01/2026") -> 500 | C49: =SUMIFS('Lista Movimenti'!$C:$C, 'Lista Movimenti'!$B:$B, $A49, 'Lista Movimenti'!$E:$E, "Risparmio", 'Lista Movimenti'!$D:$D, ">=01/02/2026", 'Lista Movimenti'!$D:$D, "<=28/02/2026") -> 200 | D49: =SUMIFS('Lista Movimenti'!$C:$C, 'Lista Movimenti'!$B:$B, $A49, 'Lista Movimenti'!$E:$E, "Risparmio", 'Lista Movimenti'!$D:$D, ">=01/03/2026", 'Lista Movimenti'!$D:$D, "<=31/03/2026") -> 0 | E49: =SUMIFS('Lista Movimenti'!$C:$C, 'Lista Movimenti'!$B:$B, $A49, 'Lista Movimenti'!$E:$E, "Risparmio", 'Lista Movimenti'!$D:$D, ">=01/04/2026", 'Lista Movimenti'!$D:$D, "<=30/04/2026") -> 0 | F49: =SUMIFS('Lista Movimenti'!$C:$C, 'Lista Movimenti'!$B:$B, $A49, 'Lista Movimenti'!$E:$E, "Risparmio", 'Lista Movimenti'!$D:$D, ">=01/05/2026", 'Lista Movimenti'!$D:$D, "<=31/05/2026") -> 0 | G49: =SUMIFS('Lista Movimenti'!$C:$C, 'Lista Movimenti'!$B:$B, $A49, 'Lista Movimenti'!$E:$E, "Risparmio", 'Lista Movimenti'!$D:$D, ">=01/06/2026", 'Lista Movimenti'!$D:$D, "<=30/06/2026") -> 0 | H49: =SUMIFS('Lista Movimenti'!$C:$C, 'Lista Movimenti'!$B:$B, $A49, 'Lista Movimenti'!$E:$E, "Risparmio", 'Lista Movimenti'!$D:$D, ">=01/07/2026", 'Lista Movimenti'!$D:$D, "<=31/07/2026") -> 0 | I49: =SUMIFS('Lista Movimenti'!$C:$C, 'Lista Movimenti'!$B:$B, $A49, 'Lista Movimenti'!$E:$E, "Risparmio", 'Lista Movimenti'!$D:$D, ">=01/08/2026", 'Lista Movimenti'!$D:$D, "<=31/08/2026") -> 0 | J49: =SUMIFS('Lista Movimenti'!$C:$C, 'Lista Movimenti'!$B:$B, $A49, 'Lista Movimenti'!$E:$E, "Risparmio", 'Lista Movimenti'!$D:$D, ">=01/09/2026", 'Lista Movimenti'!$D:$D, "<=30/09/2026") -> 0 | K49: =SUMIFS('Lista Movimenti'!$C:$C, 'Lista Movimenti'!$B:$B, $A49, 'Lista Movimenti'!$E:$E, "Risparmio", 'Lista Movimenti'!$D:$D, ">=01/10/2026", 'Lista Movimenti'!$D:$D, "<=31/10/2026") -> 0 | L49: =SUMIFS('Lista Movimenti'!$C:$C, 'Lista Movimenti'!$B:$B, $A49, 'Lista Movimenti'!$E:$E, "Risparmio", 'Lista Movimenti'!$D:$D, ">=01/11/2026", 'Lista Movimenti'!$D:$D, "<=30/11/2026") -> 0 | M49: =SUMIFS('Lista Movimenti'!$C:$C, 'Lista Movimenti'!$B:$B, $A49, 'Lista Movimenti'!$E:$E, "Risparmio", 'Lista Movimenti'!$D:$D, ">=01/12/2026", 'Lista Movimenti'!$D:$D, "<=31/12/2026") -> 0 | N49: =AVERAGE(B49:M49) -> 58.333333
A50: 📚 Cultura | B50: =SUMIFS('Lista Movimenti'!C:C, 'Lista Movimenti'!B:B, A50, 'Lista Movimenti'!E:E, "Risparmio", 'Lista Movimenti'!D:D, ">=01/01/2026", 'Lista Movimenti'!D:D, "<=31/01/2026") -> 0 | C50: =SUMIFS('Lista Movimenti'!$C:$C, 'Lista Movimenti'!$B:$B, $A50, 'Lista Movimenti'!$E:$E, "Risparmio", 'Lista Movimenti'!$D:$D, ">=01/02/2026", 'Lista Movimenti'!$D:$D, "<=28/02/2026") -> 0 | D50: =SUMIFS('Lista Movimenti'!$C:$C, 'Lista Movimenti'!$B:$B, $A50, 'Lista Movimenti'!$E:$E, "Risparmio", 'Lista Movimenti'!$D:$D, ">=01/03/2026", 'Lista Movimenti'!$D:$D, "<=31/03/2026") -> 0 | E50: =SUMIFS('Lista Movimenti'!$C:$C, 'Lista Movimenti'!$B:$B, $A50, 'Lista Movimenti'!$E:$E, "Risparmio", 'Lista Movimenti'!$D:$D, ">=01/04/2026", 'Lista Movimenti'!$D:$D, "<=30/04/2026") -> 0 | F50: =SUMIFS('Lista Movimenti'!$C:$C, 'Lista Movimenti'!$B:$B, $A50, 'Lista Movimenti'!$E:$E, "Risparmio", 'Lista Movimenti'!$D:$D, ">=01/05/2026", 'Lista Movimenti'!$D:$D, "<=31/05/2026") -> 0 | G50: =SUMIFS('Lista Movimenti'!$C:$C, 'Lista Movimenti'!$B:$B, $A50, 'Lista Movimenti'!$E:$E, "Risparmio", 'Lista Movimenti'!$D:$D, ">=01/06/2026", 'Lista Movimenti'!$D:$D, "<=30/06/2026") -> 0 | H50: =SUMIFS('Lista Movimenti'!$C:$C, 'Lista Movimenti'!$B:$B, $A50, 'Lista Movimenti'!$E:$E, "Risparmio", 'Lista Movimenti'!$D:$D, ">=01/07/2026", 'Lista Movimenti'!$D:$D, "<=31/07/2026") -> 0 | I50: =SUMIFS('Lista Movimenti'!$C:$C, 'Lista Movimenti'!$B:$B, $A50, 'Lista Movimenti'!$E:$E, "Risparmio", 'Lista Movimenti'!$D:$D, ">=01/08/2026", 'Lista Movimenti'!$D:$D, "<=31/08/2026") -> 0 | J50: =SUMIFS('Lista Movimenti'!$C:$C, 'Lista Movimenti'!$B:$B, $A50, 'Lista Movimenti'!$E:$E, "Risparmio", 'Lista Movimenti'!$D:$D, ">=01/09/2026", 'Lista Movimenti'!$D:$D, "<=30/09/2026") -> 0 | K50: =SUMIFS('Lista Movimenti'!$C:$C, 'Lista Movimenti'!$B:$B, $A50, 'Lista Movimenti'!$E:$E, "Risparmio", 'Lista Movimenti'!$D:$D, ">=01/10/2026", 'Lista Movimenti'!$D:$D, "<=31/10/2026") -> 0 | L50: =SUMIFS('Lista Movimenti'!$C:$C, 'Lista Movimenti'!$B:$B, $A50, 'Lista Movimenti'!$E:$E, "Risparmio", 'Lista Movimenti'!$D:$D, ">=01/11/2026", 'Lista Movimenti'!$D:$D, "<=30/11/2026") -> 0 | M50: =SUMIFS('Lista Movimenti'!$C:$C, 'Lista Movimenti'!$B:$B, $A50, 'Lista Movimenti'!$E:$E, "Risparmio", 'Lista Movimenti'!$D:$D, ">=01/12/2026", 'Lista Movimenti'!$D:$D, "<=31/12/2026") -> 0 | N50: =AVERAGE(B50:M50) -> 0
... A54: 🪙 Altre entrate | B54: =SUMIFS('Lista Movimenti'!C:C, 'Lista Movimenti'!B:B, A54, 'Lista Movimenti'!E:E, "Risparmio", 'Lista Movimenti'!D:D, ">=01/01/2026", 'Lista Movimenti'!D:D, "<=31/01/2026") -> 0 | C54: =SUMIFS('Lista Movimenti'!$C:$C, 'Lista Movimenti'!$B:$B, $A54, 'Lista Movimenti'!$E:$E, "Risparmio", 'Lista Movimenti'!$D:$D, ">=01/02/2026", 'Lista Movimenti'!$D:$D, "<=28/02/2026") -> 0 | D54: =SUMIFS('Lista Movimenti'!$C:$C, 'Lista Movimenti'!$B:$B, $A54, 'Lista Movimenti'!$E:$E, "Risparmio", 'Lista Movimenti'!$D:$D, ">=01/03/2026", 'Lista Movimenti'!$D:$D, "<=31/03/2026") -> 0 | E54: =SUMIFS('Lista Movimenti'!$C:$C, 'Lista Movimenti'!$B:$B, $A54, 'Lista Movimenti'!$E:$E, "Risparmio", 'Lista Movimenti'!$D:$D, ">=01/04/2026", 'Lista Movimenti'!$D:$D, "<=30/04/2026") -> 0 | F54: =SUMIFS('Lista Movimenti'!$C:$C, 'Lista Movimenti'!$B:$B, $A54, 'Lista Movimenti'!$E:$E, "Risparmio", 'Lista Movimenti'!$D:$D, ">=01/05/2026", 'Lista Movimenti'!$D:$D, "<=31/05/2026") -> 0 | G54: =SUMIFS('Lista Movimenti'!$C:$C, 'Lista Movimenti'!$B:$B, $A54, 'Lista Movimenti'!$E:$E, "Risparmio", 'Lista Movimenti'!$D:$D, ">=01/06/2026", 'Lista Movimenti'!$D:$D, "<=30/06/2026") -> 0 | H54: =SUMIFS('Lista Movimenti'!$C:$C, 'Lista Movimenti'!$B:$B, $A54, 'Lista Movimenti'!$E:$E, "Risparmio", 'Lista Movimenti'!$D:$D, ">=01/07/2026", 'Lista Movimenti'!$D:$D, "<=31/07/2026") -> 0 | I54: =SUMIFS('Lista Movimenti'!$C:$C, 'Lista Movimenti'!$B:$B, $A54, 'Lista Movimenti'!$E:$E, "Risparmio", 'Lista Movimenti'!$D:$D, ">=01/08/2026", 'Lista Movimenti'!$D:$D, "<=31/08/2026") -> 0 | J54: =SUMIFS('Lista Movimenti'!$C:$C, 'Lista Movimenti'!$B:$B, $A54, 'Lista Movimenti'!$E:$E, "Risparmio", 'Lista Movimenti'!$D:$D, ">=01/09/2026", 'Lista Movimenti'!$D:$D, "<=30/09/2026") -> 0 | K54: =SUMIFS('Lista Movimenti'!$C:$C, 'Lista Movimenti'!$B:$B, $A54, 'Lista Movimenti'!$E:$E, "Risparmio", 'Lista Movimenti'!$D:$D, ">=01/10/2026", 'Lista Movimenti'!$D:$D, "<=31/10/2026") -> 0 | L54: =SUMIFS('Lista Movimenti'!$C:$C, 'Lista Movimenti'!$B:$B, $A54, 'Lista Movimenti'!$E:$E, "Risparmio", 'Lista Movimenti'!$D:$D, ">=01/11/2026", 'Lista Movimenti'!$D:$D, "<=30/11/2026") -> 0 | M54: =SUMIFS('Lista Movimenti'!$C:$C, 'Lista Movimenti'!$B:$B, $A54, 'Lista Movimenti'!$E:$E, "Risparmio", 'Lista Movimenti'!$D:$D, ">=01/12/2026", 'Lista Movimenti'!$D:$D, "<=31/12/2026") -> 0 | N54: =AVERAGE(B54:M54) -> 0
A55: Totale Risparmi | B55: =SUM(B38:B54) -> 550 | C55: =SUM(C38:C54) -> 200 | D55: =SUM(D38:D54) -> 0 | E55: =SUM(E38:E54) -> 300 | F55: =SUM(F38:F54) -> 500 | G55: =SUM(G38:G54) -> 0 | H55: =SUM(H38:H54) -> 100 | I55: =SUM(I38:I54) -> 0 | ... N55: =SUM(N38:N54) -> 326.66667 | O55: =SUM(Risparmi_Anno[Obiettivo]) -> 0 | AE55: 0

Sheet Gen
A1: GENNAIO
A3: Categoria | B3: Totale | C3: Obiettivo
A4: 🤑 Stipendio | B4: =SUMIFS('Lista Movimenti'!C:C, 'Lista Movimenti'!B:B, A4,'Lista Movimenti'!D:D, ">=01/01/2026", 'Lista Movimenti'!D:D, "<=31/01/2026") -> 1500
A5: 🪙 Altre entrate | B5: =SUMIFS('Lista Movimenti'!C:C, 'Lista Movimenti'!B:B, A5,'Lista Movimenti'!D:D, ">=01/01/2026", 'Lista Movimenti'!D:D, "<=31/01/2026") -> 50
B6: =SUMIFS('Lista Movimenti'!C:C, 'Lista Movimenti'!B:B, A6,'Lista Movimenti'!D:D, ">=01/01/2026", 'Lista Movimenti'!D:D, "<=31/01/2026") -> 0
B7: =SUMIFS('Lista Movimenti'!C:C, 'Lista Movimenti'!B:B, A7,'Lista Movimenti'!D:D, ">=01/01/2026", 'Lista Movimenti'!D:D, "<=31/01/2026") -> 0
B8: =SUM(Entrate_Gen[Totale]) -> 1550 | C8: =SUM(Entrate_Gen[Obiettivo]) -> 0
A12: Necessita | B12: Categoria | C12: Totale | D12: Obiettivo
B13: 🏠 Casa | C13: =SUMIFS('Lista Movimenti'!C:C, 'Lista Movimenti'!B:B, B13, 'Lista Movimenti'!E:E, "Spesa", 'Lista Movimenti'!D:D, ">=01/01/2026", 'Lista Movimenti'!D:D, "<=31/01/2026") -> 230 | D13: 200
B14: 🍲 Cibo/Spesa | C14: =SUMIFS('Lista Movimenti'!C:C, 'Lista Movimenti'!B:B, B14, 'Lista Movimenti'!E:E, "Spesa", 'Lista Movimenti'!D:D, ">=01/01/2026", 'Lista Movimenti'!D:D, "<=31/01/2026") -> 125 | D14: 280
B15: 🚑 Sanità | C15: =SUMIFS('Lista Movimenti'!C:C, 'Lista Movimenti'!B:B, B15, 'Lista Movimenti'!E:E, "Spesa", 'Lista Movimenti'!D:D, ">=01/01/2026", 'Lista Movimenti'!D:D, "<=31/01/2026") -> 100 | D15: 50
B16: 🏋️ Palestra e affini | C16: =SUMIFS('Lista Movimenti'!C:C, 'Lista Movimenti'!B:B, B16, 'Lista Movimenti'!E:E, "Spesa", 'Lista Movimenti'!D:D, ">=01/01/2026", 'Lista Movimenti'!D:D, "<=31/01/2026") -> 29 | D16: 40
B17: 📱 Telefono | C17: =SUMIFS('Lista Movimenti'!C:C, 'Lista Movimenti'!B:B, B17, 'Lista Movimenti'!E:E, "Spesa", 'Lista Movimenti'!D:D, ">=01/01/2026", 'Lista Movimenti'!D:D, "<=31/01/2026") -> 12 | D17: 15
B18: 🚌 Trasporti | C18: =SUMIFS('Lista Movimenti'!C:C, 'Lista Movimenti'!B:B, B18, 'Lista Movimenti'!E:E, "Spesa", 'Lista Movimenti'!D:D, ">=01/01/2026", 'Lista Movimenti'!D:D, "<=31/01/2026") -> 60 | D18: 45
B19: 👕 Vestiti | C19: =SUMIFS('Lista Movimenti'!C:C, 'Lista Movimenti'!B:B, B19, 'Lista Movimenti'!E:E, "Spesa", 'Lista Movimenti'!D:D, ">=01/01/2026", 'Lista Movimenti'!D:D, "<=31/01/2026") -> 112 | D19: 35
A20: Totale Necessità | B20: -- Necessità -- | C20: =SUM(C13:C19) -> 668 | D20: =SUM(D13:D19) -> 665
A22: EXTRA | B22: -- Extra -- | C22: Totale | D22: Obiettivo
B23: 🎫 Abbonamenti | C23: =SUMIFS('Lista Movimenti'!C:C, 'Lista Movimenti'!B:B, B23, 'Lista Movimenti'!E:E, "Spesa", 'Lista Movimenti'!D:D, ">=01/01/2026", 'Lista Movimenti'!D:D, "<=31/01/2026") -> 9 | D23: 22
B24: 🍔 Cibo fuori | C24: =SUMIFS('Lista Movimenti'!C:C, 'Lista Movimenti'!B:B, B24, 'Lista Movimenti'!E:E, "Spesa", 'Lista Movimenti'!D:D, ">=01/01/2026", 'Lista Movimenti'!D:D, "<=31/01/2026") -> 64 | D24: 85
B25: 🎬 Intrattenimento | C25: =SUMIFS('Lista Movimenti'!C:C, 'Lista Movimenti'!B:B, B25, 'Lista Movimenti'!E:E, "Spesa", 'Lista Movimenti'!D:D, ">=01/01/2026", 'Lista Movimenti'!D:D, "<=31/01/2026") -> 36 | D25: 24
B26: 🎁 Regali | C26: =SUMIFS('Lista Movimenti'!C:C, 'Lista Movimenti'!B:B, B26, 'Lista Movimenti'!E:E, "Spesa", 'Lista Movimenti'!D:D, ">=01/01/2026", 'Lista Movimenti'!D:D, "<=31/01/2026") -> 200 | D26: 20
B27: ✈️ Viaggi/Vacanze | C27: =SUMIFS('Lista Movimenti'!C:C, 'Lista Movimenti'!B:B, B27, 'Lista Movimenti'!E:E, "Spesa", 'Lista Movimenti'!D:D, ">=01/01/2026", 'Lista Movimenti'!D:D, "<=31/01/2026") -> 0 | D27: 60
B28: 📚 Cultura | C28: =SUMIFS('Lista Movimenti'!C:C, 'Lista Movimenti'!B:B, B28, 'Lista Movimenti'!E:E, "Spesa", 'Lista Movimenti'!D:D, ">=01/01/2026", 'Lista Movimenti'!D:D, "<=31/01/2026") -> 32 | D28: 40
B29: 💅 Cura personale | C29: =SUMIFS('Lista Movimenti'!C:C, 'Lista Movimenti'!B:B, B29, 'Lista Movimenti'!E:E, "Spesa", 'Lista Movimenti'!D:D, ">=01/01/2026", 'Lista Movimenti'!D:D, "<=31/01/2026") -> 100 | D29: 95
B30: 🌟 Altro extra | C30: =SUMIFS('Lista Movimenti'!C:C, 'Lista Movimenti'!B:B, B30, 'Lista Movimenti'!E:E, "Spesa", 'Lista Movimenti'!D:D, ">=01/01/2026", 'Lista Movimenti'!D:D, "<=31/01/2026") -> 0 | D30: 13
A31: Totale Extra | B31: -- Extra -- | C31: =SUM(C23:C30) -> 441 | D31: =SUM(D23:D30) -> 359
A33: Totale Uscite | C33: =(C31 + C20) -> 1109 | D33: =(D31 + D20) -> 1024
A34: Differenza Entrate Uscite | C34: =(B8-C33) -> 441
A37: Categoria | B37: Totale | C37: Obiettivo
A38: 🏠 Casa | B38: =SUMIFS('Lista Movimenti'!C:C, 'Lista Movimenti'!B:B, A38, 'Lista Movimenti'!E:E, "Risparmio", 'Lista Movimenti'!D:D, ">=01/01/2026", 'Lista Movimenti'!D:D, "<=31/01/2026") -> 0
A39: 🍲 Cibo/Spesa | B39: =SUMIFS('Lista Movimenti'!C:C, 'Lista Movimenti'!B:B, A39, 'Lista Movimenti'!E:E, "Risparmio", 'Lista Movimenti'!D:D, ">=01/01/2026", 'Lista Movimenti'!D:D, "<=31/01/2026") -> 0
A40: 🚑 Sanità | B40: =SUMIFS('Lista Movimenti'!C:C, 'Lista Movimenti'!B:B, A40, 'Lista Movimenti'!E:E, "Risparmio", 'Lista Movimenti'!D:D, ">=01/01/2026", 'Lista Movimenti'!D:D, "<=31/01/2026") -> 0
A41: 🏋️ Palestra e affini | B41: =SUMIFS('Lista Movimenti'!C:C, 'Lista Movimenti'!B:B, A41, 'Lista Movimenti'!E:E, "Risparmio", 'Lista Movimenti'!D:D, ">=01/01/2026", 'Lista Movimenti'!D:D, "<=31/01/2026") -> 0
A42: 📱 Telefono | B42: =SUMIFS('Lista Movimenti'!C:C, 'Lista Movimenti'!B:B, A42, 'Lista Movimenti'!E:E, "Risparmio", 'Lista Movimenti'!D:D, ">=01/01/2026", 'Lista Movimenti'!D:D, "<=31/01/2026") -> 0
A43: 🚌 Trasporti | B43: =SUMIFS('Lista Movimenti'!C:C, 'Lista Movimenti'!B:B, A43, 'Lista Movimenti'!E:E, "Risparmio", 'Lista Movimenti'!D:D, ">=01/01/2026", 'Lista Movimenti'!D:D, "<=31/01/2026") -> 0
A44: 👕 Vestiti | B44: =SUMIFS('Lista Movimenti'!C:C, 'Lista Movimenti'!B:B, A44, 'Lista Movimenti'!E:E, "Risparmio", 'Lista Movimenti'!D:D, ">=01/01/2026", 'Lista Movimenti'!D:D, "<=31/01/2026") -> 0
A45: 🎫 Abbonamenti | B45: =SUMIFS('Lista Movimenti'!C:C, 'Lista Movimenti'!B:B, A45, 'Lista Movimenti'!E:E, "Risparmio", 'Lista Movimenti'!D:D, ">=01/01/2026", 'Lista Movimenti'!D:D, "<=31/01/2026") -> 0
A46: 🍔 Cibo fuori | B46: =SUMIFS('Lista Movimenti'!C:C, 'Lista Movimenti'!B:B, A46, 'Lista Movimenti'!E:E, "Risparmio", 'Lista Movimenti'!D:D, ">=01/01/2026", 'Lista Movimenti'!D:D, "<=31/01/2026") -> 0
A47: 🎬 Intrattenimento | B47: =SUMIFS('Lista Movimenti'!C:C, 'Lista Movimenti'!B:B, A47, 'Lista Movimenti'!E:E, "Risparmio", 'Lista Movimenti'!D:D, ">=01/01/2026", 'Lista Movimenti'!D:D, "<=31/01/2026") -> 0
A48: 🎁 Regali | B48: =SUMIFS('Lista Movimenti'!C:C, 'Lista Movimenti'!B:B, A48, 'Lista Movimenti'!E:E, "Risparmio", 'Lista Movimenti'!D:D, ">=01/01/2026", 'Lista Movimenti'!D:D, "<=31/01/2026") -> 0
A49: ✈️ Viaggi/Vacanze | B49: =SUMIFS('Lista Movimenti'!C:C, 'Lista Movimenti'!B:B, A49, 'Lista Movimenti'!E:E, "Risparmio", 'Lista Movimenti'!D:D, ">=01/01/2026", 'Lista Movimenti'!D:D, "<=31/01/2026") -> 500
... A54: 🪙 Altre entrate | B54: =SUMIFS('Lista Movimenti'!C:C, 'Lista Movimenti'!B:B, A54, 'Lista Movimenti'!E:E, "Risparmio", 'Lista Movimenti'!D:D, ">=01/01/2026", 'Lista Movimenti'!D:D, "<=31/01/2026") -> 0
A55: Totale Risparmi | B55: =SUM(Risparmi[Totale]) -> 550 | C55: =SUM(Risparmi[Obiettivo]) -> 0 | S55: 0

Sheet Feb
A1: GENNAIO
A3: Categoria | B3: Totale | C3: Obiettivo
A4: 🤑 Stipendio | B4: =SUMIFS('Lista Movimenti'!$C:$C, 'Lista Movimenti'!$B:$B, $A4, 'Lista Movimenti'!$D:$D, ">="&DATE(2026,2,1), 'Lista Movimenti'!$D:$D, "<="&DATE(2026,2,28)) -> 1400
A5: 🪙 Altre entrate | B5: =SUMIFS('Lista Movimenti'!$C:$C, 'Lista Movimenti'!$B:$B, $A5, 'Lista Movimenti'!$D:$D, ">="&DATE(2026,2,1), 'Lista Movimenti'!$D:$D, "<="&DATE(2026,2,28)) -> 0
B6: =SUMIFS('Lista Movimenti'!$C:$C, 'Lista Movimenti'!$B:$B, $A6, 'Lista Movimenti'!$D:$D, ">="&DATE(2026,2,1), 'Lista Movimenti'!$D:$D, "<="&DATE(2026,2,28)) -> 0
B7: =SUMIFS('Lista Movimenti'!$C:$C, 'Lista Movimenti'!$B:$B, $A7, 'Lista Movimenti'!$D:$D, ">="&DATE(2026,2,1), 'Lista Movimenti'!$D:$D, "<="&DATE(2026,2,28)) -> 0
B8: =SUM(Entrate_Feb[Totale]) -> 1400 | C8: =SUM(Entrate_Feb[Obiettivo]) -> 0
A12: Necessita | B12: Categoria | C12: Totale | D12: Obiettivo
B13: 🏠 Casa | C13: =SUMIFS('Lista Movimenti'!$C:$C, 'Lista Movimenti'!$B:$B, $B13, 'Lista Movimenti'!$E:$E, "Spesa", 'Lista Movimenti'!$D:$D, ">=01/02/2026", 'Lista Movimenti'!$D:$D, "<=28/02/2026") -> 780 | D13: 200
B14: 🍲 Cibo/Spesa | C14: =SUMIFS('Lista Movimenti'!$C:$C, 'Lista Movimenti'!$B:$B, $B14, 'Lista Movimenti'!$E:$E, "Spesa", 'Lista Movimenti'!$D:$D, ">=01/02/2026", 'Lista Movimenti'!$D:$D, "<=28/02/2026") -> 0 | D14: 280
B15: 🚑 Sanità | C15: =SUMIFS('Lista Movimenti'!$C:$C, 'Lista Movimenti'!$B:$B, $B15, 'Lista Movimenti'!$E:$E, "Spesa", 'Lista Movimenti'!$D:$D, ">=01/02/2026", 'Lista Movimenti'!$D:$D, "<=28/02/2026") -> 0 | D15: 50
B16: 🏋️ Palestra e affini | C16: =SUMIFS('Lista Movimenti'!$C:$C, 'Lista Movimenti'!$B:$B, $B16, 'Lista Movimenti'!$E:$E, "Spesa", 'Lista Movimenti'!$D:$D, ">=01/02/2026", 'Lista Movimenti'!$D:$D, "<=28/02/2026") -> 0 | D16: 40
B17: 📱 Telefono | C17: =SUMIFS('Lista Movimenti'!$C:$C, 'Lista Movimenti'!$B:$B, $B17, 'Lista Movimenti'!$E:$E, "Spesa", 'Lista Movimenti'!$D:$D, ">=01/02/2026", 'Lista Movimenti'!$D:$D, "<=28/02/2026") -> 0 | D17: 15
B18: 🚌 Trasporti | C18: =SUMIFS('Lista Movimenti'!$C:$C, 'Lista Movimenti'!$B:$B, $B18, 'Lista Movimenti'!$E:$E, "Spesa", 'Lista Movimenti'!$D:$D, ">=01/02/2026", 'Lista Movimenti'!$D:$D, "<=28/02/2026") -> 0 | D18: 45
B19: 👕 Vestiti | C19: =SUMIFS('Lista Movimenti'!$C:$C, 'Lista Movimenti'!$B:$B, $B19, 'Lista Movimenti'!$E:$E, "Spesa", 'Lista Movimenti'!$D:$D, ">=01/02/2026", 'Lista Movimenti'!$D:$D, "<=28/02/2026") -> 0 | D19: 35
A20: Totale Necessità | B20: -- Necessità -- | C20: =SUM(C13:C19) -> 780 | D20: =SUM(D13:D19) -> 665
A22: EXTRA | B22: -- Extra -- | C22: Totale | D22: Obiettivo
B23: 🎫 Abbonamenti | C23: =SUMIFS('Lista Movimenti'!$C:$C, 'Lista Movimenti'!$B:$B, $B23, 'Lista Movimenti'!$E:$E, "Spesa", 'Lista Movimenti'!$D:$D, ">=01/02/2026", 'Lista Movimenti'!$D:$D, "<=28/02/2026") -> 0 | D23: 22
B24: 🍔 Cibo fuori | C24: =SUMIFS('Lista Movimenti'!$C:$C, 'Lista Movimenti'!$B:$B, $B24, 'Lista Movimenti'!$E:$E, "Spesa", 'Lista Movimenti'!$D:$D, ">=01/02/2026", 'Lista Movimenti'!$D:$D, "<=28/02/2026") -> 79 | D24: 85
B25: 🎬 Intrattenimento | C25: =SUMIFS('Lista Movimenti'!$C:$C, 'Lista Movimenti'!$B:$B, $B25, 'Lista Movimenti'!$E:$E, "Spesa", 'Lista Movimenti'!$D:$D, ">=01/02/2026", 'Lista Movimenti'!$D:$D, "<=28/02/2026") -> 0 | D25: 24
B26: 🎁 Regali | C26: =SUMIFS('Lista Movimenti'!$C:$C, 'Lista Movimenti'!$B:$B, $B26, 'Lista Movimenti'!$E:$E, "Spesa", 'Lista Movimenti'!$D:$D, ">=01/02/2026", 'Lista Movimenti'!$D:$D, "<=28/02/2026") -> 0 | D26: 20
B27: ✈️ Viaggi/Vacanze | C27: =SUMIFS('Lista Movimenti'!$C:$C, 'Lista Movimenti'!$B:$B, $B27, 'Lista Movimenti'!$E:$E, "Spesa", 'Lista Movimenti'!$D:$D, ">=01/02/2026", 'Lista Movimenti'!$D:$D, "<=28/02/2026") -> 0 | D27: 60
B28: 📚 Cultura | C28: =SUMIFS('Lista Movimenti'!$C:$C, 'Lista Movimenti'!$B:$B, $B28, 'Lista Movimenti'!$E:$E, "Spesa", 'Lista Movimenti'!$D:$D, ">=01/02/2026", 'Lista Movimenti'!$D:$D, "<=28/02/2026") -> 0 | D28: 40
B29: 💅 Cura personale | C29: =SUMIFS('Lista Movimenti'!$C:$C, 'Lista Movimenti'!$B:$B, $B29, 'Lista Movimenti'!$E:$E, "Spesa", 'Lista Movimenti'!$D:$D, ">=01/02/2026", 'Lista Movimenti'!$D:$D, "<=28/02/2026") -> 0 | D29: 95
B30: 🌟 Altro extra | C30: =SUMIFS('Lista Movimenti'!$C:$C, 'Lista Movimenti'!$B:$B, $B30, 'Lista Movimenti'!$E:$E, "Spesa", 'Lista Movimenti'!$D:$D, ">=01/02/2026", 'Lista Movimenti'!$D:$D, "<=28/02/2026") -> 112 | D30: 13
A31: Totale Extra | B31: -- Extra -- | C31: =SUM(C23:C30) -> 191 | D31: =SUM(D23:D30) -> 359
A33: Totale Uscite | C33: =(C31 + C20) -> 971 | D33: =(D31 + D20) -> 1024
A34: Differenza Entrate Uscite | C34: =(B8-C33) -> 429
A37: Categoria | B37: Totale | C37: Obiettivo
A38: 🏠 Casa | B38: =SUMIFS('Lista Movimenti'!$C:$C, 'Lista Movimenti'!$B:$B, $A38, 'Lista Movimenti'!$E:$E, "Risparmio", 'Lista Movimenti'!$D:$D, ">=01/02/2026", 'Lista Movimenti'!$D:$D, "<=28/02/2026") -> 0
A39: 🍲 Cibo/Spesa | B39: =SUMIFS('Lista Movimenti'!$C:$C, 'Lista Movimenti'!$B:$B, $A39, 'Lista Movimenti'!$E:$E, "Risparmio", 'Lista Movimenti'!$D:$D, ">=01/02/2026", 'Lista Movimenti'!$D:$D, "<=28/02/2026") -> 0
A40: 🚑 Sanità | B40: =SUMIFS('Lista Movimenti'!$C:$C, 'Lista Movimenti'!$B:$B, $A40, 'Lista Movimenti'!$E:$E, "Risparmio", 'Lista Movimenti'!$D:$D, ">=01/02/2026", 'Lista Movimenti'!$D:$D, "<=28/02/2026") -> 0
A41: 🏋️ Palestra e affini | B41: =SUMIFS('Lista Movimenti'!$C:$C, 'Lista Movimenti'!$B:$B, $A41, 'Lista Movimenti'!$E:$E, "Risparmio", 'Lista Movimenti'!$D:$D, ">=01/02/2026", 'Lista Movimenti'!$D:$D, "<=28/02/2026") -> 0
A42: 📱 Telefono | B42: =SUMIFS('Lista Movimenti'!$C:$C, 'Lista Movimenti'!$B:$B, $A42, 'Lista Movimenti'!$E:$E, "Risparmio", 'Lista Movimenti'!$D:$D, ">=01/02/2026", 'Lista Movimenti'!$D:$D, "<=28/02/2026") -> 0
A43: 🚌 Trasporti | B43: =SUMIFS('Lista Movimenti'!$C:$C, 'Lista Movimenti'!$B:$B, $A43, 'Lista Movimenti'!$E:$E, "Risparmio", 'Lista Movimenti'!$D:$D, ">=01/02/2026", 'Lista Movimenti'!$D:$D, "<=28/02/2026") -> 0
A44: 👕 Vestiti | B44: =SUMIFS('Lista Movimenti'!$C:$C, 'Lista Movimenti'!$B:$B, $A44, 'Lista Movimenti'!$E:$E, "Risparmio", 'Lista Movimenti'!$D:$D, ">=01/02/2026", 'Lista Movimenti'!$D:$D, "<=28/02/2026") -> 0
A45: 🎫 Abbonamenti | B45: =SUMIFS('Lista Movimenti'!$C:$C, 'Lista Movimenti'!$B:$B, $A45, 'Lista Movimenti'!$E:$E, "Risparmio", 'Lista Movimenti'!$D:$D, ">=01/02/2026", 'Lista Movimenti'!$D:$D, "<=28/02/2026") -> 0
A46: 🍔 Cibo fuori | B46: =SUMIFS('Lista Movimenti'!$C:$C, 'Lista Movimenti'!$B:$B, $A46, 'Lista Movimenti'!$E:$E, "Risparmio", 'Lista Movimenti'!$D:$D, ">=01/02/2026", 'Lista Movimenti'!$D:$D, "<=28/02/2026") -> 0
A47: 🎬 Intrattenimento | B47: =SUMIFS('Lista Movimenti'!$C:$C, 'Lista Movimenti'!$B:$B, $A47, 'Lista Movimenti'!$E:$E, "Risparmio", 'Lista Movimenti'!$D:$D, ">=01/02/2026", 'Lista Movimenti'!$D:$D, "<=28/02/2026") -> 0
A48: 🎁 Regali | B48: =SUMIFS('Lista Movimenti'!$C:$C, 'Lista Movimenti'!$B:$B, $A48, 'Lista Movimenti'!$E:$E, "Risparmio", 'Lista Movimenti'!$D:$D, ">=01/02/2026", 'Lista Movimenti'!$D:$D, "<=28/02/2026") -> 0
A49: ✈️ Viaggi/Vacanze | B49: =SUMIFS('Lista Movimenti'!$C:$C, 'Lista Movimenti'!$B:$B, $A49, 'Lista Movimenti'!$E:$E, "Risparmio", 'Lista Movimenti'!$D:$D, ">=01/02/2026", 'Lista Movimenti'!$D:$D, "<=28/02/2026") -> 200
... A54: 🪙 Altre entrate | B54: =SUMIFS('Lista Movimenti'!$C:$C, 'Lista Movimenti'!$B:$B, $A54, 'Lista Movimenti'!$E:$E, "Risparmio", 'Lista Movimenti'!$D:$D, ">=01/02/2026", 'Lista Movimenti'!$D:$D, "<=28/02/2026") -> 0
A55: Totale Risparmi | B55: =SUM(Risparmi_2[Totale]) -> 200 | C55: =SUM(Risparmi_2[Obiettivo]) -> 0 | S55: 0

Sheet Mar
A1: GENNAIO
A3: Categoria | B3: Totale | C3: Obiettivo
A4: 🤑 Stipendio | B4: =SUMIFS('Lista Movimenti'!$C:$C, 'Lista Movimenti'!$B:$B, $A4, 'Lista Movimenti'!$D:$D, ">="&DATE(2026,3,1), 'Lista Movimenti'!$D:$D, "<="&DATE(2026,3,31)) -> 1500
A5: 🪙 Altre entrate | B5: =SUMIFS('Lista Movimenti'!$C:$C, 'Lista Movimenti'!$B:$B, $A5, 'Lista Movimenti'!$D:$D, ">="&DATE(2026,3,1), 'Lista Movimenti'!$D:$D, "<="&DATE(2026,3,31)) -> 10
B6: =SUMIFS('Lista Movimenti'!$C:$C, 'Lista Movimenti'!$B:$B, $A6, 'Lista Movimenti'!$D:$D, ">="&DATE(2026,3,1), 'Lista Movimenti'!$D:$D, "<="&DATE(2026,3,31)) -> 0
B7: =SUMIFS('Lista Movimenti'!$C:$C, 'Lista Movimenti'!$B:$B, $A7, 'Lista Movimenti'!$D:$D, ">="&DATE(2026,3,1), 'Lista Movimenti'!$D:$D, "<="&DATE(2026,3,31)) -> 0
B8: =SUM(Entrate_Mar[Totale]) -> 1510 | C8: =SUM(Entrate_Mar[Obiettivo]) -> 0
A12: Necessita | B12: Categoria | C12: Totale | D12: Obiettivo
B13: 🏠 Casa | C13: =SUMIFS('Lista Movimenti'!$C:$C, 'Lista Movimenti'!$B:$B, $B13, 'Lista Movimenti'!$E:$E, "Spesa", 'Lista Movimenti'!$D:$D, ">=01/03/2026", 'Lista Movimenti'!$D:$D, "<=31/03/2026") -> 0 | D13: 200
B14: 🍲 Cibo/Spesa | C14: =SUMIFS('Lista Movimenti'!$C:$C, 'Lista Movimenti'!$B:$B, $B14, 'Lista Movimenti'!$E:$E, "Spesa", 'Lista Movimenti'!$D:$D, ">=01/03/2026", 'Lista Movimenti'!$D:$D, "<=31/03/2026") -> 0 | D14: 280
B15: 🚑 Sanità | C15: =SUMIFS('Lista Movimenti'!$C:$C, 'Lista Movimenti'!$B:$B, $B15, 'Lista Movimenti'!$E:$E, "Spesa", 'Lista Movimenti'!$D:$D, ">=01/03/2026", 'Lista Movimenti'!$D:$D, "<=31/03/2026") -> 0 | D15: 50
B16: 🏋️ Palestra e affini | C16: =SUMIFS('Lista Movimenti'!$C:$C, 'Lista Movimenti'!$B:$B, $B16, 'Lista Movimenti'!$E:$E, "Spesa", 'Lista Movimenti'!$D:$D, ">=01/03/2026", 'Lista Movimenti'!$D:$D, "<=31/03/2026") -> 0 | D16: 40
B17: 📱 Telefono | C17: =SUMIFS('Lista Movimenti'!$C:$C, 'Lista Movimenti'!$B:$B, $B17, 'Lista Movimenti'!$E:$E, "Spesa", 'Lista Movimenti'!$D:$D, ">=01/03/2026", 'Lista Movimenti'!$D:$D, "<=31/03/2026") -> 0 | D17: 15
B18: 🚌 Trasporti | C18: =SUMIFS('Lista Movimenti'!$C:$C, 'Lista Movimenti'!$B:$B, $B18, 'Lista Movimenti'!$E:$E, "Spesa", 'Lista Movimenti'!$D:$D, ">=01/03/2026", 'Lista Movimenti'!$D:$D, "<=31/03/2026") -> 0 | D18: 45
B19: 👕 Vestiti | C19: =SUMIFS('Lista Movimenti'!$C:$C, 'Lista Movimenti'!$B:$B, $B19, 'Lista Movimenti'!$E:$E, "Spesa", 'Lista Movimenti'!$D:$D, ">=01/03/2026", 'Lista Movimenti'!$D:$D, "<=31/03/2026") -> 0 | D19: 35
A20: Totale Necessità | B20: -- Necessità -- | C20: =SUM(C13:C19) -> 0 | D20: =SUM(D13:D19) -> 665
A22: EXTRA | B22: -- Extra -- | C22: Totale | D22: Obiettivo
B23: 🎫 Abbonamenti | C23: =SUMIFS('Lista Movimenti'!$C:$C, 'Lista Movimenti'!$B:$B, $B23, 'Lista Movimenti'!$E:$E, "Spesa", 'Lista Movimenti'!$D:$D, ">=01/03/2026", 'Lista Movimenti'!$D:$D, "<=31/03/2026") -> 0 | D23: 22
B24: 🍔 Cibo fuori | C24: =SUMIFS('Lista Movimenti'!$C:$C, 'Lista Movimenti'!$B:$B, $B24, 'Lista Movimenti'!$E:$E, "Spesa", 'Lista Movimenti'!$D:$D, ">=01/03/2026", 'Lista Movimenti'!$D:$D, "<=31/03/2026") -> 0 | D24: 85
B25: 🎬 Intrattenimento | C25: =SUMIFS('Lista Movimenti'!$C:$C, 'Lista Movimenti'!$B:$B, $B25, 'Lista Movimenti'!$E:$E, "Spesa", 'Lista Movimenti'!$D:$D, ">=01/03/2026", 'Lista Movimenti'!$D:$D, "<=31/03/2026") -> 0 | D25: 24
B26: 🎁 Regali | C26: =SUMIFS('Lista Movimenti'!$C:$C, 'Lista Movimenti'!$B:$B, $B26, 'Lista Movimenti'!$E:$E, "Spesa", 'Lista Movimenti'!$D:$D, ">=01/03/2026", 'Lista Movimenti'!$D:$D, "<=31/03/2026") -> 0 | D26: 20
B27: ✈️ Viaggi/Vacanze | C27: =SUMIFS('Lista Movimenti'!$C:$C, 'Lista Movimenti'!$B:$B, $B27, 'Lista Movimenti'!$E:$E, "Spesa", 'Lista Movimenti'!$D:$D, ">=01/03/2026", 'Lista Movimenti'!$D:$D, "<=31/03/2026") -> 350 | D27: 60
B28: 📚 Cultura | C28: =SUMIFS('Lista Movimenti'!$C:$C, 'Lista Movimenti'!$B:$B, $B28, 'Lista Movimenti'!$E:$E, "Spesa", 'Lista Movimenti'!$D:$D, ">=01/03/2026", 'Lista Movimenti'!$D:$D, "<=31/03/2026") -> 0 | D28: 40
B29: 💅 Cura personale | C29: =SUMIFS('Lista Movimenti'!$C:$C, 'Lista Movimenti'!$B:$B, $B29, 'Lista Movimenti'!$E:$E, "Spesa", 'Lista Movimenti'!$D:$D, ">=01/03/2026", 'Lista Movimenti'!$D:$D, "<=31/03/2026") -> 30 | D29: 95
B30: 🌟 Altro extra | C30: =SUMIFS('Lista Movimenti'!$C:$C, 'Lista Movimenti'!$B:$B, $B30, 'Lista Movimenti'!$E:$E, "Spesa", 'Lista Movimenti'!$D:$D, ">=01/03/2026", 'Lista Movimenti'!$D:$D, "<=31/03/2026") -> 0 | D30: 13
A31: Totale Extra | B31: -- Extra -- | C31: =SUM(C23:C30) -> 380 | D31: =SUM(D23:D30) -> 359
A33: Totale Uscite | C33: =(C31 + C20) -> 380 | D33: =(D31 + D20) -> 1024
A34: Differenza Entrate Uscite | C34: =(B8-C33) -> 1130
A37: Categoria | B37: Totale | C37: Obiettivo
A38: 🏠 Casa | B38: =SUMIFS('Lista Movimenti'!$C:$C, 'Lista Movimenti'!$B:$B, $A38, 'Lista Movimenti'!$E:$E, "Risparmio", 'Lista Movimenti'!$D:$D, ">=01/03/2026", 'Lista Movimenti'!$D:$D, "<=31/03/2026") -> 0
A39: 🍲 Cibo/Spesa | B39: =SUMIFS('Lista Movimenti'!$C:$C, 'Lista Movimenti'!$B:$B, $A39, 'Lista Movimenti'!$E:$E, "Risparmio", 'Lista Movimenti'!$D:$D, ">=01/03/2026", 'Lista Movimenti'!$D:$D, "<=31/03/2026") -> 0
A40: 🚑 Sanità | B40: =SUMIFS('Lista Movimenti'!$C:$C, 'Lista Movimenti'!$B:$B, $A40, 'Lista Movimenti'!$E:$E, "Risparmio", 'Lista Movimenti'!$D:$D, ">=01/03/2026", 'Lista Movimenti'!$D:$D, "<=31/03/2026") -> 0
A41: 🏋️ Palestra e affini | B41: =SUMIFS('Lista Movimenti'!$C:$C, 'Lista Movimenti'!$B:$B, $A41, 'Lista Movimenti'!$E:$E, "Risparmio", 'Lista Movimenti'!$D:$D, ">=01/03/2026", 'Lista Movimenti'!$D:$D, "<=31/03/2026") -> 0
A42: 📱 Telefono | B42: =SUMIFS('Lista Movimenti'!$C:$C, 'Lista Movimenti'!$B:$B, $A42, 'Lista Movimenti'!$E:$E, "Risparmio", 'Lista Movimenti'!$D:$D, ">=01/03/2026", 'Lista Movimenti'!$D:$D, "<=31/03/2026") -> 0
A43: 🚌 Trasporti | B43: =SUMIFS('Lista Movimenti'!$C:$C, 'Lista Movimenti'!$B:$B, $A43, 'Lista Movimenti'!$E:$E, "Risparmio", 'Lista Movimenti'!$D:$D, ">=01/03/2026", 'Lista Movimenti'!$D:$D, "<=31/03/2026") -> 0
A44: 👕 Vestiti | B44: =SUMIFS('Lista Movimenti'!$C:$C, 'Lista Movimenti'!$B:$B, $A44, 'Lista Movimenti'!$E:$E, "Risparmio", 'Lista Movimenti'!$D:$D, ">=01/03/2026", 'Lista Movimenti'!$D:$D, "<=31/03/2026") -> 0
A45: 🎫 Abbonamenti | B45: =SUMIFS('Lista Movimenti'!$C:$C, 'Lista Movimenti'!$B:$B, $A45, 'Lista Movimenti'!$E:$E, "Risparmio", 'Lista Movimenti'!$D:$D, ">=01/03/2026", 'Lista Movimenti'!$D:$D, "<=31/03/2026") -> 0
A46: 🍔 Cibo fuori | B46: =SUMIFS('Lista Movimenti'!$C:$C, 'Lista Movimenti'!$B:$B, $A46, 'Lista Movimenti'!$E:$E, "Risparmio", 'Lista Movimenti'!$D:$D, ">=01/03/2026", 'Lista Movimenti'!$D:$D, "<=31/03/2026") -> 0
A47: 🎬 Intrattenimento | B47: =SUMIFS('Lista Movimenti'!$C:$C, 'Lista Movimenti'!$B:$B, $A47, 'Lista Movimenti'!$E:$E, "Risparmio", 'Lista Movimenti'!$D:$D, ">=01/03/2026", 'Lista Movimenti'!$D:$D, "<=31/03/2026") -> 0
A48: 🎁 Regali | B48: =SUMIFS('Lista Movimenti'!$C:$C, 'Lista Movimenti'!$B:$B, $A48, 'Lista Movimenti'!$E:$E, "Risparmio", 'Lista Movimenti'!$D:$D, ">=01/03/2026", 'Lista Movimenti'!$D:$D, "<=31/03/2026") -> 0
A49: ✈️ Viaggi/Vacanze | B49: =SUMIFS('Lista Movimenti'!$C:$C, 'Lista Movimenti'!$B:$B, $A49, 'Lista Movimenti'!$E:$E, "Risparmio", 'Lista Movimenti'!$D:$D, ">=01/03/2026", 'Lista Movimenti'!$D:$D, "<=31/03/2026") -> 0
... A54: 🪙 Altre entrate | B54: =SUMIFS('Lista Movimenti'!$C:$C, 'Lista Movimenti'!$B:$B, $A54, 'Lista Movimenti'!$E:$E, "Risparmio", 'Lista Movimenti'!$D:$D, ">=01/03/2026", 'Lista Movimenti'!$D:$D, "<=31/03/2026") -> 0
A55: Totale Risparmi | B55: =SUM(Risparmi_3[Totale]) -> 0 | C55: =SUM(Risparmi_3[Obiettivo]) -> 0 | S55: 0

Sheet Apr
A1: GENNAIO
A3: Categoria | B3: Totale | C3: Obiettivo
A4: 🤑 Stipendio | B4: =SUMIFS('Lista Movimenti'!$C:$C, 'Lista Movimenti'!$B:$B, $A4, 'Lista Movimenti'!$D:$D, ">="&DATE(2026,4,1), 'Lista Movimenti'!$D:$D, "<="&DATE(2026,4,30)) -> 1300
A5: 🪙 Altre entrate | B5: =SUMIFS('Lista Movimenti'!$C:$C, 'Lista Movimenti'!$B:$B, $A5, 'Lista Movimenti'!$D:$D, ">="&DATE(2026,4,1), 'Lista Movimenti'!$D:$D, "<="&DATE(2026,4,30)) -> 0
B6: =SUMIFS('Lista Movimenti'!$C:$C, 'Lista Movimenti'!$B:$B, $A6, 'Lista Movimenti'!$D:$D, ">="&DATE(2026,4,1), 'Lista Movimenti'!$D:$D, "<="&DATE(2026,4,30)) -> 0
B7: =SUMIFS('Lista Movimenti'!$C:$C, 'Lista Movimenti'!$B:$B, $A7, 'Lista Movimenti'!$D:$D, ">="&DATE(2026,4,1), 'Lista Movimenti'!$D:$D, "<="&DATE(2026,4,30)) -> 0
B8: =SUM(Entrate_Apr[Totale]) -> 1300 | C8: =SUM(Entrate_Apr[Obiettivo]) -> 0
A12: Necessita | B12: Categoria | C12: Totale | D12: Obiettivo
B13: 🏠 Casa | C13: =SUMIFS('Lista Movimenti'!$C:$C, 'Lista Movimenti'!$B:$B, $B13, 'Lista Movimenti'!$E:$E, "Spesa", 'Lista Movimenti'!$D:$D, ">=01/04/2026", 'Lista Movimenti'!$D:$D, "<=30/04/2026") -> 0 | D13: 200
B14: 🍲 Cibo/Spesa | C14: =SUMIFS('Lista Movimenti'!$C:$C, 'Lista Movimenti'!$B:$B, $B14, 'Lista Movimenti'!$E:$E, "Spesa", 'Lista Movimenti'!$D:$D, ">=01/04/2026", 'Lista Movimenti'!$D:$D, "<=30/04/2026") -> 300 | D14: 280
B15: 🚑 Sanità | C15: =SUMIFS('Lista Movimenti'!$C:$C, 'Lista Movimenti'!$B:$B, $B15, 'Lista Movimenti'!$E:$E, "Spesa", 'Lista Movimenti'!$D:$D, ">=01/04/2026", 'Lista Movimenti'!$D:$D, "<=30/04/2026") -> 0 | D15: 50
B16: 🏋️ Palestra e affini | C16: =SUMIFS('Lista Movimenti'!$C:$C, 'Lista Movimenti'!$B:$B, $B16, 'Lista Movimenti'!$E:$E, "Spesa", 'Lista Movimenti'!$D:$D, ">=01/04/2026", 'Lista Movimenti'!$D:$D, "<=30/04/2026") -> 0 | D16: 40
B17: 📱 Telefono | C17: =SUMIFS('Lista Movimenti'!$C:$C, 'Lista Movimenti'!$B:$B, $B17, 'Lista Movimenti'!$E:$E, "Spesa", 'Lista Movimenti'!$D:$D, ">=01/04/2026", 'Lista Movimenti'!$D:$D, "<=30/04/2026") -> 0 | D17: 15
B18: 🚌 Trasporti | C18: =SUMIFS('Lista Movimenti'!$C:$C, 'Lista Movimenti'!$B:$B, $B18, 'Lista Movimenti'!$E:$E, "Spesa", 'Lista Movimenti'!$D:$D, ">=01/04/2026", 'Lista Movimenti'!$D:$D, "<=30/04/2026") -> 0 | D18: 45
B19: 👕 Vestiti | C19: =SUMIFS('Lista Movimenti'!$C:$C, 'Lista Movimenti'!$B:$B, $B19, 'Lista Movimenti'!$E:$E, "Spesa", 'Lista Movimenti'!$D:$D, ">=01/04/2026", 'Lista Movimenti'!$D:$D, "<=30/04/2026") -> 0 | D19: 35
A20: Totale Necessità | B20: -- Necessità -- | C20: =SUM(C13:C19) -> 300 | D20: =SUM(D13:D19) -> 665
A22: EXTRA | B22: -- Extra -- | C22: Totale | D22: Obiettivo
B23: 🎫 Abbonamenti | C23: =SUMIFS('Lista Movimenti'!$C:$C, 'Lista Movimenti'!$B:$B, $B23, 'Lista Movimenti'!$E:$E, "Spesa", 'Lista Movimenti'!$D:$D, ">=01/04/2026", 'Lista Movimenti'!$D:$D, "<=30/04/2026") -> 32 | D23: 22
B24: 🍔 Cibo fuori | C24: =SUMIFS('Lista Movimenti'!$C:$C, 'Lista Movimenti'!$B:$B, $B24, 'Lista Movimenti'!$E:$E, "Spesa", 'Lista Movimenti'!$D:$D, ">=01/04/2026", 'Lista Movimenti'!$D:$D, "<=30/04/2026") -> 0 | D24: 85
B25: 🎬 Intrattenimento | C25: =SUMIFS('Lista Movimenti'!$C:$C, 'Lista Movimenti'!$B:$B, $B25, 'Lista Movimenti'!$E:$E, "Spesa", 'Lista Movimenti'!$D:$D, ">=01/04/2026", 'Lista Movimenti'!$D:$D, "<=30/04/2026") -> 0 | D25: 24
B26: 🎁 Regali | C26: =SUMIFS('Lista Movimenti'!$C:$C, 'Lista Movimenti'!$B:$B, $B26, 'Lista Movimenti'!$E:$E, "Spesa", 'Lista Movimenti'!$D:$D, ">=01/04/2026", 'Lista Movimenti'!$D:$D, "<=30/04/2026") -> 0 | D26: 20
B27: ✈️ Viaggi/Vacanze | C27: =SUMIFS('Lista Movimenti'!$C:$C, 'Lista Movimenti'!$B:$B, $B27, 'Lista Movimenti'!$E:$E, "Spesa", 'Lista Movimenti'!$D:$D, ">=01/04/2026", 'Lista Movimenti'!$D:$D, "<=30/04/2026") -> 0 | D27: 60
B28: 📚 Cultura | C28: =SUMIFS('Lista Movimenti'!$C:$C, 'Lista Movimenti'!$B:$B, $B28, 'Lista Movimenti'!$E:$E, "Spesa", 'Lista Movimenti'!$D:$D, ">=01/04/2026", 'Lista Movimenti'!$D:$D, "<=30/04/2026") -> 0 | D28: 40
B29: 💅 Cura personale | C29: =SUMIFS('Lista Movimenti'!$C:$C, 'Lista Movimenti'!$B:$B, $B29, 'Lista Movimenti'!$E:$E, "Spesa", 'Lista Movimenti'!$D:$D, ">=01/04/2026", 'Lista Movimenti'!$D:$D, "<=30/04/2026") -> 0 | D29: 95
B30: 🌟 Altro extra | C30: =SUMIFS('Lista Movimenti'!$C:$C, 'Lista Movimenti'!$B:$B, $B30, 'Lista Movimenti'!$E:$E, "Spesa", 'Lista Movimenti'!$D:$D, ">=01/04/2026", 'Lista Movimenti'!$D:$D, "<=30/04/2026") -> 0 | D30: 13
A31: Totale Extra | B31: -- Extra -- | C31: =SUM(C23:C30) -> 32 | D31: =SUM(D23:D30) -> 359
A33: Totale Uscite | C33: =(C31 + C20) -> 332 | D33: =(D31 + D20) -> 1024
A34: Differenza Entrate Uscite | C34: =(B8-C33) -> 968
A37: Categoria | B37: Totale | C37: Obiettivo
A38: 🏠 Casa | B38: =SUMIFS('Lista Movimenti'!$C:$C, 'Lista Movimenti'!$B:$B, $A38, 'Lista Movimenti'!$E:$E, "Risparmio", 'Lista Movimenti'!$D:$D, ">=01/04/2026", 'Lista Movimenti'!$D:$D, "<=30/04/2026") -> 300
A39: 🍲 Cibo/Spesa | B39: =SUMIFS('Lista Movimenti'!$C:$C, 'Lista Movimenti'!$B:$B, $A39, 'Lista Movimenti'!$E:$E, "Risparmio", 'Lista Movimenti'!$D:$D, ">=01/04/2026", 'Lista Movimenti'!$D:$D, "<=30/04/2026") -> 0
A40: 🚑 Sanità | B40: =SUMIFS('Lista Movimenti'!$C:$C, 'Lista Movimenti'!$B:$B, $A40, 'Lista Movimenti'!$E:$E, "Risparmio", 'Lista Movimenti'!$D:$D, ">=01/04/2026", 'Lista Movimenti'!$D:$D, "<=30/04/2026") -> 0
A41: 🏋️ Palestra e affini | B41: =SUMIFS('Lista Movimenti'!$C:$C, 'Lista Movimenti'!$B:$B, $A41, 'Lista Movimenti'!$E:$E, "Risparmio", 'Lista Movimenti'!$D:$D, ">=01/04/2026", 'Lista Movimenti'!$D:$D, "<=30/04/2026") -> 0
A42: 📱 Telefono | B42: =SUMIFS('Lista Movimenti'!$C:$C, 'Lista Movimenti'!$B:$B, $A42, 'Lista Movimenti'!$E:$E, "Risparmio", 'Lista Movimenti'!$D:$D, ">=01/04/2026", 'Lista Movimenti'!$D:$D, "<=30/04/2026") -> 0
A43: 🚌 Trasporti | B43: =SUMIFS('Lista Movimenti'!$C:$C, 'Lista Movimenti'!$B:$B, $A43, 'Lista Movimenti'!$E:$E, "Risparmio", 'Lista Movimenti'!$D:$D, ">=01/04/2026", 'Lista Movimenti'!$D:$D, "<=30/04/2026") -> 0
A44: 👕 Vestiti | B44: =SUMIFS('Lista Movimenti'!$C:$C, 'Lista Movimenti'!$B:$B, $A44, 'Lista Movimenti'!$E:$E, "Risparmio", 'Lista Movimenti'!$D:$D, ">=01/04/2026", 'Lista Movimenti'!$D:$D, "<=30/04/2026") -> 0
A45: 🎫 Abbonamenti | B45: =SUMIFS('Lista Movimenti'!$C:$C, 'Lista Movimenti'!$B:$B, $A45, 'Lista Movimenti'!$E:$E, "Risparmio", 'Lista Movimenti'!$D:$D, ">=01/04/2026", 'Lista Movimenti'!$D:$D, "<=30/04/2026") -> 0
A46: 🍔 Cibo fuori | B46: =SUMIFS('Lista Movimenti'!$C:$C, 'Lista Movimenti'!$B:$B, $A46, 'Lista Movimenti'!$E:$E, "Risparmio", 'Lista Movimenti'!$D:$D, ">=01/04/2026", 'Lista Movimenti'!$D:$D, "<=30/04/2026") -> 0
A47: 🎬 Intrattenimento | B47: =SUMIFS('Lista Movimenti'!$C:$C, 'Lista Movimenti'!$B:$B, $A47, 'Lista Movimenti'!$E:$E, "Risparmio", 'Lista Movimenti'!$D:$D, ">=01/04/2026", 'Lista Movimenti'!$D:$D, "<=30/04/2026") -> 0
A48: 🎁 Regali | B48: =SUMIFS('Lista Movimenti'!$C:$C, 'Lista Movimenti'!$B:$B, $A48, 'Lista Movimenti'!$E:$E, "Risparmio", 'Lista Movimenti'!$D:$D, ">=01/04/2026", 'Lista Movimenti'!$D:$D, "<=30/04/2026") -> 0
A49: ✈️ Viaggi/Vacanze | B49: =SUMIFS('Lista Movimenti'!$C:$C, 'Lista Movimenti'!$B:$B, $A49, 'Lista Movimenti'!$E:$E, "Risparmio", 'Lista Movimenti'!$D:$D, ">=01/04/2026", 'Lista Movimenti'!$D:$D, "<=30/04/2026") -> 0
... A54: 🪙 Altre entrate | B54: =SUMIFS('Lista Movimenti'!$C:$C, 'Lista Movimenti'!$B:$B, $A54, 'Lista Movimenti'!$E:$E, "Risparmio", 'Lista Movimenti'!$D:$D, ">=01/04/2026", 'Lista Movimenti'!$D:$D, "<=30/04/2026") -> 0
A55: Totale Risparmi | B55: =SUM(Risparmi_5[Totale]) -> 300 | C55: =SUM(Risparmi_5[Obiettivo]) -> 0 | S55: 0

Sheet Mag
A1: GENNAIO
A3: Categoria | B3: Totale | C3: Obiettivo
A4: 🤑 Stipendio | B4: =SUMIFS('Lista Movimenti'!$C:$C, 'Lista Movimenti'!$B:$B, $A4, 'Lista Movimenti'!$D:$D, ">="&DATE(2026,5,1), 'Lista Movimenti'!$D:$D, "<="&DATE(2026,5,31)) -> 1230
A5: 🪙 Altre entrate | B5: =SUMIFS('Lista Movimenti'!$C:$C, 'Lista Movimenti'!$B:$B, $A5, 'Lista Movimenti'!$D:$D, ">="&DATE(2026,5,1), 'Lista Movimenti'!$D:$D, "<="&DATE(2026,5,31)) -> 30
B6: =SUMIFS('Lista Movimenti'!$C:$C, 'Lista Movimenti'!$B:$B, $A6, 'Lista Movimenti'!$D:$D, ">="&DATE(2026,5,1), 'Lista Movimenti'!$D:$D, "<="&DATE(2026,5,31)) -> 0
B7: =SUMIFS('Lista Movimenti'!$C:$C, 'Lista Movimenti'!$B:$B, $A7, 'Lista Movimenti'!$D:$D, ">="&DATE(2026,5,1), 'Lista Movimenti'!$D:$D, "<="&DATE(2026,5,31)) -> 0
B8: =SUM(Entrate_Mag[Totale]) -> 1260 | C8: =SUM(Entrate_Mag[Obiettivo]) -> 0
A12: Necessita | B12: Categoria | C12: Totale | D12: Obiettivo
B13: 🏠 Casa | C13: =SUMIFS('Lista Movimenti'!$C:$C, 'Lista Movimenti'!$B:$B, $B13, 'Lista Movimenti'!$E:$E, "Spesa", 'Lista Movimenti'!$D:$D, ">=01/05/2026", 'Lista Movimenti'!$D:$D, "<=31/05/2026") -> 0 | D13: 200
B14: 🍲 Cibo/Spesa | C14: =SUMIFS('Lista Movimenti'!$C:$C, 'Lista Movimenti'!$B:$B, $B14, 'Lista Movimenti'!$E:$E, "Spesa", 'Lista Movimenti'!$D:$D, ">=01/05/2026", 'Lista Movimenti'!$D:$D, "<=31/05/2026") -> 0 | D14: 280
B15: 🚑 Sanità | C15: =SUMIFS('Lista Movimenti'!$C:$C, 'Lista Movimenti'!$B:$B, $B15, 'Lista Movimenti'!$E:$E, "Spesa", 'Lista Movimenti'!$D:$D, ">=01/05/2026", 'Lista Movimenti'!$D:$D, "<=31/05/2026") -> 0 | D15: 50
B16: 🏋️ Palestra e affini | C16: =SUMIFS('Lista Movimenti'!$C:$C, 'Lista Movimenti'!$B:$B, $B16, 'Lista Movimenti'!$E:$E, "Spesa", 'Lista Movimenti'!$D:$D, ">=01/05/2026", 'Lista Movimenti'!$D:$D, "<=31/05/2026") -> 0 | D16: 40
B17: 📱 Telefono | C17: =SUMIFS('Lista Movimenti'!$C:$C, 'Lista Movimenti'!$B:$B, $B17, 'Lista Movimenti'!$E:$E, "Spesa", 'Lista Movimenti'!$D:$D, ">=01/05/2026", 'Lista Movimenti'!$D:$D, "<=31/05/2026") -> 0 | D17: 15
B18: 🚌 Trasporti | C18: =SUMIFS('Lista Movimenti'!$C:$C, 'Lista Movimenti'!$B:$B, $B18, 'Lista Movimenti'!$E:$E, "Spesa", 'Lista Movimenti'!$D:$D, ">=01/05/2026", 'Lista Movimenti'!$D:$D, "<=31/05/2026") -> 0 | D18: 45
B19: 👕 Vestiti | C19: =SUMIFS('Lista Movimenti'!$C:$C, 'Lista Movimenti'!$B:$B, $B19, 'Lista Movimenti'!$E:$E, "Spesa", 'Lista Movimenti'!$D:$D, ">=01/05/2026", 'Lista Movimenti'!$D:$D, "<=31/05/2026") -> 0 | D19: 35
A20: Totale Necessità | B20: -- Necessità -- | C20: =SUM(C13:C19) -> 0 | D20: =SUM(D13:D19) -> 665
A22: EXTRA | B22: -- Extra -- | C22: Totale | D22: Obiettivo
B23: 🎫 Abbonamenti | C23: =SUMIFS('Lista Movimenti'!$C:$C, 'Lista Movimenti'!$B:$B, $B23, 'Lista Movimenti'!$E:$E, "Spesa", 'Lista Movimenti'!$D:$D, ">=01/05/2026", 'Lista Movimenti'!$D:$D, "<=31/05/2026") -> 0 | D23: 22
B24: 🍔 Cibo fuori | C24: =SUMIFS('Lista Movimenti'!$C:$C, 'Lista Movimenti'!$B:$B, $B24, 'Lista Movimenti'!$E:$E, "Spesa", 'Lista Movimenti'!$D:$D, ">=01/05/2026", 'Lista Movimenti'!$D:$D, "<=31/05/2026") -> 0 | D24: 85
B25: 🎬 Intrattenimento | C25: =SUMIFS('Lista Movimenti'!$C:$C, 'Lista Movimenti'!$B:$B, $B25, 'Lista Movimenti'!$E:$E, "Spesa", 'Lista Movimenti'!$D:$D, ">=01/05/2026", 'Lista Movimenti'!$D:$D, "<=31/05/2026") -> 24 | D25: 24
B26: 🎁 Regali | C26: =SUMIFS('Lista Movimenti'!$C:$C, 'Lista Movimenti'!$B:$B, $B26, 'Lista Movimenti'!$E:$E, "Spesa", 'Lista Movimenti'!$D:$D, ">=01/05/2026", 'Lista Movimenti'!$D:$D, "<=31/05/2026") -> 50 | D26: 20
B27: ✈️ Viaggi/Vacanze | C27: =SUMIFS('Lista Movimenti'!$C:$C, 'Lista Movimenti'!$B:$B, $B27, 'Lista Movimenti'!$E:$E, "Spesa", 'Lista Movimenti'!$D:$D, ">=01/05/2026", 'Lista Movimenti'!$D:$D, "<=31/05/2026") -> 300 | D27: 60
B28: 📚 Cultura | C28: =SUMIFS('Lista Movimenti'!$C:$C, 'Lista Movimenti'!$B:$B, $B28, 'Lista Movimenti'!$E:$E, "Spesa", 'Lista Movimenti'!$D:$D, ">=01/05/2026", 'Lista Movimenti'!$D:$D, "<=31/05/2026") -> 0 | D28: 40
B29: 💅 Cura personale | C29: =SUMIFS('Lista Movimenti'!$C:$C, 'Lista Movimenti'!$B:$B, $B29, 'Lista Movimenti'!$E:$E, "Spesa", 'Lista Movimenti'!$D:$D, ">=01/05/2026", 'Lista Movimenti'!$D:$D, "<=31/05/2026") -> 0 | D29: 95
B30: 🌟 Altro extra | C30: =SUMIFS('Lista Movimenti'!$C:$C, 'Lista Movimenti'!$B:$B, $B30, 'Lista Movimenti'!$E:$E, "Spesa", 'Lista Movimenti'!$D:$D, ">=01/05/2026", 'Lista Movimenti'!$D:$D, "<=31/05/2026") -> 0 | D30: 13
A31: Totale Extra | B31: -- Extra -- | C31: =SUM(C23:C30) -> 374 | D31: =SUM(D23:D30) -> 359
A33: Totale Uscite | C33: =(C31 + C20) -> 374 | D33: =(D31 + D20) -> 1024
A34: Differenza Entrate Uscite | C34: =(B8-C33) -> 886
A37: Categoria | B37: Totale | C37: Obiettivo
A38: 🏠 Casa | B38: =SUMIFS('Lista Movimenti'!$C:$C, 'Lista Movimenti'!$B:$B, $A38, 'Lista Movimenti'!$E:$E, "Risparmio", 'Lista Movimenti'!$D:$D, ">=01/05/2026", 'Lista Movimenti'!$D:$D, "<=31/05/2026") -> 500
A39: 🍲 Cibo/Spesa | B39: =SUMIFS('Lista Movimenti'!$C:$C, 'Lista Movimenti'!$B:$B, $A39, 'Lista Movimenti'!$E:$E, "Risparmio", 'Lista Movimenti'!$D:$D, ">=01/05/2026", 'Lista Movimenti'!$D:$D, "<=31/05/2026") -> 0
A40: 🚑 Sanità | B40: =SUMIFS('Lista Movimenti'!$C:$C, 'Lista Movimenti'!$B:$B, $A40, 'Lista Movimenti'!$E:$E, "Risparmio", 'Lista Movimenti'!$D:$D, ">=01/05/2026", 'Lista Movimenti'!$D:$D, "<=31/05/2026") -> 0
A41: 🏋️ Palestra e affini | B41: =SUMIFS('Lista Movimenti'!$C:$C, 'Lista Movimenti'!$B:$B, $A41, 'Lista Movimenti'!$E:$E, "Risparmio", 'Lista Movimenti'!$D:$D, ">=01/05/2026", 'Lista Movimenti'!$D:$D, "<=31/05/2026") -> 0
A42: 📱 Telefono | B42: =SUMIFS('Lista Movimenti'!$C:$C, 'Lista Movimenti'!$B:$B, $A42, 'Lista Movimenti'!$E:$E, "Risparmio", 'Lista Movimenti'!$D:$D, ">=01/05/2026", 'Lista Movimenti'!$D:$D, "<=31/05/2026") -> 0
A43: 🚌 Trasporti | B43: =SUMIFS('Lista Movimenti'!$C:$C, 'Lista Movimenti'!$B:$B, $A43, 'Lista Movimenti'!$E:$E, "Risparmio", 'Lista Movimenti'!$D:$D, ">=01/05/2026", 'Lista Movimenti'!$D:$D, "<=31/05/2026") -> 0
A44: 👕 Vestiti | B44: =SUMIFS('Lista Movimenti'!$C:$C, 'Lista Movimenti'!$B:$B, $A44, 'Lista Movimenti'!$E:$E, "Risparmio", 'Lista Movimenti'!$D:$D, ">=01/05/2026", 'Lista Movimenti'!$D:$D, "<=31/05/2026") -> 0
A45: 🎫 Abbonamenti | B45: =SUMIFS('Lista Movimenti'!$C:$C, 'Lista Movimenti'!$B:$B, $A45, 'Lista Movimenti'!$E:$E, "Risparmio", 'Lista Movimenti'!$D:$D, ">=01/05/2026", 'Lista Movimenti'!$D:$D, "<=31/05/2026") -> 0
A46: 🍔 Cibo fuori | B46: =SUMIFS('Lista Movimenti'!$C:$C, 'Lista Movimenti'!$B:$B, $A46, 'Lista Movimenti'!$E:$E, "Risparmio", 'Lista Movimenti'!$D:$D, ">=01/05/2026", 'Lista Movimenti'!$D:$D, "<=31/05/2026") -> 0
A47: 🎬 Intrattenimento | B47: =SUMIFS('Lista Movimenti'!$C:$C, 'Lista Movimenti'!$B:$B, $A47, 'Lista Movimenti'!$E:$E, "Risparmio", 'Lista Movimenti'!$D:$D, ">=01/05/2026", 'Lista Movimenti'!$D:$D, "<=31/05/2026") -> 0
A48: 🎁 Regali | B48: =SUMIFS('Lista Movimenti'!$C:$C, 'Lista Movimenti'!$B:$B, $A48, 'Lista Movimenti'!$E:$E, "Risparmio", 'Lista Movimenti'!$D:$D, ">=01/05/2026", 'Lista Movimenti'!$D:$D, "<=31/05/2026") -> 0
A49: ✈️ Viaggi/Vacanze | B49: =SUMIFS('Lista Movimenti'!$C:$C, 'Lista Movimenti'!$B:$B, $A49, 'Lista Movimenti'!$E:$E, "Risparmio", 'Lista Movimenti'!$D:$D, ">=01/05/2026", 'Lista Movimenti'!$D:$D, "<=31/05/2026") -> 0
... A54: 🪙 Altre entrate | B54: =SUMIFS('Lista Movimenti'!$C:$C, 'Lista Movimenti'!$B:$B, $A54, 'Lista Movimenti'!$E:$E, "Risparmio", 'Lista Movimenti'!$D:$D, ">=01/05/2026", 'Lista Movimenti'!$D:$D, "<=31/05/2026") -> 0
A55: Totale Risparmi | B55: =SUM(Risparmi_4[Totale]) -> 500 | C55: =SUM(Risparmi_4[Obiettivo]) -> 0 | S55: 0

Sheet Giu
A1: GENNAIO
A3: Categoria | B3: Totale | C3: Obiettivo
A4: 🤑 Stipendio | B4: =SUMIFS('Lista Movimenti'!$C:$C, 'Lista Movimenti'!$B:$B, $A4, 'Lista Movimenti'!$D:$D, ">="&DATE(2026,6,1), 'Lista Movimenti'!$D:$D, "<="&DATE(2026,6,30)) -> 1450
A5: 🪙 Altre entrate | B5: =SUMIFS('Lista Movimenti'!$C:$C, 'Lista Movimenti'!$B:$B, $A5, 'Lista Movimenti'!$D:$D, ">="&DATE(2026,6,1), 'Lista Movimenti'!$D:$D, "<="&DATE(2026,6,30)) -> 0
B6: =SUMIFS('Lista Movimenti'!$C:$C, 'Lista Movimenti'!$B:$B, $A6, 'Lista Movimenti'!$D:$D, ">="&DATE(2026,6,1), 'Lista Movimenti'!$D:$D, "<="&DATE(2026,6,30)) -> 0
B7: =SUMIFS('Lista Movimenti'!$C:$C, 'Lista Movimenti'!$B:$B, $A7, 'Lista Movimenti'!$D:$D, ">="&DATE(2026,6,1), 'Lista Movimenti'!$D:$D, "<="&DATE(2026,6,30)) -> 0
B8: =SUM(Entrate_Giu[Totale]) -> 1450 | C8: =SUM(Entrate_Giu[Obiettivo]) -> 0
A12: Necessita | B12: Categoria | C12: Totale | D12: Obiettivo
B13: 🏠 Casa | C13: =SUMIFS('Lista Movimenti'!$C:$C, 'Lista Movimenti'!$B:$B, $B13, 'Lista Movimenti'!$E:$E, "Spesa", 'Lista Movimenti'!$D:$D, ">=01/06/2026", 'Lista Movimenti'!$D:$D, "<=30/06/2026") -> 0 | D13: 200
B14: 🍲 Cibo/Spesa | C14: =SUMIFS('Lista Movimenti'!$C:$C, 'Lista Movimenti'!$B:$B, $B14, 'Lista Movimenti'!$E:$E, "Spesa", 'Lista Movimenti'!$D:$D, ">=01/06/2026", 'Lista Movimenti'!$D:$D, "<=30/06/2026") -> 0 | D14: 280
B15: 🚑 Sanità | C15: =SUMIFS('Lista Movimenti'!$C:$C, 'Lista Movimenti'!$B:$B, $B15, 'Lista Movimenti'!$E:$E, "Spesa", 'Lista Movimenti'!$D:$D, ">=01/06/2026", 'Lista Movimenti'!$D:$D, "<=30/06/2026") -> 0 | D15: 50
B16: 🏋️ Palestra e affini | C16: =SUMIFS('Lista Movimenti'!$C:$C, 'Lista Movimenti'!$B:$B, $B16, 'Lista Movimenti'!$E:$E, "Spesa", 'Lista Movimenti'!$D:$D, ">=01/06/2026", 'Lista Movimenti'!$D:$D, "<=30/06/2026") -> 0 | D16: 40
B17: 📱 Telefono | C17: =SUMIFS('Lista Movimenti'!$C:$C, 'Lista Movimenti'!$B:$B, $B17, 'Lista Movimenti'!$E:$E, "Spesa", 'Lista Movimenti'!$D:$D, ">=01/06/2026", 'Lista Movimenti'!$D:$D, "<=30/06/2026") -> 35 | D17: 15
B18: 🚌 Trasporti | C18: =SUMIFS('Lista Movimenti'!$C:$C, 'Lista Movimenti'!$B:$B, $B18, 'Lista Movimenti'!$E:$E, "Spesa", 'Lista Movimenti'!$D:$D, ">=01/06/2026", 'Lista Movimenti'!$D:$D, "<=30/06/2026") -> 0 | D18: 45
B19: 👕 Vestiti | C19: =SUMIFS('Lista Movimenti'!$C:$C, 'Lista Movimenti'!$B:$B, $B19, 'Lista Movimenti'!$E:$E, "Spesa", 'Lista Movimenti'!$D:$D, ">=01/06/2026", 'Lista Movimenti'!$D:$D, "<=30/06/2026") -> 0 | D19: 35
A20: Totale Necessità | B20: -- Necessità -- | C20: =SUM(C13:C19) -> 35 | D20: =SUM(D13:D19) -> 665
A22: EXTRA | B22: -- Extra -- | C22: Totale | D22: Obiettivo
B23: 🎫 Abbonamenti | C23: =SUMIFS('Lista Movimenti'!$C:$C, 'Lista Movimenti'!$B:$B, $B23, 'Lista Movimenti'!$E:$E, "Spesa", 'Lista Movimenti'!$D:$D, ">=01/06/2026", 'Lista Movimenti'!$D:$D, "<=30/06/2026") -> 0 | D23: 22
B24: 🍔 Cibo fuori | C24: =SUMIFS('Lista Movimenti'!$C:$C, 'Lista Movimenti'!$B:$B, $B24, 'Lista Movimenti'!$E:$E, "Spesa", 'Lista Movimenti'!$D:$D, ">=01/06/2026", 'Lista Movimenti'!$D:$D, "<=30/06/2026") -> 0 | D24: 85
B25: 🎬 Intrattenimento | C25: =SUMIFS('Lista Movimenti'!$C:$C, 'Lista Movimenti'!$B:$B, $B25, 'Lista Movimenti'!$E:$E, "Spesa", 'Lista Movimenti'!$D:$D, ">=01/06/2026", 'Lista Movimenti'!$D:$D, "<=30/06/2026") -> 22 | D25: 24
B26: 🎁 Regali | C26: =SUMIFS('Lista Movimenti'!$C:$C, 'Lista Movimenti'!$B:$B, $B26, 'Lista Movimenti'!$E:$E, "Spesa", 'Lista Movimenti'!$D:$D, ">=01/06/2026", 'Lista Movimenti'!$D:$D, "<=30/06/2026") -> 0 | D26: 20
B27: ✈️ Viaggi/Vacanze | C27: =SUMIFS('Lista Movimenti'!$C:$C, 'Lista Movimenti'!$B:$B, $B27, 'Lista Movimenti'!$E:$E, "Spesa", 'Lista Movimenti'!$D:$D, ">=01/06/2026", 'Lista Movimenti'!$D:$D, "<=30/06/2026") -> 0 | D27: 60
B28: 📚 Cultura | C28: =SUMIFS('Lista Movimenti'!$C:$C, 'Lista Movimenti'!$B:$B, $B28, 'Lista Movimenti'!$E:$E, "Spesa", 'Lista Movimenti'!$D:$D, ">=01/06/2026", 'Lista Movimenti'!$D:$D, "<=30/06/2026") -> 0 | D28: 40
B29: 💅 Cura personale | C29: =SUMIFS('Lista Movimenti'!$C:$C, 'Lista Movimenti'!$B:$B, $B29, 'Lista Movimenti'!$E:$E, "Spesa", 'Lista Movimenti'!$D:$D, ">=01/06/2026", 'Lista Movimenti'!$D:$D, "<=30/06/2026") -> 0 | D29: 95
B30: 🌟 Altro extra | C30: =SUMIFS('Lista Movimenti'!$C:$C, 'Lista Movimenti'!$B:$B, $B30, 'Lista Movimenti'!$E:$E, "Spesa", 'Lista Movimenti'!$D:$D, ">=01/06/2026", 'Lista Movimenti'!$D:$D, "<=30/06/2026") -> 0 | D30: 13
A31: Totale Extra | B31: -- Extra -- | C31: =SUM(C23:C30) -> 22 | D31: =SUM(D23:D30) -> 359
A33: Totale Uscite | C33: =(C31 + C20) -> 57 | D33: =(D31 + D20) -> 1024
A34: Differenza Entrate Uscite | C34: =(B8-C33) -> 1393
A37: Categoria | B37: Totale | C37: Obiettivo
A38: 🏠 Casa | B38: =SUMIFS('Lista Movimenti'!$C:$C, 'Lista Movimenti'!$B:$B, $A38, 'Lista Movimenti'!$E:$E, "Risparmio", 'Lista Movimenti'!$D:$D, ">=01/06/2026", 'Lista Movimenti'!$D:$D, "<=30/06/2026") -> 0
A39: 🍲 Cibo/Spesa | B39: =SUMIFS('Lista Movimenti'!$C:$C, 'Lista Movimenti'!$B:$B, $A39, 'Lista Movimenti'!$E:$E, "Risparmio", 'Lista Movimenti'!$D:$D, ">=01/06/2026", 'Lista Movimenti'!$D:$D, "<=30/06/2026") -> 0
A40: 🚑 Sanità | B40: =SUMIFS('Lista Movimenti'!$C:$C, 'Lista Movimenti'!$B:$B, $A40, 'Lista Movimenti'!$E:$E, "Risparmio", 'Lista Movimenti'!$D:$D, ">=01/06/2026", 'Lista Movimenti'!$D:$D, "<=30/06/2026") -> 0
A41: 🏋️ Palestra e affini | B41: =SUMIFS('Lista Movimenti'!$C:$C, 'Lista Movimenti'!$B:$B, $A41, 'Lista Movimenti'!$E:$E, "Risparmio", 'Lista Movimenti'!$D:$D, ">=01/06/2026", 'Lista Movimenti'!$D:$D, "<=30/06/2026") -> 0
A42: 📱 Telefono | B42: =SUMIFS('Lista Movimenti'!$C:$C, 'Lista Movimenti'!$B:$B, $A42, 'Lista Movimenti'!$E:$E, "Risparmio", 'Lista Movimenti'!$D:$D, ">=01/06/2026", 'Lista Movimenti'!$D:$D, "<=30/06/2026") -> 0
A43: 🚌 Trasporti | B43: =SUMIFS('Lista Movimenti'!$C:$C, 'Lista Movimenti'!$B:$B, $A43, 'Lista Movimenti'!$E:$E, "Risparmio", 'Lista Movimenti'!$D:$D, ">=01/06/2026", 'Lista Movimenti'!$D:$D, "<=30/06/2026") -> 0
A44: 👕 Vestiti | B44: =SUMIFS('Lista Movimenti'!$C:$C, 'Lista Movimenti'!$B:$B, $A44, 'Lista Movimenti'!$E:$E, "Risparmio", 'Lista Movimenti'!$D:$D, ">=01/06/2026", 'Lista Movimenti'!$D:$D, "<=30/06/2026") -> 0
A45: 🎫 Abbonamenti | B45: =SUMIFS('Lista Movimenti'!$C:$C, 'Lista Movimenti'!$B:$B, $A45, 'Lista Movimenti'!$E:$E, "Risparmio", 'Lista Movimenti'!$D:$D, ">=01/06/2026", 'Lista Movimenti'!$D:$D, "<=30/06/2026") -> 0
A46: 🍔 Cibo fuori | B46: =SUMIFS('Lista Movimenti'!$C:$C, 'Lista Movimenti'!$B:$B, $A46, 'Lista Movimenti'!$E:$E, "Risparmio", 'Lista Movimenti'!$D:$D, ">=01/06/2026", 'Lista Movimenti'!$D:$D, "<=30/06/2026") -> 0
A47: 🎬 Intrattenimento | B47: =SUMIFS('Lista Movimenti'!$C:$C, 'Lista Movimenti'!$B:$B, $A47, 'Lista Movimenti'!$E:$E, "Risparmio", 'Lista Movimenti'!$D:$D, ">=01/06/2026", 'Lista Movimenti'!$D:$D, "<=30/06/2026") -> 0
A48: 🎁 Regali | B48: =SUMIFS('Lista Movimenti'!$C:$C, 'Lista Movimenti'!$B:$B, $A48, 'Lista Movimenti'!$E:$E, "Risparmio", 'Lista Movimenti'!$D:$D, ">=01/06/2026", 'Lista Movimenti'!$D:$D, "<=30/06/2026") -> 0
A49: ✈️ Viaggi/Vacanze | B49: =SUMIFS('Lista Movimenti'!$C:$C, 'Lista Movimenti'!$B:$B, $A49, 'Lista Movimenti'!$E:$E, "Risparmio", 'Lista Movimenti'!$D:$D, ">=01/06/2026", 'Lista Movimenti'!$D:$D, "<=30/06/2026") -> 0
... A54: 🪙 Altre entrate | B54: =SUMIFS('Lista Movimenti'!$C:$C, 'Lista Movimenti'!$B:$B, $A54, 'Lista Movimenti'!$E:$E, "Risparmio", 'Lista Movimenti'!$D:$D, ">=01/06/2026", 'Lista Movimenti'!$D:$D, "<=30/06/2026") -> 0
A55: Totale Risparmi | B55: =SUM(Risparmi_6[Totale]) -> 0 | C55: =SUM(Risparmi_6[Obiettivo]) -> 0 | S55: 0

Sheet Lug
A1: GENNAIO
A3: Categoria | B3: Totale | C3: Obiettivo
A4: 🤑 Stipendio | B4: =SUMIFS('Lista Movimenti'!$C:$C, 'Lista Movimenti'!$B:$B, $A4, 'Lista Movimenti'!$D:$D, ">="&DATE(2026,7,1), 'Lista Movimenti'!$D:$D, "<="&DATE(2026,7,31)) -> 1000
A5: 🪙 Altre entrate | B5: =SUMIFS('Lista Movimenti'!$C:$C, 'Lista Movimenti'!$B:$B, $A5, 'Lista Movimenti'!$D:$D, ">="&DATE(2026,7,1), 'Lista Movimenti'!$D:$D, "<="&DATE(2026,7,31)) -> 0
B6: =SUMIFS('Lista Movimenti'!$C:$C, 'Lista Movimenti'!$B:$B, $A6, 'Lista Movimenti'!$D:$D, ">="&DATE(2026,7,1), 'Lista Movimenti'!$D:$D, "<="&DATE(2026,7,31)) -> 0
B7: =SUMIFS('Lista Movimenti'!$C:$C, 'Lista Movimenti'!$B:$B, $A7, 'Lista Movimenti'!$D:$D, ">="&DATE(2026,7,1), 'Lista Movimenti'!$D:$D, "<="&DATE(2026,7,31)) -> 0
B8: =SUM(Entrate_Lug[Totale]) -> 1000 | C8: =SUM(Entrate_Lug[Obiettivo]) -> 0
A12: Necessita | B12: Categoria | C12: Totale | D12: Obiettivo
B13: 🏠 Casa | C13: =SUMIFS('Lista Movimenti'!$C:$C, 'Lista Movimenti'!$B:$B, $B13, 'Lista Movimenti'!$E:$E, "Spesa", 'Lista Movimenti'!$D:$D, ">=01/07/2026", 'Lista Movimenti'!$D:$D, "<=31/07/2026") -> 399 | D13: 200
B14: 🍲 Cibo/Spesa | C14: =SUMIFS('Lista Movimenti'!$C:$C, 'Lista Movimenti'!$B:$B, $B14, 'Lista Movimenti'!$E:$E, "Spesa", 'Lista Movimenti'!$D:$D, ">=01/07/2026", 'Lista Movimenti'!$D:$D, "<=31/07/2026") -> 200 | D14: 280
B15: 🚑 Sanità | C15: =SUMIFS('Lista Movimenti'!$C:$C, 'Lista Movimenti'!$B:$B, $B15, 'Lista Movimenti'!$E:$E, "Spesa", 'Lista Movimenti'!$D:$D, ">=01/07/2026", 'Lista Movimenti'!$D:$D, "<=31/07/2026") -> 0 | D15: 50
B16: 🏋️ Palestra e affini | C16: =SUMIFS('Lista Movimenti'!$C:$C, 'Lista Movimenti'!$B:$B, $B16, 'Lista Movimenti'!$E:$E, "Spesa", 'Lista Movimenti'!$D:$D, ">=01/07/2026", 'Lista Movimenti'!$D:$D, "<=31/07/2026") -> 0 | D16: 40
B17: 📱 Telefono | C17: =SUMIFS('Lista Movimenti'!$C:$C, 'Lista Movimenti'!$B:$B, $B17, 'Lista Movimenti'!$E:$E, "Spesa", 'Lista Movimenti'!$D:$D, ">=01/07/2026", 'Lista Movimenti'!$D:$D, "<=31/07/2026") -> 0 | D17: 15
B18: 🚌 Trasporti | C18: =SUMIFS('Lista Movimenti'!$C:$C, 'Lista Movimenti'!$B:$B, $B18, 'Lista Movimenti'!$E:$E, "Spesa", 'Lista Movimenti'!$D:$D, ">=01/07/2026", 'Lista Movimenti'!$D:$D, "<=31/07/2026") -> 0 | D18: 45
B19: 👕 Vestiti | C19: =SUMIFS('Lista Movimenti'!$C:$C, 'Lista Movimenti'!$B:$B, $B19, 'Lista Movimenti'!$E:$E, "Spesa", 'Lista Movimenti'!$D:$D, ">=01/07/2026", 'Lista Movimenti'!$D:$D, "<=31/07/2026") -> 0 | D19: 35
A20: Totale Necessità | B20: -- Necessità -- | C20: =SUM(C13:C19) -> 599 | D20: =SUM(D13:D19) -> 665
A22: EXTRA | B22: -- Extra -- | C22: Totale | D22: Obiettivo
B23: 🎫 Abbonamenti | C23: =SUMIFS('Lista Movimenti'!$C:$C, 'Lista Movimenti'!$B:$B, $B23, 'Lista Movimenti'!$E:$E, "Spesa", 'Lista Movimenti'!$D:$D, ">=01/07/2026", 'Lista Movimenti'!$D:$D, "<=31/07/2026") -> 12 | D23: 22
B24: 🍔 Cibo fuori | C24: =SUMIFS('Lista Movimenti'!$C:$C, 'Lista Movimenti'!$B:$B, $B24, 'Lista Movimenti'!$E:$E, "Spesa", 'Lista Movimenti'!$D:$D, ">=01/07/2026", 'Lista Movimenti'!$D:$D, "<=31/07/2026") -> 0 | D24: 85
B25: 🎬 Intrattenimento | C25: =SUMIFS('Lista Movimenti'!$C:$C, 'Lista Movimenti'!$B:$B, $B25, 'Lista Movimenti'!$E:$E, "Spesa", 'Lista Movimenti'!$D:$D, ">=01/07/2026", 'Lista Movimenti'!$D:$D, "<=31/07/2026") -> 120 | D25: 24
B26: 🎁 Regali | C26: =SUMIFS('Lista Movimenti'!$C:$C, 'Lista Movimenti'!$B:$B, $B26, 'Lista Movimenti'!$E:$E, "Spesa", 'Lista Movimenti'!$D:$D, ">=01/07/2026", 'Lista Movimenti'!$D:$D, "<=31/07/2026") -> 0 | D26: 20
B27: ✈️ Viaggi/Vacanze | C27: =SUMIFS('Lista Movimenti'!$C:$C, 'Lista Movimenti'!$B:$B, $B27, 'Lista Movimenti'!$E:$E, "Spesa", 'Lista Movimenti'!$D:$D, ">=01/07/2026", 'Lista Movimenti'!$D:$D, "<=31/07/2026") -> 120 | D27: 60
B28: 📚 Cultura | C28: =SUMIFS('Lista Movimenti'!$C:$C, 'Lista Movimenti'!$B:$B, $B28, 'Lista Movimenti'!$E:$E, "Spesa", 'Lista Movimenti'!$D:$D, ">=01/07/2026", 'Lista Movimenti'!$D:$D, "<=31/07/2026") -> 0 | D28: 40
B29: 💅 Cura personale | C29: =SUMIFS('Lista Movimenti'!$C:$C, 'Lista Movimenti'!$B:$B, $B29, 'Lista Movimenti'!$E:$E, "Spesa", 'Lista Movimenti'!$D:$D, ">=01/07/2026", 'Lista Movimenti'!$D:$D, "<=31/07/2026") -> 20 | D29: 95
B30: 🌟 Altro extra | C30: =SUMIFS('Lista Movimenti'!$C:$C, 'Lista Movimenti'!$B:$B, $B30, 'Lista Movimenti'!$E:$E, "Spesa", 'Lista Movimenti'!$D:$D, ">=01/07/2026", 'Lista Movimenti'!$D:$D, "<=31/07/2026") -> 30 | D30: 13
A31: Totale Extra | B31: -- Extra -- | C31: =SUM(C23:C30) -> 302 | D31: =SUM(D23:D30) -> 359
A33: Totale Uscite | C33: =(C31 + C20) -> 901 | D33: =(D31 + D20) -> 1024
A34: Differenza Entrate Uscite | C34: =(B8-C33) -> 99
A37: Categoria | B37: Totale | C37: Obiettivo
A38: 🏠 Casa | B38: =SUMIFS('Lista Movimenti'!$C:$C, 'Lista Movimenti'!$B:$B, $A38, 'Lista Movimenti'!$E:$E, "Risparmio", 'Lista Movimenti'!$D:$D, ">=01/07/2026", 'Lista Movimenti'!$D:$D, "<=31/07/2026") -> 0
A39: 🍲 Cibo/Spesa | B39: =SUMIFS('Lista Movimenti'!$C:$C, 'Lista Movimenti'!$B:$B, $A39, 'Lista Movimenti'!$E:$E, "Risparmio", 'Lista Movimenti'!$D:$D, ">=01/07/2026", 'Lista Movimenti'!$D:$D, "<=31/07/2026") -> 0
A40: 🚑 Sanità | B40: =SUMIFS('Lista Movimenti'!$C:$C, 'Lista Movimenti'!$B:$B, $A40, 'Lista Movimenti'!$E:$E, "Risparmio", 'Lista Movimenti'!$D:$D, ">=01/07/2026", 'Lista Movimenti'!$D:$D, "<=31/07/2026") -> 0
A41: 🏋️ Palestra e affini | B41: =SUMIFS('Lista Movimenti'!$C:$C, 'Lista Movimenti'!$B:$B, $A41, 'Lista Movimenti'!$E:$E, "Risparmio", 'Lista Movimenti'!$D:$D, ">=01/07/2026", 'Lista Movimenti'!$D:$D, "<=31/07/2026") -> 0
A42: 📱 Telefono | B42: =SUMIFS('Lista Movimenti'!$C:$C, 'Lista Movimenti'!$B:$B, $A42, 'Lista Movimenti'!$E:$E, "Risparmio", 'Lista Movimenti'!$D:$D, ">=01/07/2026", 'Lista Movimenti'!$D:$D, "<=31/07/2026") -> 0
A43: 🚌 Trasporti | B43: =SUMIFS('Lista Movimenti'!$C:$C, 'Lista Movimenti'!$B:$B, $A43, 'Lista Movimenti'!$E:$E, "Risparmio", 'Lista Movimenti'!$D:$D, ">=01/07/2026", 'Lista Movimenti'!$D:$D, "<=31/07/2026") -> 0
A44: 👕 Vestiti | B44: =SUMIFS('Lista Movimenti'!$C:$C, 'Lista Movimenti'!$B:$B, $A44, 'Lista Movimenti'!$E:$E, "Risparmio", 'Lista Movimenti'!$D:$D, ">=01/07/2026", 'Lista Movimenti'!$D:$D, "<=31/07/2026") -> 0
A45: 🎫 Abbonamenti | B45: =SUMIFS('Lista Movimenti'!$C:$C, 'Lista Movimenti'!$B:$B, $A45, 'Lista Movimenti'!$E:$E, "Risparmio", 'Lista Movimenti'!$D:$D, ">=01/07/2026", 'Lista Movimenti'!$D:$D, "<=31/07/2026") -> 0
A46: 🍔 Cibo fuori | B46: =SUMIFS('Lista Movimenti'!$C:$C, 'Lista Movimenti'!$B:$B, $A46, 'Lista Movimenti'!$E:$E, "Risparmio", 'Lista Movimenti'!$D:$D, ">=01/07/2026", 'Lista Movimenti'!$D:$D, "<=31/07/2026") -> 0
A47: 🎬 Intrattenimento | B47: =SUMIFS('Lista Movimenti'!$C:$C, 'Lista Movimenti'!$B:$B, $A47, 'Lista Movimenti'!$E:$E, "Risparmio", 'Lista Movimenti'!$D:$D, ">=01/07/2026", 'Lista Movimenti'!$D:$D, "<=31/07/2026") -> 0
A48: 🎁 Regali | B48: =SUMIFS('Lista Movimenti'!$C:$C, 'Lista Movimenti'!$B:$B, $A48, 'Lista Movimenti'!$E:$E, "Risparmio", 'Lista Movimenti'!$D:$D, ">=01/07/2026", 'Lista Movimenti'!$D:$D, "<=31/07/2026") -> 100
A49: ✈️ Viaggi/Vacanze | B49: =SUMIFS('Lista Movimenti'!$C:$C, 'Lista Movimenti'!$B:$B, $A49, 'Lista Movimenti'!$E:$E, "Risparmio", 'Lista Movimenti'!$D:$D, ">=01/07/2026", 'Lista Movimenti'!$D:$D, "<=31/07/2026") -> 0
... A54: 🪙 Altre entrate | B54: =SUMIFS('Lista Movimenti'!$C:$C, 'Lista Movimenti'!$B:$B, $A54, 'Lista Movimenti'!$E:$E, "Risparmio", 'Lista Movimenti'!$D:$D, ">=01/07/2026", 'Lista Movimenti'!$D:$D, "<=31/07/2026") -> 0
A55: Totale Risparmi | B55: =SUM(Risparmi_7[Totale]) -> 100 | C55: =SUM(Risparmi_7[Obiettivo]) -> 0 | S55: 0

Sheet Ago
A1: GENNAIO
A3: Categoria | B3: Totale | C3: Obiettivo
A4: 🤑 Stipendio | B4: =SUMIFS('Lista Movimenti'!$C:$C, 'Lista Movimenti'!$B:$B, $A4, 'Lista Movimenti'!$D:$D, ">="&DATE(2026,8,1), 'Lista Movimenti'!$D:$D, "<="&DATE(2026,8,31)) -> 1250
A5: 🪙 Altre entrate | B5: =SUMIFS('Lista Movimenti'!$C:$C, 'Lista Movimenti'!$B:$B, $A5, 'Lista Movimenti'!$D:$D, ">="&DATE(2026,8,1), 'Lista Movimenti'!$D:$D, "<="&DATE(2026,8,31)) -> 60
B6: =SUMIFS('Lista Movimenti'!$C:$C, 'Lista Movimenti'!$B:$B, $A6, 'Lista Movimenti'!$D:$D, ">="&DATE(2026,8,1), 'Lista Movimenti'!$D:$D, "<="&DATE(2026,8,31)) -> 0
B7: =SUMIFS('Lista Movimenti'!$C:$C, 'Lista Movimenti'!$B:$B, $A7, 'Lista Movimenti'!$D:$D, ">="&DATE(2026,8,1), 'Lista Movimenti'!$D:$D, "<="&DATE(2026,8,31)) -> 0
B8: =SUM(Entrate_Ago[Totale]) -> 1310 | C8: =SUM(Entrate_Ago[Obiettivo]) -> 0
A12: Necessita | B12: Categoria | C12: Totale | D12: Obiettivo
B13: 🏠 Casa | C13: =SUMIFS('Lista Movimenti'!$C:$C, 'Lista Movimenti'!$B:$B, $B13, 'Lista Movimenti'!$E:$E, "Spesa", 'Lista Movimenti'!$D:$D, ">=01/08/2026", 'Lista Movimenti'!$D:$D, "<=31/08/2026") -> 0 | D13: 200
B14: 🍲 Cibo/Spesa | C14: =SUMIFS('Lista Movimenti'!$C:$C, 'Lista Movimenti'!$B:$B, $B14, 'Lista Movimenti'!$E:$E, "Spesa", 'Lista Movimenti'!$D:$D, ">=01/08/2026", 'Lista Movimenti'!$D:$D, "<=31/08/2026") -> 0 | D14: 280
B15: 🚑 Sanità | C15: =SUMIFS('Lista Movimenti'!$C:$C, 'Lista Movimenti'!$B:$B, $B15, 'Lista Movimenti'!$E:$E, "Spesa", 'Lista Movimenti'!$D:$D, ">=01/08/2026", 'Lista Movimenti'!$D:$D, "<=31/08/2026") -> 0 | D15: 50
B16: 🏋️ Palestra e affini | C16: =SUMIFS('Lista Movimenti'!$C:$C, 'Lista Movimenti'!$B:$B, $B16, 'Lista Movimenti'!$E:$E, "Spesa", 'Lista Movimenti'!$D:$D, ">=01/08/2026", 'Lista Movimenti'!$D:$D, "<=31/08/2026") -> 55 | D16: 40
B17: 📱 Telefono | C17: =SUMIFS('Lista Movimenti'!$C:$C, 'Lista Movimenti'!$B:$B, $B17, 'Lista Movimenti'!$E:$E, "Spesa", 'Lista Movimenti'!$D:$D, ">=01/08/2026", 'Lista Movimenti'!$D:$D, "<=31/08/2026") -> 0 | D17: 15
B18: 🚌 Trasporti | C18: =SUMIFS('Lista Movimenti'!$C:$C, 'Lista Movimenti'!$B:$B, $B18, 'Lista Movimenti'!$E:$E, "Spesa", 'Lista Movimenti'!$D:$D, ">=01/08/2026", 'Lista Movimenti'!$D:$D, "<=31/08/2026") -> 0 | D18: 45
B19: 👕 Vestiti | C19: =SUMIFS('Lista Movimenti'!$C:$C, 'Lista Movimenti'!$B:$B, $B19, 'Lista Movimenti'!$E:$E, "Spesa", 'Lista Movimenti'!$D:$D, ">=01/08/2026", 'Lista Movimenti'!$D:$D, "<=31/08/2026") -> 0 | D19: 35
A20: Totale Necessità | B20: -- Necessità -- | C20: =SUM(C13:C19) -> 55 | D20: =SUM(D13:D19) -> 665
A22: EXTRA | B22: -- Extra -- | C22: Totale | D22: Obiettivo
B23: 🎫 Abbonamenti | C23: =SUMIFS('Lista Movimenti'!$C:$C, 'Lista Movimenti'!$B:$B, $B23, 'Lista Movimenti'!$E:$E, "Spesa", 'Lista Movimenti'!$D:$D, ">=01/08/2026", 'Lista Movimenti'!$D:$D, "<=31/08/2026") -> 0 | D23: 22
B24: 🍔 Cibo fuori | C24: =SUMIFS('Lista Movimenti'!$C:$C, 'Lista Movimenti'!$B:$B, $B24, 'Lista Movimenti'!$E:$E, "Spesa", 'Lista Movimenti'!$D:$D, ">=01/08/2026", 'Lista Movimenti'!$D:$D, "<=31/08/2026") -> 0 | D24: 85
B25: 🎬 Intrattenimento | C25: =SUMIFS('Lista Movimenti'!$C:$C, 'Lista Movimenti'!$B:$B, $B25, 'Lista Movimenti'!$E:$E, "Spesa", 'Lista Movimenti'!$D:$D, ">=01/08/2026", 'Lista Movimenti'!$D:$D, "<=31/08/2026") -> 0 | D25: 24
B26: 🎁 Regali | C26: =SUMIFS('Lista Movimenti'!$C:$C, 'Lista Movimenti'!$B:$B, $B26, 'Lista Movimenti'!$E:$E, "Spesa", 'Lista Movimenti'!$D:$D, ">=01/08/2026", 'Lista Movimenti'!$D:$D, "<=31/08/2026") -> 0 | D26: 20
B27: ✈️ Viaggi/Vacanze | C27: =SUMIFS('Lista Movimenti'!$C:$C, 'Lista Movimenti'!$B:$B, $B27, 'Lista Movimenti'!$E:$E, "Spesa", 'Lista Movimenti'!$D:$D, ">=01/08/2026", 'Lista Movimenti'!$D:$D, "<=31/08/2026") -> 0 | D27: 60
B28: 📚 Cultura | C28: =SUMIFS('Lista Movimenti'!$C:$C, 'Lista Movimenti'!$B:$B, $B28, 'Lista Movimenti'!$E:$E, "Spesa", 'Lista Movimenti'!$D:$D, ">=01/08/2026", 'Lista Movimenti'!$D:$D, "<=31/08/2026") -> 10 | D28: 40
B29: 💅 Cura personale | C29: =SUMIFS('Lista Movimenti'!$C:$C, 'Lista Movimenti'!$B:$B, $B29, 'Lista Movimenti'!$E:$E, "Spesa", 'Lista Movimenti'!$D:$D, ">=01/08/2026", 'Lista Movimenti'!$D:$D, "<=31/08/2026") -> 0 | D29: 95
B30: 🌟 Altro extra | C30: =SUMIFS('Lista Movimenti'!$C:$C, 'Lista Movimenti'!$B:$B, $B30, 'Lista Movimenti'!$E:$E, "Spesa", 'Lista Movimenti'!$D:$D, ">=01/08/2026", 'Lista Movimenti'!$D:$D, "<=31/08/2026") -> 0 | D30: 13
A31: Totale Extra | B31: -- Extra -- | C31: =SUM(C23:C30) -> 10 | D31: =SUM(D23:D30) -> 359
A33: Totale Uscite | C33: =(C31 + C20) -> 65 | D33: =(D31 + D20) -> 1024
A34: Differenza Entrate Uscite | C34: =(B8-C33) -> 1245
A37: Categoria | B37: Totale | C37: Obiettivo
A38: 🏠 Casa | B38: =SUMIFS('Lista Movimenti'!$C:$C, 'Lista Movimenti'!$B:$B, $A38, 'Lista Movimenti'!$E:$E, "Risparmio", 'Lista Movimenti'!$D:$D, ">=01/08/2026", 'Lista Movimenti'!$D:$D, "<=31/08/2026") -> 0
A39: 🍲 Cibo/Spesa | B39: =SUMIFS('Lista Movimenti'!$C:$C, 'Lista Movimenti'!$B:$B, $A39, 'Lista Movimenti'!$E:$E, "Risparmio", 'Lista Movimenti'!$D:$D, ">=01/08/2026", 'Lista Movimenti'!$D:$D, "<=31/08/2026") -> 0
A40: 🚑 Sanità | B40: =SUMIFS('Lista Movimenti'!$C:$C, 'Lista Movimenti'!$B:$B, $A40, 'Lista Movimenti'!$E:$E, "Risparmio", 'Lista Movimenti'!$D:$D, ">=01/08/2026", 'Lista Movimenti'!$D:$D, "<=31/08/2026") -> 0
A41: 🏋️ Palestra e affini | B41: =SUMIFS('Lista Movimenti'!$C:$C, 'Lista Movimenti'!$B:$B, $A41, 'Lista Movimenti'!$E:$E, "Risparmio", 'Lista Movimenti'!$D:$D, ">=01/08/2026", 'Lista Movimenti'!$D:$D, "<=31/08/2026") -> 0
A42: 📱 Telefono | B42: =SUMIFS('Lista Movimenti'!$C:$C, 'Lista Movimenti'!$B:$B, $A42, 'Lista Movimenti'!$E:$E, "Risparmio", 'Lista Movimenti'!$D:$D, ">=01/08/2026", 'Lista Movimenti'!$D:$D, "<=31/08/2026") -> 0
A43: 🚌 Trasporti | B43: =SUMIFS('Lista Movimenti'!$C:$C, 'Lista Movimenti'!$B:$B, $A43, 'Lista Movimenti'!$E:$E, "Risparmio", 'Lista Movimenti'!$D:$D, ">=01/08/2026", 'Lista Movimenti'!$D:$D, "<=31/08/2026") -> 0
A44: 👕 Vestiti | B44: =SUMIFS('Lista Movimenti'!$C:$C, 'Lista Movimenti'!$B:$B, $A44, 'Lista Movimenti'!$E:$E, "Risparmio", 'Lista Movimenti'!$D:$D, ">=01/08/2026", 'Lista Movimenti'!$D:$D, "<=31/08/2026") -> 0
A45: 🎫 Abbonamenti | B45: =SUMIFS('Lista Movimenti'!$C:$C, 'Lista Movimenti'!$B:$B, $A45, 'Lista Movimenti'!$E:$E, "Risparmio", 'Lista Movimenti'!$D:$D, ">=01/08/2026", 'Lista Movimenti'!$D:$D, "<=31/08/2026") -> 0
A46: 🍔 Cibo fuori | B46: =SUMIFS('Lista Movimenti'!$C:$C, 'Lista Movimenti'!$B:$B, $A46, 'Lista Movimenti'!$E:$E, "Risparmio", 'Lista Movimenti'!$D:$D, ">=01/08/2026", 'Lista Movimenti'!$D:$D, "<=31/08/2026") -> 0
A47: 🎬 Intrattenimento | B47: =SUMIFS('Lista Movimenti'!$C:$C, 'Lista Movimenti'!$B:$B, $A47, 'Lista Movimenti'!$E:$E, "Risparmio", 'Lista Movimenti'!$D:$D, ">=01/08/2026", 'Lista Movimenti'!$D:$D, "<=31/08/2026") -> 0
A48: 🎁 Regali | B48: =SUMIFS('Lista Movimenti'!$C:$C, 'Lista Movimenti'!$B:$B, $A48, 'Lista Movimenti'!$E:$E, "Risparmio", 'Lista Movimenti'!$D:$D, ">=01/08/2026", 'Lista Movimenti'!$D:$D, "<=31/08/2026") -> 0
A49: ✈️ Viaggi/Vacanze | B49: =SUMIFS('Lista Movimenti'!$C:$C, 'Lista Movimenti'!$B:$B, $A49, 'Lista Movimenti'!$E:$E, "Risparmio", 'Lista Movimenti'!$D:$D, ">=01/08/2026", 'Lista Movimenti'!$D:$D, "<=31/08/2026") -> 0
... A54: 🪙 Altre entrate | B54: =SUMIFS('Lista Movimenti'!$C:$C, 'Lista Movimenti'!$B:$B, $A54, 'Lista Movimenti'!$E:$E, "Risparmio", 'Lista Movimenti'!$D:$D, ">=01/08/2026", 'Lista Movimenti'!$D:$D, "<=31/08/2026") -> 0
A55: Totale Risparmi | B55: =SUM(Risparmi_8[Totale]) -> 0 | C55: =SUM(Risparmi_8[Obiettivo]) -> 0 | S55: 0

Sheet Set
A3: Categoria | B3: Totale | C3: Obiettivo
A4: 🤑 Stipendio | B4: =SUMIFS('Lista Movimenti'!$C:$C, 'Lista Movimenti'!$B:$B, $A4, 'Lista Movimenti'!$D:$D, ">="&DATE(2026,9,1), 'Lista Movimenti'!$D:$D, "<="&DATE(2026,9,30)) -> 1500
A5: 🪙 Altre entrate | B5: =SUMIFS('Lista Movimenti'!$C:$C, 'Lista Movimenti'!$B:$B, $A5, 'Lista Movimenti'!$D:$D, ">="&DATE(2026,9,1), 'Lista Movimenti'!$D:$D, "<="&DATE(2026,9,30)) -> 0
B6: =SUMIFS('Lista Movimenti'!$C:$C, 'Lista Movimenti'!$B:$B, $A6, 'Lista Movimenti'!$D:$D, ">="&DATE(2026,9,1), 'Lista Movimenti'!$D:$D, "<="&DATE(2026,9,30)) -> 0
B7: =SUMIFS('Lista Movimenti'!$C:$C, 'Lista Movimenti'!$B:$B, $A7, 'Lista Movimenti'!$D:$D, ">="&DATE(2026,9,1), 'Lista Movimenti'!$D:$D, "<="&DATE(2026,9,30)) -> 0
B8: =SUM(Entrate_Set[Totale]) -> 1500 | C8: =SUM(Entrate_Set[Obiettivo]) -> 0
A12: Necessita | B12: Categoria | C12: Totale | D12: Obiettivo
B13: 🏠 Casa | C13: =SUMIFS('Lista Movimenti'!$C:$C, 'Lista Movimenti'!$B:$B, $B13, 'Lista Movimenti'!$E:$E, "Spesa", 'Lista Movimenti'!$D:$D, ">=01/09/2026", 'Lista Movimenti'!$D:$D, "<=30/09/2026") -> 0 | D13: 200
B14: 🍲 Cibo/Spesa | C14: =SUMIFS('Lista Movimenti'!$C:$C, 'Lista Movimenti'!$B:$B, $B14, 'Lista Movimenti'!$E:$E, "Spesa", 'Lista Movimenti'!$D:$D, ">=01/09/2026", 'Lista Movimenti'!$D:$D, "<=30/09/2026") -> 0 | D14: 280
B15: 🚑 Sanità | C15: =SUMIFS('Lista Movimenti'!$C:$C, 'Lista Movimenti'!$B:$B, $B15, 'Lista Movimenti'!$E:$E, "Spesa", 'Lista Movimenti'!$D:$D, ">=01/09/2026", 'Lista Movimenti'!$D:$D, "<=30/09/2026") -> 0 | D15: 50
B16: 🏋️ Palestra e affini | C16: =SUMIFS('Lista Movimenti'!$C:$C, 'Lista Movimenti'!$B:$B, $B16, 'Lista Movimenti'!$E:$E, "Spesa", 'Lista Movimenti'!$D:$D, ">=01/09/2026", 'Lista Movimenti'!$D:$D, "<=30/09/2026") -> 0 | D16: 40
B17: 📱 Telefono | C17: =SUMIFS('Lista Movimenti'!$C:$C, 'Lista Movimenti'!$B:$B, $B17, 'Lista Movimenti'!$E:$E, "Spesa", 'Lista Movimenti'!$D:$D, ">=01/09/2026", 'Lista Movimenti'!$D:$D, "<=30/09/2026") -> 0 | D17: 15
B18: 🚌 Trasporti | C18: =SUMIFS('Lista Movimenti'!$C:$C, 'Lista Movimenti'!$B:$B, $B18, 'Lista Movimenti'!$E:$E, "Spesa", 'Lista Movimenti'!$D:$D, ">=01/09/2026", 'Lista Movimenti'!$D:$D, "<=30/09/2026") -> 0 | D18: 45
B19: 👕 Vestiti | C19: =SUMIFS('Lista Movimenti'!$C:$C, 'Lista Movimenti'!$B:$B, $B19, 'Lista Movimenti'!$E:$E, "Spesa", 'Lista Movimenti'!$D:$D, ">=01/09/2026", 'Lista Movimenti'!$D:$D, "<=30/09/2026") -> 0 | D19: 35
A20: Totale Necessità | B20: -- Necessità -- | C20: =SUM(C13:C19) -> 0 | D20: =SUM(D13:D19) -> 665
A22: EXTRA | B22: -- Extra -- | C22: Totale | D22: Obiettivo
B23: 🎫 Abbonamenti | C23: =SUMIFS('Lista Movimenti'!$C:$C, 'Lista Movimenti'!$B:$B, $B23, 'Lista Movimenti'!$E:$E, "Spesa", 'Lista Movimenti'!$D:$D, ">=01/09/2026", 'Lista Movimenti'!$D:$D, "<=30/09/2026") -> 0 | D23: 22
B24: 🍔 Cibo fuori | C24: =SUMIFS('Lista Movimenti'!$C:$C, 'Lista Movimenti'!$B:$B, $B24, 'Lista Movimenti'!$E:$E, "Spesa", 'Lista Movimenti'!$D:$D, ">=01/09/2026", 'Lista Movimenti'!$D:$D, "<=30/09/2026") -> 0 | D24: 85
B25: 🎬 Intrattenimento | C25: =SUMIFS('Lista Movimenti'!$C:$C, 'Lista Movimenti'!$B:$B, $B25, 'Lista Movimenti'!$E:$E, "Spesa", 'Lista Movimenti'!$D:$D, ">=01/09/2026", 'Lista Movimenti'!$D:$D, "<=30/09/2026") -> 0 | D25: 24
B26: 🎁 Regali | C26: =SUMIFS('Lista Movimenti'!$C:$C, 'Lista Movimenti'!$B:$B, $B26, 'Lista Movimenti'!$E:$E, "Spesa", 'Lista Movimenti'!$D:$D, ">=01/09/2026", 'Lista Movimenti'!$D:$D, "<=30/09/2026") -> 0 | D26: 20
B27: ✈️ Viaggi/Vacanze | C27: =SUMIFS('Lista Movimenti'!$C:$C, 'Lista Movimenti'!$B:$B, $B27, 'Lista Movimenti'!$E:$E, "Spesa", 'Lista Movimenti'!$D:$D, ">=01/09/2026", 'Lista Movimenti'!$D:$D, "<=30/09/2026") -> 150 | D27: 60
B28: 📚 Cultura | C28: =SUMIFS('Lista Movimenti'!$C:$C, 'Lista Movimenti'!$B:$B, $B28, 'Lista Movimenti'!$E:$E, "Spesa", 'Lista Movimenti'!$D:$D, ">=01/09/2026", 'Lista Movimenti'!$D:$D, "<=30/09/2026") -> 0 | D28: 40
B29: 💅 Cura personale | C29: =SUMIFS('Lista Movimenti'!$C:$C, 'Lista Movimenti'!$B:$B, $B29, 'Lista Movimenti'!$E:$E, "Spesa", 'Lista Movimenti'!$D:$D, ">=01/09/2026", 'Lista Movimenti'!$D:$D, "<=30/09/2026") -> 0 | D29: 95
B30: 🌟 Altro extra | C30: =SUMIFS('Lista Movimenti'!$C:$C, 'Lista Movimenti'!$B:$B, $B30, 'Lista Movimenti'!$E:$E, "Spesa", 'Lista Movimenti'!$D:$D, ">=01/09/2026", 'Lista Movimenti'!$D:$D, "<=30/09/2026") -> 0 | D30: 13
A31: Totale Extra | B31: -- Extra -- | C31: =SUM(C23:C30) -> 150 | D31: =SUM(D23:D30) -> 359
A33: Totale Uscite | C33: =(C31 + C20) -> 150 | D33: =(D31 + D20) -> 1024
A34: Differenza Entrate Uscite | C34: =(B8-C33) -> 1350
A37: Categoria | B37: Totale | C37: Obiettivo
A38: 🏠 Casa | B38: =SUMIFS('Lista Movimenti'!$C:$C, 'Lista Movimenti'!$B:$B, $A38, 'Lista Movimenti'!$E:$E, "Risparmio", 'Lista Movimenti'!$D:$D, ">=01/09/2026", 'Lista Movimenti'!$D:$D, "<=30/09/2026") -> 230
A39: 🍲 Cibo/Spesa | B39: =SUMIFS('Lista Movimenti'!$C:$C, 'Lista Movimenti'!$B:$B, $A39, 'Lista Movimenti'!$E:$E, "Risparmio", 'Lista Movimenti'!$D:$D, ">=01/09/2026", 'Lista Movimenti'!$D:$D, "<=30/09/2026") -> 0
A40: 🚑 Sanità | B40: =SUMIFS('Lista Movimenti'!$C:$C, 'Lista Movimenti'!$B:$B, $A40, 'Lista Movimenti'!$E:$E, "Risparmio", 'Lista Movimenti'!$D:$D, ">=01/09/2026", 'Lista Movimenti'!$D:$D, "<=30/09/2026") -> 0
A41: 🏋️ Palestra e affini | B41: =SUMIFS('Lista Movimenti'!$C:$C, 'Lista Movimenti'!$B:$B, $A41, 'Lista Movimenti'!$E:$E, "Risparmio", 'Lista Movimenti'!$D:$D, ">=01/09/2026", 'Lista Movimenti'!$D:$D, "<=30/09/2026") -> 0
A42: 📱 Telefono | B42: =SUMIFS('Lista Movimenti'!$C:$C, 'Lista Movimenti'!$B:$B, $A42, 'Lista Movimenti'!$E:$E, "Risparmio", 'Lista Movimenti'!$D:$D, ">=01/09/2026", 'Lista Movimenti'!$D:$D, "<=30/09/2026") -> 0
A43: 🚌 Trasporti | B43: =SUMIFS('Lista Movimenti'!$C:$C, 'Lista Movimenti'!$B:$B, $A43, 'Lista Movimenti'!$E:$E, "Risparmio", 'Lista Movimenti'!$D:$D, ">=01/09/2026", 'Lista Movimenti'!$D:$D, "<=30/09/2026") -> 0
A44: 👕 Vestiti | B44: =SUMIFS('Lista Movimenti'!$C:$C, 'Lista Movimenti'!$B:$B, $A44, 'Lista Movimenti'!$E:$E, "Risparmio", 'Lista Movimenti'!$D:$D, ">=01/09/2026", 'Lista Movimenti'!$D:$D, "<=30/09/2026") -> 0
A45: 🎫 Abbonamenti | B45: =SUMIFS('Lista Movimenti'!$C:$C, 'Lista Movimenti'!$B:$B, $A45, 'Lista Movimenti'!$E:$E, "Risparmio", 'Lista Movimenti'!$D:$D, ">=01/09/2026", 'Lista Movimenti'!$D:$D, "<=30/09/2026") -> 0
A46: 🍔 Cibo fuori | B46: =SUMIFS('Lista Movimenti'!$C:$C, 'Lista Movimenti'!$B:$B, $A46, 'Lista Movimenti'!$E:$E, "Risparmio", 'Lista Movimenti'!$D:$D, ">=01/09/2026", 'Lista Movimenti'!$D:$D, "<=30/09/2026") -> 0
A47: 🎬 Intrattenimento | B47: =SUMIFS('Lista Movimenti'!$C:$C, 'Lista Movimenti'!$B:$B, $A47, 'Lista Movimenti'!$E:$E, "Risparmio", 'Lista Movimenti'!$D:$D, ">=01/09/2026", 'Lista Movimenti'!$D:$D, "<=30/09/2026") -> 0
A48: 🎁 Regali | B48: =SUMIFS('Lista Movimenti'!$C:$C, 'Lista Movimenti'!$B:$B, $A48, 'Lista Movimenti'!$E:$E, "Risparmio", 'Lista Movimenti'!$D:$D, ">=01/09/2026", 'Lista Movimenti'!$D:$D, "<=30/09/2026") -> 0
A49: ✈️ Viaggi/Vacanze | B49: =SUMIFS('Lista Movimenti'!$C:$C, 'Lista Movimenti'!$B:$B, $A49, 'Lista Movimenti'!$E:$E, "Risparmio", 'Lista Movimenti'!$D:$D, ">=01/09/2026", 'Lista Movimenti'!$D:$D, "<=30/09/2026") -> 0
... A54: 🪙 Altre entrate | B54: =SUMIFS('Lista Movimenti'!$C:$C, 'Lista Movimenti'!$B:$B, $A54, 'Lista Movimenti'!$E:$E, "Risparmio", 'Lista Movimenti'!$D:$D, ">=01/09/2026", 'Lista Movimenti'!$D:$D, "<=30/09/2026") -> 0
A55: Totale Risparmi | B55: =SUM(Risparmi_9[Totale]) -> 230 | C55: =SUM(Risparmi_9[Obiettivo]) -> 0 | S55: 0

Sheet Ott
A3: Categoria | B3: Totale | C3: Obiettivo
A4: 🤑 Stipendio | B4: =SUMIFS('Lista Movimenti'!$C:$C, 'Lista Movimenti'!$B:$B, $A4, 'Lista Movimenti'!$D:$D, ">="&DATE(2026,10,1), 'Lista Movimenti'!$D:$D, "<="&DATE(2026,10,31)) -> 1600
A5: 🪙 Altre entrate | B5: =SUMIFS('Lista Movimenti'!$C:$C, 'Lista Movimenti'!$B:$B, $A5, 'Lista Movimenti'!$D:$D, ">="&DATE(2026,10,1), 'Lista Movimenti'!$D:$D, "<="&DATE(2026,10,31)) -> 20
B6: =SUMIFS('Lista Movimenti'!$C:$C, 'Lista Movimenti'!$B:$B, $A6, 'Lista Movimenti'!$D:$D, ">="&DATE(2026,10,1), 'Lista Movimenti'!$D:$D, "<="&DATE(2026,10,31)) -> 0
B7: =SUMIFS('Lista Movimenti'!$C:$C, 'Lista Movimenti'!$B:$B, $A7, 'Lista Movimenti'!$D:$D, ">="&DATE(2026,10,1), 'Lista Movimenti'!$D:$D, "<="&DATE(2026,10,31)) -> 0
B8: =SUM(Entrate_Ott[Totale]) -> 1620 | C8: =SUM(Entrate_Ott[Obiettivo]) -> 0
A12: Necessita | B12: Categoria | C12: Totale | D12: Obiettivo
B13: 🏠 Casa | C13: =SUMIFS('Lista Movimenti'!$C:$C, 'Lista Movimenti'!$B:$B, $B13, 'Lista Movimenti'!$E:$E, "Spesa", 'Lista Movimenti'!$D:$D, ">=01/10/2026", 'Lista Movimenti'!$D:$D, "<=31/10/2026") -> 0 | D13: 200
B14: 🍲 Cibo/Spesa | C14: =SUMIFS('Lista Movimenti'!$C:$C, 'Lista Movimenti'!$B:$B, $B14, 'Lista Movimenti'!$E:$E, "Spesa", 'Lista Movimenti'!$D:$D, ">=01/10/2026", 'Lista Movimenti'!$D:$D, "<=31/10/2026") -> 100 | D14: 280
B15: 🚑 Sanità | C15: =SUMIFS('Lista Movimenti'!$C:$C, 'Lista Movimenti'!$B:$B, $B15, 'Lista Movimenti'!$E:$E, "Spesa", 'Lista Movimenti'!$D:$D, ">=01/10/2026", 'Lista Movimenti'!$D:$D, "<=31/10/2026") -> 0 | D15: 50
B16: 🏋️ Palestra e affini | C16: =SUMIFS('Lista Movimenti'!$C:$C, 'Lista Movimenti'!$B:$B, $B16, 'Lista Movimenti'!$E:$E, "Spesa", 'Lista Movimenti'!$D:$D, ">=01/10/2026", 'Lista Movimenti'!$D:$D, "<=31/10/2026") -> 0 | D16: 40
B17: 📱 Telefono | C17: =SUMIFS('Lista Movimenti'!$C:$C, 'Lista Movimenti'!$B:$B, $B17, 'Lista Movimenti'!$E:$E, "Spesa", 'Lista Movimenti'!$D:$D, ">=01/10/2026", 'Lista Movimenti'!$D:$D, "<=31/10/2026") -> 0 | D17: 15
B18: 🚌 Trasporti | C18: =SUMIFS('Lista Movimenti'!$C:$C, 'Lista Movimenti'!$B:$B, $B18, 'Lista Movimenti'!$E:$E, "Spesa", 'Lista Movimenti'!$D:$D, ">=01/10/2026", 'Lista Movimenti'!$D:$D, "<=31/10/2026") -> 0 | D18: 45
B19: 👕 Vestiti | C19: =SUMIFS('Lista Movimenti'!$C:$C, 'Lista Movimenti'!$B:$B, $B19, 'Lista Movimenti'!$E:$E, "Spesa", 'Lista Movimenti'!$D:$D, ">=01/10/2026", 'Lista Movimenti'!$D:$D, "<=31/10/2026") -> 0 | D19: 35
A20: Totale Necessità | B20: -- Necessità -- | C20: =SUM(C13:C19) -> 100 | D20: =SUM(D13:D19) -> 665
A22: EXTRA | B22: -- Extra -- | C22: Totale | D22: Obiettivo
B23: 🎫 Abbonamenti | C23: =SUMIFS('Lista Movimenti'!$C:$C, 'Lista Movimenti'!$B:$B, $B23, 'Lista Movimenti'!$E:$E, "Spesa", 'Lista Movimenti'!$D:$D, ">=01/10/2026", 'Lista Movimenti'!$D:$D, "<=31/10/2026") -> 0 | D23: 22
B24: 🍔 Cibo fuori | C24: =SUMIFS('Lista Movimenti'!$C:$C, 'Lista Movimenti'!$B:$B, $B24, 'Lista Movimenti'!$E:$E, "Spesa", 'Lista Movimenti'!$D:$D, ">=01/10/2026", 'Lista Movimenti'!$D:$D, "<=31/10/2026") -> 0 | D24: 85
B25: 🎬 Intrattenimento | C25: =SUMIFS('Lista Movimenti'!$C:$C, 'Lista Movimenti'!$B:$B, $B25, 'Lista Movimenti'!$E:$E, "Spesa", 'Lista Movimenti'!$D:$D, ">=01/10/2026", 'Lista Movimenti'!$D:$D, "<=31/10/2026") -> 0 | D25: 24
B26: 🎁 Regali | C26: =SUMIFS('Lista Movimenti'!$C:$C, 'Lista Movimenti'!$B:$B, $B26, 'Lista Movimenti'!$E:$E, "Spesa", 'Lista Movimenti'!$D:$D, ">=01/10/2026", 'Lista Movimenti'!$D:$D, "<=31/10/2026") -> 0 | D26: 20
B27: ✈️ Viaggi/Vacanze | C27: =SUMIFS('Lista Movimenti'!$C:$C, 'Lista Movimenti'!$B:$B, $B27, 'Lista Movimenti'!$E:$E, "Spesa", 'Lista Movimenti'!$D:$D, ">=01/10/2026", 'Lista Movimenti'!$D:$D, "<=31/10/2026") -> 0 | D27: 60
B28: 📚 Cultura | C28: =SUMIFS('Lista Movimenti'!$C:$C, 'Lista Movimenti'!$B:$B, $B28, 'Lista Movimenti'!$E:$E, "Spesa", 'Lista Movimenti'!$D:$D, ">=01/10/2026", 'Lista Movimenti'!$D:$D, "<=31/10/2026") -> 10 | D28: 40
B29: 💅 Cura personale | C29: =SUMIFS('Lista Movimenti'!$C:$C, 'Lista Movimenti'!$B:$B, $B29, 'Lista Movimenti'!$E:$E, "Spesa", 'Lista Movimenti'!$D:$D, ">=01/10/2026", 'Lista Movimenti'!$D:$D, "<=31/10/2026") -> 0 | D29: 95
B30: 🌟 Altro extra | C30: =SUMIFS('Lista Movimenti'!$C:$C, 'Lista Movimenti'!$B:$B, $B30, 'Lista Movimenti'!$E:$E, "Spesa", 'Lista Movimenti'!$D:$D, ">=01/10/2026", 'Lista Movimenti'!$D:$D, "<=31/10/2026") -> 0 | D30: 13
A31: Totale Extra | B31: -- Extra -- | C31: =SUM(C23:C30) -> 10 | D31: =SUM(D23:D30) -> 359
A33: Totale Uscite | C33: =(C31 + C20) -> 110 | D33: =(D31 + D20) -> 1024
A34: Differenza Entrate Uscite | C34: =(B8-C33) -> 1510
A37: Categoria | B37: Totale | C37: Obiettivo
A38: 🏠 Casa | B38: =SUMIFS('Lista Movimenti'!$C:$C, 'Lista Movimenti'!$B:$B, $A38, 'Lista Movimenti'!$E:$E, "Risparmio", 'Lista Movimenti'!$D:$D, ">=01/10/2026", 'Lista Movimenti'!$D:$D, "<=31/10/2026") -> 115
A39: 🍲 Cibo/Spesa | B39: =SUMIFS('Lista Movimenti'!$C:$C, 'Lista Movimenti'!$B:$B, $A39, 'Lista Movimenti'!$E:$E, "Risparmio", 'Lista Movimenti'!$D:$D, ">=01/10/2026", 'Lista Movimenti'!$D:$D, "<=31/10/2026") -> 0
A40: 🚑 Sanità | B40: =SUMIFS('Lista Movimenti'!$C:$C, 'Lista Movimenti'!$B:$B, $A40, 'Lista Movimenti'!$E:$E, "Risparmio", 'Lista Movimenti'!$D:$D, ">=01/10/2026", 'Lista Movimenti'!$D:$D, "<=31/10/2026") -> 0
A41: 🏋️ Palestra e affini | B41: =SUMIFS('Lista Movimenti'!$C:$C, 'Lista Movimenti'!$B:$B, $A41, 'Lista Movimenti'!$E:$E, "Risparmio", 'Lista Movimenti'!$D:$D, ">=01/10/2026", 'Lista Movimenti'!$D:$D, "<=31/10/2026") -> 1500
A42: 📱 Telefono | B42: =SUMIFS('Lista Movimenti'!$C:$C, 'Lista Movimenti'!$B:$B, $A42, 'Lista Movimenti'!$E:$E, "Risparmio", 'Lista Movimenti'!$D:$D, ">=01/10/2026", 'Lista Movimenti'!$D:$D, "<=31/10/2026") -> 0
A43: 🚌 Trasporti | B43: =SUMIFS('Lista Movimenti'!$C:$C, 'Lista Movimenti'!$B:$B, $A43, 'Lista Movimenti'!$E:$E, "Risparmio", 'Lista Movimenti'!$D:$D, ">=01/10/2026", 'Lista Movimenti'!$D:$D, "<=31/10/2026") -> 0
A44: 👕 Vestiti | B44: =SUMIFS('Lista Movimenti'!$C:$C, 'Lista Movimenti'!$B:$B, $A44, 'Lista Movimenti'!$E:$E, "Risparmio", 'Lista Movimenti'!$D:$D, ">=01/10/2026", 'Lista Movimenti'!$D:$D, "<=31/10/2026") -> 0
A45: 🎫 Abbonamenti | B45: =SUMIFS('Lista Movimenti'!$C:$C, 'Lista Movimenti'!$B:$B, $A45, 'Lista Movimenti'!$E:$E, "Risparmio", 'Lista Movimenti'!$D:$D, ">=01/10/2026", 'Lista Movimenti'!$D:$D, "<=31/10/2026") -> 0
A46: 🍔 Cibo fuori | B46: =SUMIFS('Lista Movimenti'!$C:$C, 'Lista Movimenti'!$B:$B, $A46, 'Lista Movimenti'!$E:$E, "Risparmio", 'Lista Movimenti'!$D:$D, ">=01/10/2026", 'Lista Movimenti'!$D:$D, "<=31/10/2026") -> 0
A47: 🎬 Intrattenimento | B47: =SUMIFS('Lista Movimenti'!$C:$C, 'Lista Movimenti'!$B:$B, $A47, 'Lista Movimenti'!$E:$E, "Risparmio", 'Lista Movimenti'!$D:$D, ">=01/10/2026", 'Lista Movimenti'!$D:$D, "<=31/10/2026") -> 0
A48: 🎁 Regali | B48: =SUMIFS('Lista Movimenti'!$C:$C, 'Lista Movimenti'!$B:$B, $A48, 'Lista Movimenti'!$E:$E, "Risparmio", 'Lista Movimenti'!$D:$D, ">=01/10/2026", 'Lista Movimenti'!$D:$D, "<=31/10/2026") -> 175
A49: ✈️ Viaggi/Vacanze | B49: =SUMIFS('Lista Movimenti'!$C:$C, 'Lista Movimenti'!$B:$B, $A49, 'Lista Movimenti'!$E:$E, "Risparmio", 'Lista Movimenti'!$D:$D, ">=01/10/2026", 'Lista Movimenti'!$D:$D, "<=31/10/2026") -> 0
... A54: 🪙 Altre entrate | B54: =SUMIFS('Lista Movimenti'!$C:$C, 'Lista Movimenti'!$B:$B, $A54, 'Lista Movimenti'!$E:$E, "Risparmio", 'Lista Movimenti'!$D:$D, ">=01/10/2026", 'Lista Movimenti'!$D:$D, "<=31/10/2026") -> 0
A55: Totale Risparmi | B55: =SUM(Risparmi_Ott[Totale]) -> 1790 | C55: =SUM(Risparmi_Ott[Obiettivo]) -> 0 | S55: 0

Sheet Nov
A3: Categoria | B3: Totale | C3: Obiettivo
A4: 🤑 Stipendio | B4: =SUMIFS('Lista Movimenti'!$C:$C, 'Lista Movimenti'!$B:$B, $A4, 'Lista Movimenti'!$D:$D, ">="&DATE(2026,11,1), 'Lista Movimenti'!$D:$D, "<="&DATE(2026,11,30)) -> 1150
A5: 🪙 Altre entrate | B5: =SUMIFS('Lista Movimenti'!$C:$C, 'Lista Movimenti'!$B:$B, $A5, 'Lista Movimenti'!$D:$D, ">="&DATE(2026,11,1), 'Lista Movimenti'!$D:$D, "<="&DATE(2026,11,30)) -> 0
B6: =SUMIFS('Lista Movimenti'!$C:$C, 'Lista Movimenti'!$B:$B, $A6, 'Lista Movimenti'!$D:$D, ">="&DATE(2026,11,1), 'Lista Movimenti'!$D:$D, "<="&DATE(2026,11,30)) -> 0
B7: =SUMIFS('Lista Movimenti'!$C:$C, 'Lista Movimenti'!$B:$B, $A7, 'Lista Movimenti'!$D:$D, ">="&DATE(2026,11,1), 'Lista Movimenti'!$D:$D, "<="&DATE(2026,11,30)) -> 0
B8: =SUM(Entrate_Nov[Totale]) -> 1150 | C8: =SUM(Entrate_Nov[Obiettivo]) -> 0
A12: Necessita | B12: Categoria | C12: Totale | D12: Obiettivo
B13: 🏠 Casa | C13: =SUMIFS('Lista Movimenti'!$C:$C, 'Lista Movimenti'!$B:$B, $B13, 'Lista Movimenti'!$E:$E, "Spesa", 'Lista Movimenti'!$D:$D, ">=01/11/2026", 'Lista Movimenti'!$D:$D, "<=30/11/2026") -> 200 | D13: 200
B14: 🍲 Cibo/Spesa | C14: =SUMIFS('Lista Movimenti'!$C:$C, 'Lista Movimenti'!$B:$B, $B14, 'Lista Movimenti'!$E:$E, "Spesa", 'Lista Movimenti'!$D:$D, ">=01/11/2026", 'Lista Movimenti'!$D:$D, "<=30/11/2026") -> 0 | D14: 280
B15: 🚑 Sanità | C15: =SUMIFS('Lista Movimenti'!$C:$C, 'Lista Movimenti'!$B:$B, $B15, 'Lista Movimenti'!$E:$E, "Spesa", 'Lista Movimenti'!$D:$D, ">=01/11/2026", 'Lista Movimenti'!$D:$D, "<=30/11/2026") -> 0 | D15: 50
B16: 🏋️ Palestra e affini | C16: =SUMIFS('Lista Movimenti'!$C:$C, 'Lista Movimenti'!$B:$B, $B16, 'Lista Movimenti'!$E:$E, "Spesa", 'Lista Movimenti'!$D:$D, ">=01/11/2026", 'Lista Movimenti'!$D:$D, "<=30/11/2026") -> 0 | D16: 40
B17: 📱 Telefono | C17: =SUMIFS('Lista Movimenti'!$C:$C, 'Lista Movimenti'!$B:$B, $B17, 'Lista Movimenti'!$E:$E, "Spesa", 'Lista Movimenti'!$D:$D, ">=01/11/2026", 'Lista Movimenti'!$D:$D, "<=30/11/2026") -> 0 | D17: 15
B18: 🚌 Trasporti | C18: =SUMIFS('Lista Movimenti'!$C:$C, 'Lista Movimenti'!$B:$B, $B18, 'Lista Movimenti'!$E:$E, "Spesa", 'Lista Movimenti'!$D:$D, ">=01/11/2026", 'Lista Movimenti'!$D:$D, "<=30/11/2026") -> 0 | D18: 45
B19: 👕 Vestiti | C19: =SUMIFS('Lista Movimenti'!$C:$C, 'Lista Movimenti'!$B:$B, $B19, 'Lista Movimenti'!$E:$E, "Spesa", 'Lista Movimenti'!$D:$D, ">=01/11/2026", 'Lista Movimenti'!$D:$D, "<=30/11/2026") -> 0 | D19: 35
A20: Totale Necessità | B20: -- Necessità -- | C20: =SUM(C13:C19) -> 200 | D20: =SUM(D13:D19) -> 665
A22: EXTRA | B22: -- Extra -- | C22: Totale | D22: Obiettivo
B23: 🎫 Abbonamenti | C23: =SUMIFS('Lista Movimenti'!$C:$C, 'Lista Movimenti'!$B:$B, $B23, 'Lista Movimenti'!$E:$E, "Spesa", 'Lista Movimenti'!$D:$D, ">=01/11/2026", 'Lista Movimenti'!$D:$D, "<=30/11/2026") -> 12 | D23: 22
B24: 🍔 Cibo fuori | C24: =SUMIFS('Lista Movimenti'!$C:$C, 'Lista Movimenti'!$B:$B, $B24, 'Lista Movimenti'!$E:$E, "Spesa", 'Lista Movimenti'!$D:$D, ">=01/11/2026", 'Lista Movimenti'!$D:$D, "<=30/11/2026") -> 0 | D24: 85
B25: 🎬 Intrattenimento | C25: =SUMIFS('Lista Movimenti'!$C:$C, 'Lista Movimenti'!$B:$B, $B25, 'Lista Movimenti'!$E:$E, "Spesa", 'Lista Movimenti'!$D:$D, ">=01/11/2026", 'Lista Movimenti'!$D:$D, "<=30/11/2026") -> 0 | D25: 24
B26: 🎁 Regali | C26: =SUMIFS('Lista Movimenti'!$C:$C, 'Lista Movimenti'!$B:$B, $B26, 'Lista Movimenti'!$E:$E, "Spesa", 'Lista Movimenti'!$D:$D, ">=01/11/2026", 'Lista Movimenti'!$D:$D, "<=30/11/2026") -> 0 | D26: 20
B27: ✈️ Viaggi/Vacanze | C27: =SUMIFS('Lista Movimenti'!$C:$C, 'Lista Movimenti'!$B:$B, $B27, 'Lista Movimenti'!$E:$E, "Spesa", 'Lista Movimenti'!$D:$D, ">=01/11/2026", 'Lista Movimenti'!$D:$D, "<=30/11/2026") -> 0 | D27: 60
B28: 📚 Cultura | C28: =SUMIFS('Lista Movimenti'!$C:$C, 'Lista Movimenti'!$B:$B, $B28, 'Lista Movimenti'!$E:$E, "Spesa", 'Lista Movimenti'!$D:$D, ">=01/11/2026", 'Lista Movimenti'!$D:$D, "<=30/11/2026") -> 0 | D28: 40
B29: 💅 Cura personale | C29: =SUMIFS('Lista Movimenti'!$C:$C, 'Lista Movimenti'!$B:$B, $B29, 'Lista Movimenti'!$E:$E, "Spesa", 'Lista Movimenti'!$D:$D, ">=01/11/2026", 'Lista Movimenti'!$D:$D, "<=30/11/2026") -> 0 | D29: 95
B30: 🌟 Altro extra | C30: =SUMIFS('Lista Movimenti'!$C:$C, 'Lista Movimenti'!$B:$B, $B30, 'Lista Movimenti'!$E:$E, "Spesa", 'Lista Movimenti'!$D:$D, ">=01/11/2026", 'Lista Movimenti'!$D:$D, "<=30/11/2026") -> 0 | D30: 13
A31: Totale Extra | B31: -- Extra -- | C31: =SUM(C23:C30) -> 12 | D31: =SUM(D23:D30) -> 359
A33: Totale Uscite | C33: =(C31 + C20) -> 212 | D33: =(D31 + D20) -> 1024
A34: Differenza Entrate Uscite | C34: =(B8-C33) -> 938
A37: Categoria | B37: Totale | C37: Obiettivo
A38: 🏠 Casa | B38: =SUMIFS('Lista Movimenti'!$C:$C, 'Lista Movimenti'!$B:$B, $A38, 'Lista Movimenti'!$E:$E, "Risparmio", 'Lista Movimenti'!$D:$D, ">=01/11/2026", 'Lista Movimenti'!$D:$D, "<=30/11/2026") -> 0
A39: 🍲 Cibo/Spesa | B39: =SUMIFS('Lista Movimenti'!$C:$C, 'Lista Movimenti'!$B:$B, $A39, 'Lista Movimenti'!$E:$E, "Risparmio", 'Lista Movimenti'!$D:$D, ">=01/11/2026", 'Lista Movimenti'!$D:$D, "<=30/11/2026") -> 0
A40: 🚑 Sanità | B40: =SUMIFS('Lista Movimenti'!$C:$C, 'Lista Movimenti'!$B:$B, $A40, 'Lista Movimenti'!$E:$E, "Risparmio", 'Lista Movimenti'!$D:$D, ">=01/11/2026", 'Lista Movimenti'!$D:$D, "<=30/11/2026") -> 0
A41: 🏋️ Palestra e affini | B41: =SUMIFS('Lista Movimenti'!$C:$C, 'Lista Movimenti'!$B:$B, $A41, 'Lista Movimenti'!$E:$E, "Risparmio", 'Lista Movimenti'!$D:$D, ">=01/11/2026", 'Lista Movimenti'!$D:$D, "<=30/11/2026") -> 0
A42: 📱 Telefono | B42: =SUMIFS('Lista Movimenti'!$C:$C, 'Lista Movimenti'!$B:$B, $A42, 'Lista Movimenti'!$E:$E, "Risparmio", 'Lista Movimenti'!$D:$D, ">=01/11/2026", 'Lista Movimenti'!$D:$D, "<=30/11/2026") -> 0
A43: 🚌 Trasporti | B43: =SUMIFS('Lista Movimenti'!$C:$C, 'Lista Movimenti'!$B:$B, $A43, 'Lista Movimenti'!$E:$E, "Risparmio", 'Lista Movimenti'!$D:$D, ">=01/11/2026", 'Lista Movimenti'!$D:$D, "<=30/11/2026") -> 0
A44: 👕 Vestiti | B44: =SUMIFS('Lista Movimenti'!$C:$C, 'Lista Movimenti'!$B:$B, $A44, 'Lista Movimenti'!$E:$E, "Risparmio", 'Lista Movimenti'!$D:$D, ">=01/11/2026", 'Lista Movimenti'!$D:$D, "<=30/11/2026") -> 0
A45: 🎫 Abbonamenti | B45: =SUMIFS('Lista Movimenti'!$C:$C, 'Lista Movimenti'!$B:$B, $A45, 'Lista Movimenti'!$E:$E, "Risparmio", 'Lista Movimenti'!$D:$D, ">=01/11/2026", 'Lista Movimenti'!$D:$D, "<=30/11/2026") -> 0
A46: 🍔 Cibo fuori | B46: =SUMIFS('Lista Movimenti'!$C:$C, 'Lista Movimenti'!$B:$B, $A46, 'Lista Movimenti'!$E:$E, "Risparmio", 'Lista Movimenti'!$D:$D, ">=01/11/2026", 'Lista Movimenti'!$D:$D, "<=30/11/2026") -> 0
A47: 🎬 Intrattenimento | B47: =SUMIFS('Lista Movimenti'!$C:$C, 'Lista Movimenti'!$B:$B, $A47, 'Lista Movimenti'!$E:$E, "Risparmio", 'Lista Movimenti'!$D:$D, ">=01/11/2026", 'Lista Movimenti'!$D:$D, "<=30/11/2026") -> 0
A48: 🎁 Regali | B48: =SUMIFS('Lista Movimenti'!$C:$C, 'Lista Movimenti'!$B:$B, $A48, 'Lista Movimenti'!$E:$E, "Risparmio", 'Lista Movimenti'!$D:$D, ">=01/11/2026", 'Lista Movimenti'!$D:$D, "<=30/11/2026") -> 0
A49: ✈️ Viaggi/Vacanze | B49: =SUMIFS('Lista Movimenti'!$C:$C, 'Lista Movimenti'!$B:$B, $A49, 'Lista Movimenti'!$E:$E, "Risparmio", 'Lista Movimenti'!$D:$D, ">=01/11/2026", 'Lista Movimenti'!$D:$D, "<=30/11/2026") -> 0
... A54: 🪙 Altre entrate | B54: =SUMIFS('Lista Movimenti'!$C:$C, 'Lista Movimenti'!$B:$B, $A54, 'Lista Movimenti'!$E:$E, "Risparmio", 'Lista Movimenti'!$D:$D, ">=01/11/2026", 'Lista Movimenti'!$D:$D, "<=30/11/2026") -> 0
A55: Totale Risparmi | B55: =SUM(Risparmi_Nov[Totale]) -> 0 | C55: =SUM(Risparmi_Nov[Obiettivo]) -> 0 | S55: 0

Sheet Dic
A3: Categoria | B3: Totale | C3: Obiettivo
A4: 🤑 Stipendio | B4: =SUMIFS('Lista Movimenti'!$C:$C, 'Lista Movimenti'!$B:$B, $A4, 'Lista Movimenti'!$D:$D, ">="&DATE(2026,12,1), 'Lista Movimenti'!$D:$D, "<="&DATE(2026,12,31)) -> 1450
A5: 🪙 Altre entrate | B5: =SUMIFS('Lista Movimenti'!$C:$C, 'Lista Movimenti'!$B:$B, $A5, 'Lista Movimenti'!$D:$D, ">="&DATE(2026,12,1), 'Lista Movimenti'!$D:$D, "<="&DATE(2026,12,31)) -> 0
B6: =SUMIFS('Lista Movimenti'!$C:$C, 'Lista Movimenti'!$B:$B, $A6, 'Lista Movimenti'!$D:$D, ">="&DATE(2026,12,1), 'Lista Movimenti'!$D:$D, "<="&DATE(2026,12,31)) -> 0
B7: =SUMIFS('Lista Movimenti'!$C:$C, 'Lista Movimenti'!$B:$B, $A7, 'Lista Movimenti'!$D:$D, ">="&DATE(2026,12,1), 'Lista Movimenti'!$D:$D, "<="&DATE(2026,12,31)) -> 0
B8: =SUM(Entrate_Dic[Totale]) -> 1450 | C8: =SUM(Entrate_Dic[Obiettivo]) -> 0
A12: Necessita | B12: Categoria | C12: Totale | D12: Obiettivo
B13: 🏠 Casa | C13: =SUMIFS('Lista Movimenti'!$C:$C, 'Lista Movimenti'!$B:$B, $B13, 'Lista Movimenti'!$E:$E, "Spesa", 'Lista Movimenti'!$D:$D, ">=01/12/2026", 'Lista Movimenti'!$D:$D, "<=31/12/2026") -> 0 | D13: 200
B14: 🍲 Cibo/Spesa | C14: =SUMIFS('Lista Movimenti'!$C:$C, 'Lista Movimenti'!$B:$B, $B14, 'Lista Movimenti'!$E:$E, "Spesa", 'Lista Movimenti'!$D:$D, ">=01/12/2026", 'Lista Movimenti'!$D:$D, "<=31/12/2026") -> 0 | D14: 280
B15: 🚑 Sanità | C15: =SUMIFS('Lista Movimenti'!$C:$C, 'Lista Movimenti'!$B:$B, $B15, 'Lista Movimenti'!$E:$E, "Spesa", 'Lista Movimenti'!$D:$D, ">=01/12/2026", 'Lista Movimenti'!$D:$D, "<=31/12/2026") -> 0 | D15: 50
B16: 🏋️ Palestra e affini | C16: =SUMIFS('Lista Movimenti'!$C:$C, 'Lista Movimenti'!$B:$B, $B16, 'Lista Movimenti'!$E:$E, "Spesa", 'Lista Movimenti'!$D:$D, ">=01/12/2026", 'Lista Movimenti'!$D:$D, "<=31/12/2026") -> 45 | D16: 40
B17: 📱 Telefono | C17: =SUMIFS('Lista Movimenti'!$C:$C, 'Lista Movimenti'!$B:$B, $B17, 'Lista Movimenti'!$E:$E, "Spesa", 'Lista Movimenti'!$D:$D, ">=01/12/2026", 'Lista Movimenti'!$D:$D, "<=31/12/2026") -> 25 | D17: 15
B18: 🚌 Trasporti | C18: =SUMIFS('Lista Movimenti'!$C:$C, 'Lista Movimenti'!$B:$B, $B18, 'Lista Movimenti'!$E:$E, "Spesa", 'Lista Movimenti'!$D:$D, ">=01/12/2026", 'Lista Movimenti'!$D:$D, "<=31/12/2026") -> 0 | D18: 45
B19: 👕 Vestiti | C19: =SUMIFS('Lista Movimenti'!$C:$C, 'Lista Movimenti'!$B:$B, $B19, 'Lista Movimenti'!$E:$E, "Spesa", 'Lista Movimenti'!$D:$D, ">=01/12/2026", 'Lista Movimenti'!$D:$D, "<=31/12/2026") -> 110 | D19: 35
A20: Totale Necessità | B20: -- Necessità -- | C20: =SUM(C13:C19) -> 180 | D20: =SUM(D13:D19) -> 665
A22: EXTRA | B22: -- Extra -- | C22: Totale | D22: Obiettivo
B23: 🎫 Abbonamenti | C23: =SUMIFS('Lista Movimenti'!$C:$C, 'Lista Movimenti'!$B:$B, $B23, 'Lista Movimenti'!$E:$E, "Spesa", 'Lista Movimenti'!$D:$D, ">=01/12/2026", 'Lista Movimenti'!$D:$D, "<=31/12/2026") -> 0 | D23: 22
B24: 🍔 Cibo fuori | C24: =SUMIFS('Lista Movimenti'!$C:$C, 'Lista Movimenti'!$B:$B, $B24, 'Lista Movimenti'!$E:$E, "Spesa", 'Lista Movimenti'!$D:$D, ">=01/12/2026", 'Lista Movimenti'!$D:$D, "<=31/12/2026") -> 120 | D24: 85
B25: 🎬 Intrattenimento | C25: =SUMIFS('Lista Movimenti'!$C:$C, 'Lista Movimenti'!$B:$B, $B25, 'Lista Movimenti'!$E:$E, "Spesa", 'Lista Movimenti'!$D:$D, ">=01/12/2026", 'Lista Movimenti'!$D:$D, "<=31/12/2026") -> 0 | D25: 24
B26: 🎁 Regali | C26: =SUMIFS('Lista Movimenti'!$C:$C, 'Lista Movimenti'!$B:$B, $B26, 'Lista Movimenti'!$E:$E, "Spesa", 'Lista Movimenti'!$D:$D, ">=01/12/2026", 'Lista Movimenti'!$D:$D, "<=31/12/2026") -> 0 | D26: 20
B27: ✈️ Viaggi/Vacanze | C27: =SUMIFS('Lista Movimenti'!$C:$C, 'Lista Movimenti'!$B:$B, $B27, 'Lista Movimenti'!$E:$E, "Spesa", 'Lista Movimenti'!$D:$D, ">=01/12/2026", 'Lista Movimenti'!$D:$D, "<=31/12/2026") -> 0 | D27: 60
B28: 📚 Cultura | C28: =SUMIFS('Lista Movimenti'!$C:$C, 'Lista Movimenti'!$B:$B, $B28, 'Lista Movimenti'!$E:$E, "Spesa", 'Lista Movimenti'!$D:$D, ">=01/12/2026", 'Lista Movimenti'!$D:$D, "<=31/12/2026") -> 0 | D28: 40
B29: 💅 Cura personale | C29: =SUMIFS('Lista Movimenti'!$C:$C, 'Lista Movimenti'!$B:$B, $B29, 'Lista Movimenti'!$E:$E, "Spesa", 'Lista Movimenti'!$D:$D, ">=01/12/2026", 'Lista Movimenti'!$D:$D, "<=31/12/2026") -> 0 | D29: 95
B30: 🌟 Altro extra | C30: =SUMIFS('Lista Movimenti'!$C:$C, 'Lista Movimenti'!$B:$B, $B30, 'Lista Movimenti'!$E:$E, "Spesa", 'Lista Movimenti'!$D:$D, ">=01/12/2026", 'Lista Movimenti'!$D:$D, "<=31/12/2026") -> 0 | D30: 13
A31: Totale Extra | B31: -- Extra -- | C31: =SUM(C23:C30) -> 120 | D31: =SUM(D23:D30) -> 359
A33: Totale Uscite | C33: =(C31 + C20) -> 300 | D33: =(D31 + D20) -> 1024
A34: Differenza Entrate Uscite | C34: =(B8-C33) -> 1150
A37: Categoria | B37: Totale | C37: Obiettivo
A38: 🏠 Casa | B38: =SUMIFS('Lista Movimenti'!$C:$C, 'Lista Movimenti'!$B:$B, $A38, 'Lista Movimenti'!$E:$E, "Risparmio", 'Lista Movimenti'!$D:$D, ">=01/12/2026", 'Lista Movimenti'!$D:$D, "<=31/12/2026") -> 250
A39: 🍲 Cibo/Spesa | B39: =SUMIFS('Lista Movimenti'!$C:$C, 'Lista Movimenti'!$B:$B, $A39, 'Lista Movimenti'!$E:$E, "Risparmio", 'Lista Movimenti'!$D:$D, ">=01/12/2026", 'Lista Movimenti'!$D:$D, "<=31/12/2026") -> 0
A40: 🚑 Sanità | B40: =SUMIFS('Lista Movimenti'!$C:$C, 'Lista Movimenti'!$B:$B, $A40, 'Lista Movimenti'!$E:$E, "Risparmio", 'Lista Movimenti'!$D:$D, ">=01/12/2026", 'Lista Movimenti'!$D:$D, "<=31/12/2026") -> 0
A41: 🏋️ Palestra e affini | B41: =SUMIFS('Lista Movimenti'!$C:$C, 'Lista Movimenti'!$B:$B, $A41, 'Lista Movimenti'!$E:$E, "Risparmio", 'Lista Movimenti'!$D:$D, ">=01/12/2026", 'Lista Movimenti'!$D:$D, "<=31/12/2026") -> 0
A42: 📱 Telefono | B42: =SUMIFS('Lista Movimenti'!$C:$C, 'Lista Movimenti'!$B:$B, $A42, 'Lista Movimenti'!$E:$E, "Risparmio", 'Lista Movimenti'!$D:$D, ">=01/12/2026", 'Lista Movimenti'!$D:$D, "<=31/12/2026") -> 0
A43: 🚌 Trasporti | B43: =SUMIFS('Lista Movimenti'!$C:$C, 'Lista Movimenti'!$B:$B, $A43, 'Lista Movimenti'!$E:$E, "Risparmio", 'Lista Movimenti'!$D:$D, ">=01/12/2026", 'Lista Movimenti'!$D:$D, "<=31/12/2026") -> 0
A44: 👕 Vestiti | B44: =SUMIFS('Lista Movimenti'!$C:$C, 'Lista Movimenti'!$B:$B, $A44, 'Lista Movimenti'!$E:$E, "Risparmio", 'Lista Movimenti'!$D:$D, ">=01/12/2026", 'Lista Movimenti'!$D:$D, "<=31/12/2026") -> 0
A45: 🎫 Abbonamenti | B45: =SUMIFS('Lista Movimenti'!$C:$C, 'Lista Movimenti'!$B:$B, $A45, 'Lista Movimenti'!$E:$E, "Risparmio", 'Lista Movimenti'!$D:$D, ">=01/12/2026", 'Lista Movimenti'!$D:$D, "<=31/12/2026") -> 0
A46: 🍔 Cibo fuori | B46: =SUMIFS('Lista Movimenti'!$C:$C, 'Lista Movimenti'!$B:$B, $A46, 'Lista Movimenti'!$E:$E, "Risparmio", 'Lista Movimenti'!$D:$D, ">=01/12/2026", 'Lista Movimenti'!$D:$D, "<=31/12/2026") -> 0
A47: 🎬 Intrattenimento | B47: =SUMIFS('Lista Movimenti'!$C:$C, 'Lista Movimenti'!$B:$B, $A47, 'Lista Movimenti'!$E:$E, "Risparmio", 'Lista Movimenti'!$D:$D, ">=01/12/2026", 'Lista Movimenti'!$D:$D, "<=31/12/2026") -> 0
A48: 🎁 Regali | B48: =SUMIFS('Lista Movimenti'!$C:$C, 'Lista Movimenti'!$B:$B, $A48, 'Lista Movimenti'!$E:$E, "Risparmio", 'Lista Movimenti'!$D:$D, ">=01/12/2026", 'Lista Movimenti'!$D:$D, "<=31/12/2026") -> 0
A49: ✈️ Viaggi/Vacanze | B49: =SUMIFS('Lista Movimenti'!$C:$C, 'Lista Movimenti'!$B:$B, $A49, 'Lista Movimenti'!$E:$E, "Risparmio", 'Lista Movimenti'!$D:$D, ">=01/12/2026", 'Lista Movimenti'!$D:$D, "<=31/12/2026") -> 0
... A54: 🪙 Altre entrate | B54: =SUMIFS('Lista Movimenti'!$C:$C, 'Lista Movimenti'!$B:$B, $A54, 'Lista Movimenti'!$E:$E, "Risparmio", 'Lista Movimenti'!$D:$D, ">=01/12/2026", 'Lista Movimenti'!$D:$D, "<=31/12/2026") -> 0
A55: Totale Risparmi | B55: =SUM(Risparmi_Dic[Totale]) -> 250 | C55: =SUM(Risparmi_Dic[Obiettivo]) -> 0 | S55: 0

Sheet Sinking Funds
A1: Attività | B1: Stato | C1: Obiettivo | D1: Risparmio Mensile | E1: Risparmiato Precedentemente | F1: Spese | G1: Saldo Attuale | H1: Saldo Mancante | I1: Data di inizio | J1: Note | K1: Data di Scadenza
A2: ✈️ Viaggi/Vacanze | B2: In corso | C2: 1000 | D2: =MAX(0, H2 / MAX(1, (YEAR(K2)*12 + MONTH(K2)) - (YEAR(TODAY())*12 + MONTH(TODAY())) + 1)) -> 356.66667 | E2: 150 | F2: =SUMIFS('Lista Movimenti'!$C:$C, 'Lista Movimenti'!$B:$B, $A2, 'Lista Movimenti'!$E:$E, "Spesa") -> 920 | G2: =E2 + SUMIFS('Lista Movimenti'!$C:$C, 'Lista Movimenti'!$B:$B, $A2, 'Lista Movimenti'!$E:$E, "Risparmio")-F2 -> -70 | H2: =(C2-G2) -> 1070 | I2: 46023 | K2: 46226
A3: 🏠 Casa | B3: In corso | C3: 2000 | D3: =MAX(0, H3 / MAX(1, (YEAR(K3)*12 + MONTH(K3)) - (YEAR(TODAY())*12 + MONTH(TODAY())) + 1)) -> 316.28571 | E3: 0 | F3: =SUMIFS('Lista Movimenti'!$C:$C, 'Lista Movimenti'!$B:$B, $A3, 'Lista Movimenti'!$E:$E, "Spesa") -> 1609 | G3: =E3 + SUMIFS('Lista Movimenti'!$C:$C, 'Lista Movimenti'!$B:$B, $A3, 'Lista Movimenti'!$E:$E, "Risparmio")-F3 -> -214 | H3: =(C3-G3) -> 2214 | K3: 46341
A4: 🏋️ Palestra e affini | B4: In corso | C4: 250 | D4: =MAX(0, H4 / MAX(1, (YEAR(K4)*12 + MONTH(K4)) - (YEAR(TODAY())*12 + MONTH(TODAY())) + 1)) -> 0 | F4: =SUMIFS('Lista Movimenti'!$C:$C, 'Lista Movimenti'!$B:$B, $A4, 'Lista Movimenti'!$E:$E, "Spesa") -> 129 | G4: =E4 + SUMIFS('Lista Movimenti'!$C:$C, 'Lista Movimenti'!$B:$B, $A4, 'Lista Movimenti'!$E:$E, "Risparmio")-F4 -> 1371 | H4: =(C4-G4) -> -1121 | K4: 46371
A5: 🎁 Regali | B5: Completata | C5: 100 | D5: =MAX(0, H5 / MAX(1, (YEAR(K5)*12 + MONTH(K5)) - (YEAR(TODAY())*12 + MONTH(TODAY())) + 1)) -> 18.75 | F5: =SUMIFS('Lista Movimenti'!$C:$C, 'Lista Movimenti'!$B:$B, $A5, 'Lista Movimenti'!$E:$E, "Spesa") -> 250 | G5: =E5 + SUMIFS('Lista Movimenti'!$C:$C, 'Lista Movimenti'!$B:$B, $A5, 'Lista Movimenti'!$E:$E, "Risparmio")-F5 -> 25 | H5: =(C5-G5) -> 75 | K5: 46242
D6: =MAX(0, H6 / MAX(1, (YEAR(K6)*12 + MONTH(K6)) - (YEAR(TODAY())*12 + MONTH(TODAY())) + 1)) -> 0 | F6: =SUMIFS('Lista Movimenti'!$C:$C, 'Lista Movimenti'!$B:$B, $A6, 'Lista Movimenti'!$E:$E, "Spesa") -> 0 | G6: =E6 + SUMIFS('Lista Movimenti'!$C:$C, 'Lista Movimenti'!$B:$B, $A6, 'Lista Movimenti'!$E:$E, "Risparmio")-F6 -> 0 | H6: =(C6-G6) -> 0
D7: =MAX(0, H7 / MAX(1, (YEAR(K7)*12 + MONTH(K7)) - (YEAR(TODAY())*12 + MONTH(TODAY())) + 1)) -> 0 | F7: =SUMIFS('Lista Movimenti'!$C:$C, 'Lista Movimenti'!$B:$B, $A7, 'Lista Movimenti'!$E:$E, "Spesa") -> 0 | G7: =E7 + SUMIFS('Lista Movimenti'!$C:$C, 'Lista Movimenti'!$B:$B, $A7, 'Lista Movimenti'!$E:$E, "Risparmio")-F7 -> 0 | H7: =(C7-G7) -> 0
D8: =MAX(0, H8 / MAX(1, (YEAR(K8)*12 + MONTH(K8)) - (YEAR(TODAY())*12 + MONTH(TODAY())) + 1)) -> 0 | F8: =SUMIFS('Lista Movimenti'!$C:$C, 'Lista Movimenti'!$B:$B, $A8, 'Lista Movimenti'!$E:$E, "Spesa") -> 0 | G8: =E8 + SUMIFS('Lista Movimenti'!$C:$C, 'Lista Movimenti'!$B:$B, $A8, 'Lista Movimenti'!$E:$E, "Risparmio")-F8 -> 0 | H8: =(C8-G8) -> 0
D9: =MAX(0, H9 / MAX(1, (YEAR(K9)*12 + MONTH(K9)) - (YEAR(TODAY())*12 + MONTH(TODAY())) + 1)) -> 0 | F9: =SUMIFS('Lista Movimenti'!$C:$C, 'Lista Movimenti'!$B:$B, $A9, 'Lista Movimenti'!$E:$E, "Spesa") -> 0 | G9: =E9 + SUMIFS('Lista Movimenti'!$C:$C, 'Lista Movimenti'!$B:$B, $A9, 'Lista Movimenti'!$E:$E, "Risparmio")-F9 -> 0 | H9: =(C9-G9) -> 0
D10: =MAX(0, H10 / MAX(1, (YEAR(K10)*12 + MONTH(K10)) - (YEAR(TODAY())*12 + MONTH(TODAY())) + 1)) -> 0 | F10: =SUMIFS('Lista Movimenti'!$C:$C, 'Lista Movimenti'!$B:$B, $A10, 'Lista Movimenti'!$E:$E, "Spesa") -> 0 | G10: =E10 + SUMIFS('Lista Movimenti'!$C:$C, 'Lista Movimenti'!$B:$B, $A10, 'Lista Movimenti'!$E:$E, "Risparmio")-F10 -> 0 | H10: =(C10-G10) -> 0
D11: =MAX(0, H11 / MAX(1, (YEAR(K11)*12 + MONTH(K11)) - (YEAR(TODAY())*12 + MONTH(TODAY())) + 1)) -> 0 | F11: =SUMIFS('Lista Movimenti'!$C:$C, 'Lista Movimenti'!$B:$B, $A11, 'Lista Movimenti'!$E:$E, "Spesa") -> 0 | G11: =E11 + SUMIFS('Lista Movimenti'!$C:$C, 'Lista Movimenti'!$B:$B, $A11, 'Lista Movimenti'!$E:$E, "Risparmio")-F11 -> 0 | H11: =(C11-G11) -> 0
D12: =MAX(0, H12 / MAX(1, (YEAR(K12)*12 + MONTH(K12)) - (YEAR(TODAY())*12 + MONTH(TODAY())) + 1)) -> 0 | F12: =SUMIFS('Lista Movimenti'!$C:$C, 'Lista Movimenti'!$B:$B, $A12, 'Lista Movimenti'!$E:$E, "Spesa") -> 0 | G12: =E12 + SUMIFS('Lista Movimenti'!$C:$C, 'Lista Movimenti'!$B:$B, $A12, 'Lista Movimenti'!$E:$E, "Risparmio")-F12 -> 0 | H12: =(C12-G12) -> 0
D13: =MAX(0, H13 / MAX(1, (YEAR(K13)*12 + MONTH(K13)) - (YEAR(TODAY())*12 + MONTH(TODAY())) + 1)) -> 0 | F13: =SUMIFS('Lista Movimenti'!$C:$C, 'Lista Movimenti'!$B:$B, $A13, 'Lista Movimenti'!$E:$E, "Spesa") -> 0 | G13: =E13 + SUMIFS('Lista Movimenti'!$C:$C, 'Lista Movimenti'!$B:$B, $A13, 'Lista Movimenti'!$E:$E, "Risparmio")-F13 -> 0 | H13: =(C13-G13) -> 0
D14: =MAX(0, H14 / MAX(1, (YEAR(K14)*12 + MONTH(K14)) - (YEAR(TODAY())*12 + MONTH(TODAY())) + 1)) -> 0 | F14: =SUMIFS('Lista Movimenti'!$C:$C, 'Lista Movimenti'!$B:$B, $A14, 'Lista Movimenti'!$E:$E, "Spesa") -> 0 | G14: =E14 + SUMIFS('Lista Movimenti'!$C:$C, 'Lista Movimenti'!$B:$B, $A14, 'Lista Movimenti'!$E:$E, "Risparmio")-F14 -> 0 | H14: =(C14-G14) -> 0
D15: =MAX(0, H15 / MAX(1, (YEAR(K15)*12 + MONTH(K15)) - (YEAR(TODAY())*12 + MONTH(TODAY())) + 1)) -> 0 | F15: =SUMIFS('Lista Movimenti'!$C:$C, 'Lista Movimenti'!$B:$B, $A15, 'Lista Movimenti'!$E:$E, "Spesa") -> 0 | G15: =E15 + SUMIFS('Lista Movimenti'!$C:$C, 'Lista Movimenti'!$B:$B, $A15, 'Lista Movimenti'!$E:$E, "Risparmio")-F15 -> 0 | H15: =(C15-G15) -> 0
A18: Obiettivo Totale | B18: Totale Saldo Attuale | C18: Totale Saldo Mancante | D18: % Completamento Obiettivi | E18: % Mancante Obiettivi | F18: Risparmio Mensile Totale
A19: =SUM(C2:C15) -> 3350 | B19: =SUM(G2:G15) -> 1112 | C19: =(A19-B19) -> 2238 | D19: =(B19/A19) -> 0.3319403 | E19: =(1-D19) -> 0.6680597 | F19: =SUM(D2:D15) -> 691.70238

Sheet Investimenti
A1: Asset/Strumento | B1: Categoria | C1: Quantità Posseduta | D1: PMC | E1: Ticker | F1: Prezzo Attuale | G1: Valore Iniziale | H1: Valore Attuale | I1: Profitto/Perdita
A2: Fondo Pensione | B2: Fondo | F2: =IFERROR(__xludf.DUMMYFUNCTION("IF(B2=""Azioni"", GOOGLEFINANCE(E2), """")"),"") | H2: =SUMPRODUCT((Investimenti!B2="Azioni") * (Investimenti!C2) * (Investimenti!F2)) -> 0 | I2: =(H2-G2) -> 0
A3: Azioni Tesla | B3: Azioni | C3: 12 | D3: 876 | E3: NASDAQ:TSLA | F3: =IFERROR(__xludf.DUMMYFUNCTION("IF(B3=""Azioni"", GOOGLEFINANCE(E3), """")"),435.79) -> 435.79 | G3: =SUMPRODUCT((Investimenti!B2:B100="Azioni") * (Investimenti!C2:C100) * (Investimenti!D2:D100)) -> 10512 | H3: =SUMPRODUCT((Investimenti!B3="Azioni") * (Investimenti!C3) * (Investimenti!F3)) -> 5229.48 | I3: =(H3-G3) -> -5282.52
A4: Assicurazioni Unipol | B4: Assicurazioni | F4: =IFERROR(__xludf.DUMMYFUNCTION("IF(B4=""Azioni"", GOOGLEFINANCE(E4), """")"),"") | H4: =SUMPRODUCT((Investimenti!B4="Azioni") * (Investimenti!C4) * (Investimenti!F4)) -> 0 | I4: =(H4-G4) -> 0
F5: =IFERROR(__xludf.DUMMYFUNCTION("IF(B5=""Azioni"", GOOGLEFINANCE(E5), """")"),"") | H5: =SUMPRODUCT((Investimenti!B5="Azioni") * (Investimenti!C5) * (Investimenti!F5)) -> 0 | I5: =(H5-G5) -> 0
F6: =IFERROR(__xludf.DUMMYFUNCTION("IF(B6=""Azioni"", GOOGLEFINANCE(E6), """")"),"") | H6: =SUMPRODUCT((Investimenti!B6="Azioni") * (Investimenti!C6) * (Investimenti!F6)) -> 0 | I6: =(H6-G6) -> 0
F7: =IFERROR(__xludf.DUMMYFUNCTION("IF(B7=""Azioni"", GOOGLEFINANCE(E7), """")"),"") | H7: =SUMPRODUCT((Investimenti!B7="Azioni") * (Investimenti!C7) * (Investimenti!F7)) -> 0 | I7: =(H7-G7) -> 0
F8: =IFERROR(__xludf.DUMMYFUNCTION("IF(B8=""Azioni"", GOOGLEFINANCE(E8), """")"),"") | H8: =SUMPRODUCT((Investimenti!B8="Azioni") * (Investimenti!C8) * (Investimenti!F8)) -> 0 | I8: =(H8-G8) -> 0
F9: =IFERROR(__xludf.DUMMYFUNCTION("IF(B9=""Azioni"", GOOGLEFINANCE(E9), """")"),"") | H9: =SUMPRODUCT((Investimenti!B9="Azioni") * (Investimenti!C9) * (Investimenti!F9)) -> 0 | I9: =(H9-G9) -> 0
F10: =IFERROR(__xludf.DUMMYFUNCTION("IF(B10=""Azioni"", GOOGLEFINANCE(E10), """")"),"") | H10: =SUMPRODUCT((Investimenti!B10="Azioni") * (Investimenti!C10) * (Investimenti!F10)) -> 0 | I10: =(H10-G10) -> 0
F11: =IFERROR(__xludf.DUMMYFUNCTION("IF(B11=""Azioni"", GOOGLEFINANCE(E11), """")"),"") | H11: =SUMPRODUCT((Investimenti!B11="Azioni") * (Investimenti!C11) * (Investimenti!F11)) -> 0 | I11: =(H11-G11) -> 0
F12: =IFERROR(__xludf.DUMMYFUNCTION("IF(B12=""Azioni"", GOOGLEFINANCE(E12), """")"),"") | H12: =SUMPRODUCT((Investimenti!B12="Azioni") * (Investimenti!C12) * (Investimenti!F12)) -> 0 | I12: =(H12-G12) -> 0
F13: =IFERROR(__xludf.DUMMYFUNCTION("IF(B13=""Azioni"", GOOGLEFINANCE(E13), """")"),"") | H13: =SUMPRODUCT((Investimenti!B13="Azioni") * (Investimenti!C13) * (Investimenti!F13)) -> 0 | I13: =(H13-G13) -> 0
F14: =IFERROR(__xludf.DUMMYFUNCTION("IF(B14=""Azioni"", GOOGLEFINANCE(E14), """")"),"") | H14: =SUMPRODUCT((Investimenti!B14="Azioni") * (Investimenti!C14) * (Investimenti!F14)) -> 0 | I14: =(H14-G14) -> 0
F15: =IFERROR(__xludf.DUMMYFUNCTION("IF(B15=""Azioni"", GOOGLEFINANCE(E15), """")"),"") | H15: =SUMPRODUCT((Investimenti!B15="Azioni") * (Investimenti!C15) * (Investimenti!F15)) -> 0 | I15: =(H15-G15) -> 0
F16: =IFERROR(__xludf.DUMMYFUNCTION("IF(B16=""Azioni"", GOOGLEFINANCE(E16), """")"),"") | H16: =SUMPRODUCT((Investimenti!B16="Azioni") * (Investimenti!C16) * (Investimenti!F16)) -> 0 | I16: =(H16-G16) -> 0
F17: =IFERROR(__xludf.DUMMYFUNCTION("IF(B17=""Azioni"", GOOGLEFINANCE(E17), """")"),"") | H17: =SUMPRODUCT((Investimenti!B17="Azioni") * (Investimenti!C17) * (Investimenti!F17)) -> 0 | I17: =(H17-G17) -> 0
F18: =IFERROR(__xludf.DUMMYFUNCTION("IF(B18=""Azioni"", GOOGLEFINANCE(E18), """")"),"") | H18: =SUMPRODUCT((Investimenti!B18="Azioni") * (Investimenti!C18) * (Investimenti!F18)) -> 0 | I18: =(H18-G18) -> 0
F19: =IFERROR(__xludf.DUMMYFUNCTION("IF(B19=""Azioni"", GOOGLEFINANCE(E19), """")"),"") | H19: =SUMPRODUCT((Investimenti!B19="Azioni") * (Investimenti!C19) * (Investimenti!F19)) -> 0 | I19: =(H19-G19) -> 0
F20: =IFERROR(__xludf.DUMMYFUNCTION("IF(B20=""Azioni"", GOOGLEFINANCE(E20), """")"),"") | H20: =SUMPRODUCT((Investimenti!B20="Azioni") * (Investimenti!C20) * (Investimenti!F20)) -> 0 | I20: =(H20-G20) -> 0
F21: =IFERROR(__xludf.DUMMYFUNCTION("IF(B21=""Azioni"", GOOGLEFINANCE(E21), """")"),"") | H21: =SUMPRODUCT((Investimenti!B21="Azioni") * (Investimenti!C21) * (Investimenti!F21)) -> 0 | I21: =(H21-G21) -> 0
F22: =IFERROR(__xludf.DUMMYFUNCTION("IF(B22=""Azioni"", GOOGLEFINANCE(E22), """")"),"") | H22: =SUMPRODUCT((Investimenti!B22="Azioni") * (Investimenti!C22) * (Investimenti!F22)) -> 0 | I22: =(H22-G22) -> 0
F23: =IFERROR(__xludf.DUMMYFUNCTION("IF(B23=""Azioni"", GOOGLEFINANCE(E23), """")"),"") | H23: =SUMPRODUCT((Investimenti!B23="Azioni") * (Investimenti!C23) * (Investimenti!F23)) -> 0 | I23: =(H23-G23) -> 0
F24: =IFERROR(__xludf.DUMMYFUNCTION("IF(B24=""Azioni"", GOOGLEFINANCE(E24), """")"),"") | H24: =SUMPRODUCT((Investimenti!B24="Azioni") * (Investimenti!C24) * (Investimenti!F24)) -> 0 | I24: =(H24-G24) -> 0
F25: =IFERROR(__xludf.DUMMYFUNCTION("IF(B25=""Azioni"", GOOGLEFINANCE(E25), """")"),"") | H25: =SUMPRODUCT((Investimenti!B25="Azioni") * (Investimenti!C25) * (Investimenti!F25)) -> 0 | I25: =(H25-G25) -> 0
A26: TOTALI | B26: 0 | G26: =SUM(INVESTIMENTI[Valore Iniziale]) -> 10512 | H26: =SUM(INVESTIMENTI[Valore Attuale]) -> 5229.48 | I26: =SUM(INVESTIMENTI[Profitto/Perdita]) -> -5282.52

Sheet Debiti
A1: Attività | B1: Categorie | C1: Valore Debito | D1: Rata Mensile | E1: Totale Pagato | F1: Totale Mancante | G1: Data Inizio | H1: Data Scadenza
A2: Mutuo Casa | B2: Mutuo | C2: 150000 | D2: =IF(ISBLANK(H2), "", F2 / DATEDIF(G2, H2, "M")) -> 439.83402 | E2: 44000 | F2: =(C2-E2) -> 106000 | G2: 46027 | H2: 53368
D3: =IF(ISBLANK(H3), "", F3 / DATEDIF(G3, H3, "M")) | F3: =(C3-E3) -> 0
D4: =IF(ISBLANK(H4), "", F4 / DATEDIF(G4, H4, "M")) | F4: =(C4-E4) -> 0
D5: =IF(ISBLANK(H5), "", F5 / DATEDIF(G5, H5, "M")) | F5: =(C5-E5) -> 0
D6: =IF(ISBLANK(H6), "", F6 / DATEDIF(G6, H6, "M")) | F6: =(C6-E6) -> 0
D7: =IF(ISBLANK(H7), "", F7 / DATEDIF(G7, H7, "M")) | F7: =(C7-E7) -> 0
D8: =IF(ISBLANK(H8), "", F8 / DATEDIF(G8, H8, "M")) | F8: =(C8-E8) -> 0
D9: =IF(ISBLANK(H9), "", F9 / DATEDIF(G9, H9, "M")) | F9: =(C9-E9) -> 0
D10: =IF(ISBLANK(H10), "", F10 / DATEDIF(G10, H10, "M")) | F10: =(C10-E10) -> 0
D11: =IF(ISBLANK(H11), "", F11 / DATEDIF(G11, H11, "M")) | F11: =(C11-E11) -> 0
D12: =IF(ISBLANK(H12), "", F12 / DATEDIF(G12, H12, "M")) | F12: =(C12-E12) -> 0
D13: =IF(ISBLANK(H13), "", F13 / DATEDIF(G13, H13, "M")) | F13: =(C13-E13) -> 0
D14: =IF(ISBLANK(H14), "", F14 / DATEDIF(G14, H14, "M")) | F14: =(C14-E14) -> 0
D15: =IF(ISBLANK(H15), "", F15 / DATEDIF(G15, H15, "M")) | F15: =(C15-E15) -> 0
A16: TOTALI | C16: =SUM(Debiti[Valore Debito]) -> 150000 | D16: =SUM(Debiti[Rata Mensile]) -> 439.83402 | E16: =SUM(Debiti[Totale Pagato]) -> 44000 | F16: =SUM(Debiti[Totale Mancante]) -> 106000

Sheet Net Worth
A1: Data Attuale | B1: Liquidità | C1: Sinking Funds | D1: Investimenti | E1: Debiti | F1: Totale Net Worth
A2: OGGI | B2: 2000 | C2: =(Riepilogo_Sinking_Funds[Totale Saldo Attuale]) -> 1112 | D2: =SUM(INVESTIMENTI[Valore Attuale]) -> 5229.48 | E2: =SUM(Debiti[Totale Mancante]) -> 106000 | F2: =B2+C2+D2-E2 -> -97658.52
A8: Data Attuale | B8: Liquidità | C8: Sinking Funds | D8: Investimenti | E8: Debiti | F8: Totale Net Worth
A9: INIZIO ANNO | B9: 1400 | C9: 700 | D9: 4500 | E9: 112000 | F9: =B9+C9+D9-E9 -> -105400

Sheet Modifiche
A1: -- Necessità -- | C1: Per modificare/aggiungere categorie è necessario modificare l'elenco a sinistra | I1: MODIFICHE
A2: 🏠 Casa | I2: Se ti serve scrivere delle modifiche da fare o cose che vorresti aggiungere scrivile pure in questo foglio
A3: 🍲 Cibo/Spesa
A4: 🚑 Sanità
A5: 🏋️ Palestra e affini
A6: 📱 Telefono
A7: 🚌 Trasporti
A8: 👕 Vestiti
A9: -- Extra --
A10: 🎫 Abbonamenti
A11: 🍔 Cibo fuori
A12: 🎬 Intrattenimento
A13: 🎁 Regali
A14: ✈️ Viaggi/Vacanze
... A20: 🪙 Altre entrate
